Workbook

Sheet Master
A1: Activate/Deactivate | B1: Count | C1: Column1 | D1: Object_Type | E1: Old F or T # | F1: Indicator Name | G1: Object ID | H1: Figure ID | I1: Our Data Source | J1: Table # | K1: Primary Data Source | L1: County Assigned
A2: Activate | B2: 1 | D2: Table | E2: T1 | F2: Population Demographic Characteristics, 2023 | G2: tbl-population-demographics | I2: US Census ACS 5-Year | J2: Table S0101 | L2: Orange
A3: Activate | B3: 2 | D3: Table | E3: T2 | F3: Population by Sex, 2023 | G3: tbl-sex | I3: US Census ACS 5-Year | J3: Table S0101 | L3: Orange
A4: Activate | B4: 3 | D4: Table | E4: T3 | F4: Population by Age, 2023 | G4: tbl-age | I4: US Census ACS 5-Year | J4: Table S0101 | L4: Orange
A5: Activate | B5: 4 | D5: Table | E5: T4 | F5: Population by Ethnicity, 2023 | G5: tbl-ethnicity | I5: US Census ACS 5-Year | J5: Table B03002 | L5: Orange
A6: Activate | B6: 5 | D6: Table | E6: T5 | F6: Population by Race, 2023 | G6: tbl-race | I6: US Census ACS 5-Year | J6: Table B03002 | L6: Orange
A7: Activate | B7: 6 | D7: Table | E7: T6 | F7: Population by Spoken Language, 2023 | G7: tbl-language | I7: US Census ACS 5-Year | J7: Table S1601 | L7: Orange
A8: Activate | B8: 7 | D8: Table | E8: T7 | F8: Population 25 Years and Older, 2023 | G8: tbl-pop-25 | I8: US Census ACS 5-Year | J8: Table S1501 | L8: Orange
A9: Activate | B9: 8 | D9: Table | E9: T8 | F9: Population by Educational Attainment, 2023 | G9: tbl-education-base | I9: US Census ACS 5-Year | J9: Table S1501 | L9: Orange
A10: Activate | B10: 9 | D10: Table | E10: T9 | F10: Total Households, 2023 | G10: tbl-households | I10: US Census ACS 5-Year | J10: Table S1901 | L10: Orange
A11: Activate | B11: 10 | D11: Table | E11: T10 | F11: Households by Income, 2023 | G11: tbl-income | I11: US Census ACS 5-Year | J11: Table S1901 | L11: Orange
A12: Activate | B12: 11 | D12: Table | E12: T11 | F12: Population by Veteran Status, 2023 | G12: tbl-veteran | I12: US Census ACS 5-Year | J12: Table S2101 | L12: Orange
A13: Activate | B13: 12 | D13: Table | E13: T12 | F13: Percentage of Population by Type of Disability, 2023 | G13: tbl-disability | I13: US Census ACS 5-Year | J13: Table S1810 | L13: Orange
A14: Activate | B14: 13 | D14: Figure | E14: F1 | F14: Percentage in Labor Force, Population 16 Years and Older, 2021–2023 | G14: tbl-labor-force | H14: fig-labor-force | I14: US Census ACS 5-Year | J14: Table DP03 | L14: Orange
A15: Activate | B15: 14 | D15: Figure | E15: F2 | F15: Percentage of Population Unemployed, 16 Years and Older, 2021-2023 | G15: tbl-unemployed | H15: fig-unemployed | I15: US Census ACS 5-Year | J15: Table DP03 | L15: Orange
A16: Activate | B16: 15 | D16: Figure | E16: F3 | F16: Percentage of Overall Food Insecurity, 2020–2023 | G16: tbl-food-insecurity | H16: fig-food-insecurity | I16: Feeding America | L16: Orange
A17: Activate | B17: 16 | D17: Figure | E17: F4 | F17: Percentage of Food Insecurity, Children 18 Years and Younger, 2020–2023 | G17: tbl-childhood-food-insecurity | H17: fig-childhood-food-insecurity | I17: Feeding America | L17: Orange
A18: Activate | B18: 17 | D18: Figure | E18: F5 | F18: Percentage of Cost Burdened Renter Occupied Units, 2021–2023 | G18: tbl-cost-burdened-renters | H18: fig-cost-burdened-renters | I18: US Census ACS 5-Year | J18: Table DP04 | L18: Orange
A19: Activate | B19: 18 | D19: Figure | E19: F6 | F19: Percentage of Severely Cost Burdened Households, 2016–2023 | G19: tbl-severely-cost-burdened | H19: fig-severely-cost-burdened | I19: County Health Rankings and Roadmaps | K19: US Census ACS 5-Year | L19: Orange
A20: Activate | B20: 19 | D20: Table | E20: T13 | F20: Number of people living in HUD-Subsidized Housing in the Past 12 Months, 2021–2024 | G20: tbl-hud-housing | I20: US Department of Housing and Urban Development | L20: Orange
A21: Activate | B21: 20 | D21: Table | E21: T14 | F21: Poverty Threshold for 2024 by Size of Family and Number of Related Children 18 Years and Younger | G21: tbl-poverty-threshold | I21: US Census | L21: Orange
A22: Activate | B22: 21 | D22: Figure | E22: F7 | F22: Percentage of Population in Poverty, 2021–2023 | G22: tbl-poverty-rate | H22: fig-poverty-rate | I22: US Census ACS 5-Year | J22: Table S1701 | L22: Orange
A23: Activate | B23: 22 | D23: Figure | E23: F8 | F23: Percentage of Families below Poverty by Race and Ethnicity, 2018–2022 | G23: tbl-poverty-by-race | H23: fig-poverty-by-race | I23: NYS County Health Indicators by Race/Ethnicity (CHIRE) | K23: US Census SAIPE | L23: Orange
A24: Activate | B24: 23 | D24: Figure | E24: F9 | F24: Enrollment Rate of Economically Disadvantaged Students, 2021-2023 | G24: tbl-economically-disadvantaged | H24: fig-economically-disadvantaged | I24: NYS Education Department | L24: Orange
A25: Activate | B25: 24 | D25: Table | E25: T15 | F25: ALICE Household Survival Budget, New York State, 2023 | G25: tbl-alice-budget | I25: United for ALICE | L25: Orange
A26: Activate | B26: 25 | D26: Figure | E26: F10 | F26: ALICE Threshold Percentage, 2023 | G26: tbl-alice-threshold | H26: fig-alice-threshold | I26: United for ALICE | L26: Orange
A27: Activate | B27: 26 | D27: Figure | E27: F11 | F27: High School Graduation Rate, 2021-2023 | G27: tbl-graduation-rate | H27: fig-graduation-rate | I27: NYS Education Department | L27: Orange
A28: Activate | B28: 27 | D28: Figure | E28: F12 | F28: High School Graduation Rate, by Race and Ethnicity, 2023 | G28: tbl-graduation-by-race | H28: fig-graduation-by-race | I28: NYS Education Department | L28: Orange
A29: Activate | B29: 28 | D29: Figure | E29: F 13 | F29: Rate of Higher Education Attainment, 2023 | G29: tbl-educational-attainment | H29: fig-educational-attainment | I29: US Census ACS 5-Year | J29: Table S1501 | L29: Orange
A30: Activate | B30: 29 | D30: Figure | E30: F 14 | F30: Percentage of Population that Speaks English "Less Than Very Well", 5 Years and Older, 2021–2023 | G30: tbl-language-proficiency | H30: fig-language-proficiency | I30: US Census ACS 5-Year | J30: Table S1601 | L30: Orange
A31: Activate | B31: 30 | D31: Figure | E31: F15 | F31: Percentage of Disconnected Youth, 16–19 Years Old, 2014–2023 | G31: tbl-disconnected-youth | H31: fig-disconnected-youth | I31: County Health Rankings and Roadmaps | L31: Orange
A32: Activate | B32: 31 | D32: Figure | E32: F16 | F32: Index Score of Residential Segregation, 2013–2023 | G32: tbl-residential-segregation | H32: fig-residential-segregation | I32: County Health Rankings and Roadmaps | L32: Orange
A33: Activate | B33: 32 | D33: Figure | E33: F17 | F33: Percentage of Adults Who Did Not Receive Medical Care Due to Cost, 2016, 2018, and 2021 | G33: tbl-adult-medical-care-cost | H33: fig-medical-care-cost | I33: NYS Behavioral Risk Factor Surveillance System (BRFSS) | L33: Orange
A34: Activate | B34: 33 | D34: Figure | E34: F18 | F34: Percentage of Children Without Health Insurance, 2020–2023 | G34: tbl-children-uninsured | H34: fig-children-uninsured | I34: County Health Rankings and Roadmaps | L34: Orange
A35: Activate | B35: 34 | D35: Figure | E35: F19 | F35: Percentage of Adults with Health Insurance, 2020–2023 | G35: tbl-adult-health-insured | H35: fig-adult-health-insured | I35: US Census | L35: Orange
A36: Activate | B36: 35 | D36: Table | E36: T16 | F36: Medically Underserved Areas and Populations | G36: tbl-medically-underserved | I36: HRSA | J36: Data Warehouse | L36: Orange
A37: Activate | B37: 36 | E37: F20 | F37: Ratio of Residents to Primary Care Providers, 2019–2022 | G37: tbl-primary-care-providers | H37: fig-primary-care-providers | I37: County Health Rankings and Roadmaps | L37: Orange
A38: Activate | B38: 37 | E38: F21 | F38: Ratio of Residents to Dentists, 2019–2022 | G38: tbl-dentists | H38: fig-dentists | I38: County Health Rankings and Roadmaps | L38: Orange
A39: Activate | B39: 38 | E39: F22 | F39: Ratio of Residents to Mental Health Providers, 2021–2024 | G39: tbl-mental-health-providers | H39: fig-mental-health-providers | I39: County Health Rankings and Roadmaps | K39: National Provider Identification Registry, Center for Medicaid and Medicare Services | L39: Orange
A40: Activate | B40: 39 | E40: F23 | F40: Percentage of Adults Who Have a Regular Health Care Provider, 2016, 2018, and 2021 | G40: tbl-adult-access-primary-care | H40: fig-access-to-primary-care | I40: NYS Community Health Indicator Reports (CHIRS) | K40: NYS Behavioral Risk Factor Surveillance System (BRFSS) | L40: Orange
A41: Activate | B41: 40 | E41: F24 | F41: Potentially Preventable Hospitalizations, Age-Adjusted Rate per 10,000 Population, 2020–2022 | G41: tbl-pph | H41: fig-pph | I41: NYS County Health Indicators by Race/Ethnicity (CHIRE) | K41: NY Statewide Planning and Research Cooperative System | L41: Orange
A42: Activate | B42: 41 | E42: F25 | F42: Potentially Preventable Hospitalizations, Rate Difference Between Black Non-Hispanics and White Non-Hispanics, 2016–2022 | G42: tbl-pph-black-white-nh | H42: fig-pph-black-white-nh | I42: NYS Prevention Agenda Tracking Dashboard | K42: NY Statewide Planning and Research Cooperative System | L42: Orange
A43: Activate | B43: 42 | E43: F26 | F43: Potentially Preventable Hospitalizations, Rate Difference Between Hispanics and White Non-Hispanics, 2016–2022 | G43: tbl-pph-white-nh | H43: fig-pph-white-nh | I43: NYS Prevention Agenda Tracking Dashboard | K43: NY Statewide Planning and Research Cooperative System | L43: Orange
A44: Activate | B44: 43 | E44: F27 | F44: Index of Factors that Contribute to a Healthy Food Environment, 2018, 2019, and 2022 | G44: tbl-food-environment | H44: tbl-food-environment | I44: County Health Rankings and Roadmaps | K44: US Department of Agriculture | L44: Orange
A45: Activate | B45: 44 | E45: F28 | F45: Percentage of Population with Limited Access to Healthy Foods, 2015 and 2019 | G45: tbl-limited-healthy-foods | H45: fig-limited-healthy-foods | I45: County Health Rankings and Roadmaps | K45: US Department of Agriculture | L45: Orange
A46: Activate | B46: 45 | E46: F29 | F46: Violent Crimes, Rate per 100,000 Population, 2018–2021 | G46: tbl-violent-crime | H46: fig-violent-crime | I46: NYS Division of Criminal Justice Services | L46: Orange
A47: Activate | B47: 46 | E47: F30 | F47: Average Daily Density of Fine Particulate Matter, 2014, 2016, 2018, and 2020 | G47: tbl-density-matter | H47: fig-density-matter | I47: County Health Rankings and Roadmaps | K47: Environmental Public Health Tracking Network | L47: Orange
A48: Activate | B48: 47 | E48: F31 | F48: Percentage of Children Tested for Lead Before 36 Months of Age, 2013, 2016, 2017, and 2019 | G48: tbl-lead-children | H48: fig-lead-children | I48: NYS Community Health Indicator Reports (CHIRS) | K48: NYS Child Health Lead Poisoning Prevention Program | L48: Orange
A49: Activate | B49: 48 | E49: F32 | F49: Percentage of Households with Severe Housing Problems, 2017–2021 | G49: tbl-severe-housing | H49: fig-severe-housing | I49: County Health Rankings and Roadmaps | K49: US Census | L49: Orange
A50: Activate | B50: 49 | E50: F33 | F50: Percentage of Households with No Vehicles Available, 2021–2023 | G50: tbl-no-vehicles | H50: fig-no-vehicles | I50: US Census ACS 5-Year | J50: Table DP04 | K50: US Census | L50: Orange
A51: Activate | B51: 50 | E51: F34 | F51: Percentage of Workers by Mode of Transportation to Work, 2023 | G51: tbl-mode-to-work | H51: fig-mode-to-work | I51: US Census ACS 5-Year | J51: Table B08141 | K51: US Census | L51: Orange
A52: Activate | B52: 51 | E52: F35 | F52: Mean Travel Time to Work, 2021–2023 | G52: tbl-mean-time-work | H52: fig-mean-time-work | I52: US Census ACS 5-Year | J52: Table DP03 | K52: US Census | L52: Orange
A53: Activate | B53: 52 | E53: F36 | F53: Top Rated Issues That Affect Health in Dutchess County (n = 109) | G53: tbl-DC-affect-health | H53: fig-DC-affect-health | I53: Community Partner Survey | K53: Community Partner Survey | L53: Dutchess
A54: Activate | B54: 53 | E54: F37 | F54: Top Rated Barriers to Achieving Better Health in Dutchess County (n = 109) | G54: tbl-DC-achieve-health | H54: fig-DC-achieve-health | I54: Community Partner Survey | K54: Community Partner Survey | L54: Dutchess
A55: Activate | B55: 54 | E55: F38 | F55: The Impact of Health Issues in Dutchess County (n = 106) | G55: tbl-DC-impact-hlth-issue | H55: fig-DC-impact-hlth-issue | I55: Community Partner Survey | K55: Community Partner Survey | L55: Dutchess
A56: Activate | B56: 55 | E56: F39 | F56: The Impact of the Social Determinants of Health in Dutchess County (n = 103) | G56: tbl-DC-impact-sdoh | H56: fig-DC-impact-sdoh | I56: Community Partner Survey | K56: Community Partner Survey | L56: Dutchess
A57: Activate | B57: 56 | E57: F40 | F57: The Impact of Economic Wellbeing in Dutchess County (n = 103) | G57: tbl-DC-eco-wellbeing | H57: fig-DC-eco-wellbeing | I57: Community Partner Survey | K57: Community Partner Survey | L57: Dutchess
A58: Activate | B58: 57 | E58: F41 | F58: The Impact of Mental Wellbeing & Substance Use in Dutchess County (n = 101) | G58: tbl-DC-impact-mhsu | H58: fig-DC-impact-mhsu | I58: Community Partner Survey | K58: Community Partner Survey | L58: Dutchess
A59: Activate | B59: 58 | E59: F42 | F59: The Impact of Health Insurance Coverage & Access to Care in Dutchess County (n = 100) | G59: tbl-DC-impact-hlthinsur-access | H59: fig-DC-impact-hlthinsur-access | I59: Community Partner Survey | K59: Community Partner Survey | L59: Dutchess
A60: Activate | B60: 59 | E60: F43 | F60: Top Rated Issues That Affect Health in Orange County (n = 170) | G60: tbl-OC-affect-health | H60: fig-OC-affect-health | I60: Community Partner Survey | K60: Community Partner Survey | L60: Dutchess
A61: Activate | B61: 60 | E61: F44 | F61: Top Rated Barriers to Achieving Better Health in Orange County (n = 170) | G61: tbl-OC-achieve-health | H61: fig-OC-achieve-health | I61: Community Partner Survey | K61: Community Partner Survey | L61: Dutchess
A62: Activate | B62: 61 | E62: F45 | F62: The Impact of Health Issues in Orange County (n = 163) | G62: tbl-OC-impact-hlth-issue | H62: fig-OC-impact-hlth-issue | I62: Community Partner Survey | K62: Community Partner Survey | L62: Dutchess
A63: Activate | B63: 62 | E63: F46 | F63: The Impact of the Social Determinants of Health in Orange County (n = 160) | G63: tbl-OC-impact-sdoh | H63: fig-OC-impact-sdoh | I63: Community Partner Survey | K63: Community Partner Survey | L63: Dutchess
A64: Activate | B64: 63 | E64: F47 | F64: The Impact of Economic Wellbeing in Orange County (n = 159) | G64: tbl-OC-eco-wellbeing | H64: fig-OC-eco-wellbeing | I64: Community Partner Survey | K64: Community Partner Survey | L64: Dutchess
... A102: Activate | B102: 101 | E102: F85 | F102: Percentage of Adults Who Consume One or More Sugary Beverages Daily, 2016, 2018, and 2021 | G102: tbl-BRFSS-adult-sug-bev | H102: fig-BRFSS-sug-bev | I102: NYS Behavioral Risk Factor Surveillance System (NYS Behavioral Risk Factor Surveillance System (BRFSS) ) | K102: BRFSS | L102: Sullivan
A103: Activate | B103: 102 | E103: T17 | F103: Top Five Leading Causes of Death, by Count and Age-Adjusted Rate per 100,000 Population, 2022 | G103: tbl-five-lead-death-aar | H103: fig-five-lead-death | I103: NYS Vital Statistics | J103: Leading Causes of Death | K103: Vital Statistics of NYS | L103: Ulster
A104: Activate | B104: 103 | E104: F86 | F104: Percentage of Deaths That are Premature, 2019–2022 | G104: tbl-premature-death-percent | H104: =IF(LEFT(G104,4)="tbl-","fig-" & MID(G104,5,LEN(G104)-4),"") -> fig-premature-death-percent | I104: NYS Prevention Agenda Tracking Dashboard | K104: Vital Statistics of NYS | L104: Ulster
A105: Activate | B105: 104 | E105: F87 | F105: Premature Deaths, Percentage Difference Between Black Non-Hispanics and White Non-Hispanics, 2019–2022 | G105: tbl-premature-death-percent-diff-BNHvsWNH | H105: =IF(LEFT(G105,4)="tbl-","fig-" & MID(G105,5,LEN(G105)-4),"") -> fig-premature-death-percent-diff-BNHvsWNH | I105: NYS Prevention Agenda Tracking Dashboard | K105: Vital Statistics of NYS | L105: Ulster
A106: Activate | B106: 105 | E106: F88 | F106: Premature Deaths, Percentage Difference Between Hispanics and White Non-Hispanics, 2019–2022 | G106: tbl-premature-death-percent-diff-HvsWNH | H106: =IF(LEFT(G106,4)="tbl-","fig-" & MID(G106,5,LEN(G106)-4),"") -> fig-premature-death-percent-diff-HvsWNH | I106: NYS Prevention Agenda Tracking Dashboard | K106: Vital Statistics of NYS | L106: Ulster
A107: Activate | B107: 106 | E107: F89 | F107: Chronic Lower Respiratory Disease Hospitalization, Age-Adjusted Rate per 10,000 Population, 2020–2022 | G107: tbl-clrd-hospital-aar | H107: =IF(LEFT(G107,4)="tbl-","fig-" & MID(G107,5,LEN(G107)-4),"") -> fig-clrd-hospital-aar
A108: Activate | B108: 107 | E108: F90 | F108: Chronic Lower Respiratory Disease Mortality, Age-Adjusted Rate per 100,000 Population, 2020-2022 | G108: tbl-clrd-mortal-aar | H108: =IF(LEFT(G108,4)="tbl-","fig-" & MID(G108,5,LEN(G108)-4),"") -> fig-clrd-mortal-aar | I108: NYS Community Health Indicator Reports (CHIRS) | K108: NY Statewide Planning and Research Cooperative System | L108: Dutchess
A109: Activate | B109: 108 | E109: F91 | F109: Chronic Lower Respiratory Disease Hospitalization, Age-Adjusted Rate per 10,000 by Race and Ethnicity, 2020–2022 | G109: tbl-clrd-hospital-rande-aar | H109: =IF(LEFT(G109,4)="tbl-","fig-" & MID(G109,5,LEN(G109)-4),"") -> fig-clrd-hospital-rande-aar
A110: Activate | B110: 109 | E110: F92 | F110: Chronic Lower Respiratory Disease Mortality, Age-Adjusted Rate per 100,000 Population by Race and Ethnicity, 2020–2022 | G110: tbl-clrd-mortal-rande-aar | H110: =IF(LEFT(G110,4)="tbl-","fig-" & MID(G110,5,LEN(G110)-4),"") -> fig-clrd-mortal-rande-aar | I110: NYS Community Health Indicator Reports (CHIRS) | K110: Vital Statistics of NYS | L110: Dutchess
A111: Activate | B111: 110 | E111: F93 | F111: Percentage of Adults with Current Asthma, 2016, 2018, and 2021 | G111: tbl-brfss-adult-asthma | H111: =IF(LEFT(G111,4)="tbl-","fig-" & MID(G111,5,LEN(G111)-4),"") -> fig-brfss-adult-asthma | I111: NYS Behavioral Risk Factor Surveillance System (BRFSS) | L111: Dutchess
A112: Activate | B112: 111 | E112: F94 | F112: Asthma Hospitalization, Age-Adjusted Rate per 10,000 Population, 2020–2022 | G112: tbl-asthma-hopsital-aar | H112: =IF(LEFT(G112,4)="tbl-","fig-" & MID(G112,5,LEN(G112)-4),"") -> fig-asthma-hopsital-aar | I112: NYS Community Health Indicator Reports (CHIRS) | K112: NY Statewide Planning and Research Cooperative System | L112: Dutchess
A113: Activate | B113: 112 | E113: F95 | F113: Asthma Hospitalization, Age-Adjusted Rate per 10,000 Population by Race and Ethnicity, 2020–2022 | G113: tbl-asthma-hopsital-rande-aar | H113: =IF(LEFT(G113,4)="tbl-","fig-" & MID(G113,5,LEN(G113)-4),"") -> fig-asthma-hopsital-rande-aar | I113: NYS County Health Indicators by Race/Ethnicity (CHIRE) | K113: NY Statewide Planning and Research Cooperative System | L113: Dutchess
A114: Activate | B114: 113 | E114: F96 | F114: Asthma Emergency Department Visits, Rate per 10,000 Population 0–17 Years Old, 2017–2023 | G114: tbl-0to17-asthma-ed-rate | H114: =IF(LEFT(G114,4)="tbl-","fig-" & MID(G114,5,LEN(G114)-4),"") -> fig-0to17-asthma-ed-rate | I114: NYSDOH Asthma Dashboard | K114: NY Statewide Planning and Research Cooperative System | L114: Dutchess
A115: Activate | B115: 114 | E115: F97 | F115: Percentage of Adults with Cardiovascular Disease, 2016, 2018, and 2021 | G115: tbl-adult-cardiovasdz-percent | H115: =IF(LEFT(G115,4)="tbl-","fig-" & MID(G115,5,LEN(G115)-4),"") -> fig-adult-cardiovasdz-percent
A116: Activate | B116: 115 | E116: F98 | F116: Cardiovascular Hospitalization, Age-Adjusted Rate per 10,000, 2019–2021 | G116: tbl-cardiovasdz-hospi-aar | H116: =IF(LEFT(G116,4)="tbl-","fig-" & MID(G116,5,LEN(G116)-4),"") -> fig-cardiovasdz-hospi-aar | I116: NYS Community Health Indicator Reports (CHIRS) | K116: NY Statewide Planning and Research Cooperative System | L116: Rockland
A117: Activate | B117: 116 | E117: F99 | F117: Cardiovascular Disease Mortality, Age-Adjusted Rate Per 100,000 Population, 2018–2021 | G117: tbl-cardiovasdz-mortal-aar | H117: =IF(LEFT(G117,4)="tbl-","fig-" & MID(G117,5,LEN(G117)-4),"") -> fig-cardiovasdz-mortal-aar | I117: NYS Community Health Indicator Reports (CHIRS) | K117: Vital Statistics of NYS | L117: Rockland
A118: Activate | B118: 117 | E118: F100 | F118: Percentage of Adults with Physician Diagnosed High Blood Pressure, 2022 | G118: tbl-adult-highbp-mddx-percent | H118: =IF(LEFT(G118,4)="tbl-","fig-" & MID(G118,5,LEN(G118)-4),"") -> fig-adult-highbp-mddx-percent | I118: NYS Behavioral Risk Factor Surveillance System (BRFSS) | L118: Rockland
A119: Activate | B119: 118 | E119: F101 | F119: Cerebrovascular Disease Hospitalization, Age-Adjusted Rate per 10,000 Population, 2019–2021 | G119: tbl-cerebrovasdz-hospital-aar | H119: =IF(LEFT(G119,4)="tbl-","fig-" & MID(G119,5,LEN(G119)-4),"") -> fig-cerebrovasdz-hospital-aar | I119: NYS Community Health Indicator Reports (CHIRS) | K119: NY Statewide Planning and Research Cooperative System | L119: Rockland
A120: Activate | B120: 119 | E120: F102 | F120: Cerebrovascular Disease Hospitalization, Age-Adjusted Rate per 10,000 Population by Race and Ethnicity, 2020–2022 | G120: tbl-cerebrovasdz-hospital-rande-aar | H120: =IF(LEFT(G120,4)="tbl-","fig-" & MID(G120,5,LEN(G120)-4),"") -> fig-cerebrovasdz-hospital-rande-aar | I120: NYS County Health Indicators by Race/Ethnicity (CHIRE) | K120: NY Statewide Planning and Research Cooperative System | L120: Rockland
A121: Activate | B121: 120 | E121: F103 | F121: Cerebrovascular Disease Mortality, Age-Adjusted Rate per 100,000 Population, 2018–2021 | G121: tbl-cerebrovasdz-mortal-aar | H121: =IF(LEFT(G121,4)="tbl-","fig-" & MID(G121,5,LEN(G121)-4),"") -> fig-cerebrovasdz-mortal-aar | I121: NYS Community Health Indicator Reports (CHIRS) | K121: Vital Statistics of NYS | L121: Rockland
A122: Activate | B122: 121 | E122: F104 | F122: Cerebrovascular Disease Mortality, Age-Adjusted Rate per 100,000 Population by Race and Ethnicity, 2020–2022 | G122: tbl-cerebrovasdz-mortal-rande-aar | H122: =IF(LEFT(G122,4)="tbl-","fig-" & MID(G122,5,LEN(G122)-4),"") -> fig-cerebrovasdz-mortal-rande-aar | I122: NYS County Health Indicators by Race/Ethnicity (CHIRE) | K122: Vital Statistics of NYS | L122: Rockland
A123: Activate | B123: 122 | E123: F105 | F123: Coronary Heart Disease Hospitalization, Age-Adjusted Rate per 10,000, 2021 | G123: tbl-coronary-heart-disease-hospital-aar | H123: =IF(LEFT(G123,4)="tbl-","fig-" & MID(G123,5,LEN(G123)-4),"") -> fig-coronary-heart-disease-hospital-aar
A124: Activate | B124: 123 | E124: F106 | F124: Coronary Heart Disease Age-Adjusted Hospitalization Rate per 10,00 by Race/Ethnicity, 2020–2022 | G124: tbl-coronary-heart-disease-hospital-rande-aar | H124: =IF(LEFT(G124,4)="tbl-","fig-" & MID(G124,5,LEN(G124)-4),"") -> fig-coronary-heart-disease-hospital-rande-aar
A125: Activate | B125: 124 | E125: F107 | F125: Heart Attack, Age-Adjusted Hospitalization Rate per 10,000 population, 2021 | G125: tbl-heartattack-hospital-aar | H125: =IF(LEFT(G125,4)="tbl-","fig-" & MID(G125,5,LEN(G125)-4),"") -> fig-heartattack-hospital-aar
A126: Activate | B126: 125 | E126: F108 | F126: Congestive Heart Failure Mortality, Age-Adjusted Rate per 100,000 Population, 2018–2021 | G126: tbl-congheartfail-mortal-aar | H126: =IF(LEFT(G126,4)="tbl-","fig-" & MID(G126,5,LEN(G126)-4),"") -> fig-congheartfail-mortal-aar | I126: NYS Community Health Indicator Reports (CHIRS) | K126: Vital Statistics | L126: Westchester
A127: Activate | B127: 126 | E127: F203 | F127: Dropped
F128: Coronary Heart Disease, Age-Adjusted Hospitalization Rate per 10,000 by Race/Ethnicity, 2020-2022 | G128: tbl-congheartfail-mortal-rande | H128: =IF(LEFT(G128,4)="tbl-","fig-" & MID(G128,5,LEN(G128)-4),"") -> fig-congheartfail-mortal-rande
F129: Heart Attack Mortality, Age-Adjusted Rate per 100,000 Population, 2018–2021 | G129: tbl-heartattack-mortal-aar | H129: =IF(LEFT(G129,4)="tbl-","fig-" & MID(G129,5,LEN(G129)-4),"") -> fig-heartattack-mortal-aar
A130: Activate | B130: 127 | E130: 204 | F130: Percentage of Adults with Physician Diagnosed Prediabetes and Diabetes, 2021 | G130: tbl-mddx-predm-dm-percent | H130: =IF(LEFT(G130,4)="tbl-","fig-" & MID(G130,5,LEN(G130)-4),"") -> fig-mddx-predm-dm-percent | I130: NYS Behavioral Risk Factor Surveillance System (BRFSS) | L130: Westchester
A131: Activate | B131: 128 | E131: F205 | F131: Dropped
A132: Activate | B132: 129 | E132: 206 | F132: Diabetes Hospitalization, Age-Adjusted Rate per 10,000 Population, 2021 | G132: tbl-dm-hospital-aar | H132: =IF(LEFT(G132,4)="tbl-","fig-" & MID(G132,5,LEN(G132)-4),"") -> fig-dm-hospital-aar | I132: NYS Community Health Indicator Reports (CHIRS) | K132: NY Statewide Planning and Research Cooperative System | L132: Westchester
A133: Activate | B133: 130 | E133: 207 | F133: Diabetes Hospitalization, Age-Adjusted Rate per 10,000 by Race and Ethnicity, 2020–2022 | G133: tbl-dm-hospital-rande-aar | H133: =IF(LEFT(G133,4)="tbl-","fig-" & MID(G133,5,LEN(G133)-4),"") -> fig-dm-hospital-rande-aar | I133: NYS County Health Indicators by Race/Ethnicity (CHIRE) | L133: Westchester
A134: Activate | B134: 131 | E134: 208 | F134: Percentage of Adults Who Had a Test for High Blood Sugar or Diabetes Within the Past Three Years, 2013–2014, 2016, 2018, and 2021 | G134: tbl-highbs-dm-percent | H134: =IF(LEFT(G134,4)="tbl-","fig-" & MID(G134,5,LEN(G134)-4),"") -> fig-highbs-dm-percent | I134: NYS Behavioral Risk Factor Surveillance System (BRFSS) | L134: Westchester
A135: Activate | B135: 132 | E135: 209 | F135: Diabetes Mortality, Age-Adjusted Rate per 100,000 Population, 2018–2021 | G135: tbl-dm-mortal-aar | H135: =IF(LEFT(G135,4)="tbl-","fig-" & MID(G135,5,LEN(G135)-4),"") -> fig-dm-mortal-aar | I135: NYS Community Health Indicator Reports (CHIRS) | K135: NY Statewide Planning and Research Cooperative System | L135: Westchester
A136: Activate | B136: 133 | E136: F210 | F136: Dropped
A137: Activate | B137: 134 | E137: 211 | F137: Diabetes Mortality, Age-Adjusted per 100,000 Population by Race and Ethnicity, 2020–2022 | G137: tbl-dm-mortal-rande-aar | H137: =IF(LEFT(G137,4)="tbl-","fig-" & MID(G137,5,LEN(G137)-4),"") -> fig-dm-mortal-rande-aar | I137: NYS County Health Indicators by Race/Ethnicity (CHIRE) | K137: Vital Statistics of NYS | L137: Westchester
...

Sheet Dropdowns
A1: integer | B1: Y-labels | D1: Footnotes | E1: Sources | F1: Links | G1: Dates | H1: Notes
A2: number | B2: Case Rate | C2: * | D2: *: BRFSS - Crude rate is unreliable due to large standard error. | E2: Source: Centers for Disease Control and Prevention | F2: https://health.data.ny.gov/Health/Behavioral-Risk-Factor-Surveillance-System-BRFSS-H/jsy7-eb4n/data | G2: July 2025 | H2: Note: "Other" includes American Indian or Alaska Native and Native Hawaiian or Other Pacific Islander.
A3: percent1 | B3: Index | C3: * | D3: *: BRFSS - Percentage is unreliable due to large standard error. | E3: Source: Community Partner Survey Focus Groups | F3: https://www.cdc.gov/places/ | G3: June 2025 | H3: Note:A community water system is a public water system that serves the same people year-round. Most residences including homes, apartments, and condominiums in cities, towns, and mobile home parks are served by community water systems. This is a measure of the number of residents served by community water systems with optimal fluoride levels per 100 residents served by community water systems.
A4: percent2 | B4: Number of Cases | C4: * | D4: *: Data are unstable due to a margin of error greater than 10%. | E4: Source: Feeding America | F4: https://webbi1.health.ny.gov/SASStoredProcess/guest?_program=%2FEBI%2FPHIG%2Fapps%2Fchir_dashboard%2Fchir_dashboard&p=ch&cos=33 | G4: May 2025 | H4: Note: County of residence was assigned based on ZIP Code for cases in which patient county of residence was listed as unknown or missing but a valid NY ZIP Code was present.
A5: currency | B5: Percent | C5: * | D5: *: Data are unstable due to fewer than 10 events in the numerator. | E5: Source: Health Resources and Services Administration Data Warehouse | F5: https://www.health.ny.gov/statistics/community/minority/county/orange.htm | G5: April 2025 | H5: Note: Feeding America takes the CPS data and analyzes the relationships between food insecurity and its determinants (i.e., unemployment, poverty, disability, homeownership, and median income), as well as the percentage of the population that is Black and the percentage of the population that is Hispanic. Coefficient estimates from this analysis combined with information on the same variables defined at the county and congressional district levels are generated to estimate food insecurity.
A6: currency2 | B6: Rate per 1,000 | C6: * | D6: *: Data are unstable due to fewer than 20 events in the numerator. | E6: Source: NYC Poison Center | F6: https://www.health.ny.gov/statistics/diseases/communicable/docs/2019_hepc_regional.pdf | G6: March 2025 | H6: Note: Five-year age-adjusted rates.
A7: ratio | B7: Rate per 10,000 | C7: * | D7: *: The percentage is unstable. | E7: Source: NYS Board of Elections | F7: https://www.health.ny.gov/statistics/chac/perinatal/county/2018-2020/orange.htm | G7: February 2025 | H7: Note: IMU* = Index of Medical Underservice.
A8: date | B8: Rate per 100,000 | C8: * | D8: *: The rate is unstable. | E8: Source: NYS Cancer Registry and Cancer Statistics | F8: https://www.criminaljustice.ny.gov/crimnet/ojsa/arrests/index.htm | G8: January 2025 | H8: Note: Incidence and mortality rates stratified by race/ethnicity are not available. However, trend data for incidence and mortality rates can be found on NYSDOH Community Health Indicator Reports (CHIRS).
B9: Ratio | C9: + | D9: : The 2019 ED data in NYC may be incomplete and subject to change. Thus, the state rates may be underestimated and subject to change. | E9: Source: NYS Community Health Indicator Reports Dashboard | F9: https://data.nysed.gov/gradrate.php?year=2022&county=44 | G9: December 2024 | H9: Note: Incidence and mortality rates stratified by race/ethnicity are not shown due to suppressed and/or unstable data in most counties. However, trend data for incidence and mortality rates can be found on NYSDOH Community Health Indicator Reports (CHIRS).
C10: Other | D10: Other (please specify): Some additional responses from participants include access to healthy affordable food, transportation, valuing health as a family priority, affordable housing, lack of chronic disease self-management programs, lack of social support systems, language barriers. | E10: Source: NYS County Health Indicators by Race and Ethnicity | F10: https://webbi1.health.ny.gov/SASStoredProcess/guest?_program=%2FEBI%2FPHIG%2Fapps%2Fmch_dashboard%2Fmch_dashboard&p=ch&cos=33 | G10: November 2024 | H10: Note: Index of dissimilarity where higher values indicate greater residential segregation between Black and White County residents.
C11: Other | D11: Other (please specify): Some additional responses from participants include finding child care, access to health care providers who are trained in LGBTQIA+ health care needs, mental health services, immigration issues, language and cultural barriers, and financial issues. | E11: Source: NYS Department of Health Office of Sexual Health and Epidemiology | F11: https://webbi1.health.ny.gov/SASStoredProcess/guest?_program=%2FEBI%2FPHIG%2Fapps%2Fopioid_dashboard%2Fop_dashboard&p=ch&cos=33 | G11: October 2024 | H11: Note: Mortality rates stratified by race/ethnicity are not available.
C12: Other | D12: Other (please specify): Some additional responses from participants include location of services, lack of financial resources, transportation, affordable housing, and service providers not being aware of biases they bring into marginalized communities. | E12: Source: NYS Division of Criminal Justice Services | F12: https://webbi1.health.ny.gov/SASStoredProcess/guest?_program=%2FEBI%2FPHIG%2Fapps%2Fdashboard%2Fpa_dashboard&p=ch&cos=33 | G12: September 2024 | H12: Note: Opioid pain relievers include illicitly produced opioids such as fentanyl.
C13: Other | D13: Other (please specify): Some additional responses from participants include navigating health care access, poverty, affordable transportation, and accessibility and availability of quality services. | E13: Source: NYS Education Department | F13: https://www.health.ny.gov/statistics/diseases/communicable/std/docs/sti_surveillance_report_2021.pdf | G13: August 2024 | H13: Note: Other forms of coverage not shown include Indian Health, CHAMPUS, Other, and Not Stated. Medicaid includes births with Medicaid listed as secondary payer.
C14: Other | D14: Other (please specify): Some additional responses from participants include stigma, language barrier as a large portion of the population being served speaks Spanish, navigating the health system, and places to play and/or exercise. | E14: Source: NYS Leading Causes of Death Dashboard | F14: https://statecancerprofiles.cancer.gov/ | G14: July 2024 | H14: Note: Race or races with which the student primarily identifies are indicated by the student or the parent/guardian.
C15: s | D15: s: Data are suppressed due to unreliable or missing data. | E15: Source: NYS Opioid Data Dashboard | F15: https://data.census.gov/cedsci/ | G15: June 2024 | H15: Note: Ranks are based on numbers of deaths, then on mortality rates.
C16: s | D16: s: Data are suppressed due to not meeting reporting criteria. | E16: Source: NYS Prevention Agenda Tracking Dashboard | F16: https://www.americashealthrankings.org/ | G16: May 2024 | H16: Note: Respondents who report any one of the six disability types are considered to have a disability in the American Community Survey. The previous Regional CHA utilized data from the NYSDOH Expanded Behavioral Risk Factor Surveillance System (BRFSS). The data change between the BRFSS and the ACS accounts for the drastic changes between the Regional CHAs.
C17: s | D17: s: Data are suppressed due to lack of preliminary data. | E17: Source: NYS Smoker's Quitline | F17: https://ahead.hiv.gov/ | G17: April 2024 | H17: Note: Severely cost burdened is defined as the percent of households that spend 50% or more of their household income on housing. The 2019 County Health Rankings (CHR) used data from 2013-2017 and the 2022 CHR used data from 2016-2020 for this measure.
C18: s | D18: s: Data are suppressed due to not meeting confidentialty criteria. | E18: Source: NYSDOH Behavioral Risk Factor Surveillance System | F18: https://wonder.cdc.gov/ | G18: March 2024 | H18: Note: Single-year crude rates.
C19: s | D19: s: Data are suppressed due to small sample size. | E19: Source: NYSDOH Bureau of Communicable Disease Control | F19: https://nccd.cdc.gov/Youthonline/App/Results.aspx?LID=XX | G19: February 2024 | H19: Note: The American Community Survey asks respondents how many automobiles, vans, and trucks of one-ton capacity or less are kept at home for use by members of the household.
E20: Source: NYSDOH Communicable Disease Annual Reports | F20: https://www.cdc.gov/injury/wisqars/index.html | G20: January 2024 | H20: Note: The American Community Survey asks respondents how they usually got to work last week. For respondents who use multiple transportation modes they are restricted to the single method of transportation used for the longest distance.
E21: Source: NYSDOH Communicable Disease Electronic Surveillance System | F21: https://www.cdc.gov/mmwr/index.html | G21: December 2023 | H21: Note: The American Community Survey asks respondents if they have ever served on active duty in the US Armed Forces.
E22: Source: NYSDOH, Wadsworth Center Rabies Laboratory | F22: https://www.cdc.gov/asthma/asthmadata.htm | G22: November 2023 | H22: Note: The American Community Survey asks respondents if they have worked in the past week. If the answer is no, they are asked why they are not working. For those who are not working, they are asked whether they plan to return to work, and when they last worked.
E23: Source: United for ALICE | F23: https://www.cdc.gov/nceh/ | G23: October 2023 | H23: Note: The American Community Survey asks respondents if they own or rent the house, apartment, or mobile home they live in. If rented, they ask the monthly rent. Cost burdened is defined as the percentage of renter occupied units in which gross rent is 30% or more of household income.
E24: Source: University of Wisconsin Population Health Institute. County Health Rankings & Roadmaps | F24: https://www.cdc.gov/nchs/index.htm | G24: September 2023 | H24: Note: The American Community Survey asks respondents in the workforce how many minutes it usually takes them to get from home to work. The travel time refers to a one-way trip on a typical day. This includes time spent waiting for public transportation, picking up passengers in carpools, and time spent in other activities related to getting to work.
E25: Source: Upstate NY Poison Center | F25: https://www.cdc.gov/nchs/nhis/shs.htm | G25: August 2023 | H25: Note: The American Community Survey asks respondents their income in the past 12 months including joint income. This is for income that is received on a regular basis before payments for taxes, social security, etc. If a family’s total income is less than the official poverty threshold for a family of that size and composition, they are considered to be in poverty.
E26: Source: US Census Bureau | F26: https://www.cdc.gov/diabetes/data/index.html | G26: July 2023 | H26: Note: The American Community Survey asks respondents their income in the past 12 months. Data are provided as a percent of total households in Table S1901. Calculations were made to provide data as a number in Table 28.
E27: Source: US Census Bureau; American Community Survey | F27: https://www.cdc.gov/nchhstp/atlas/index.htm | G27: June 2023 | H27: Note: The American Community Survey asks respondents to report whether they sometimes or always spoke a language other than English at home. People who knew languages other than English but did not use them at home, who only used them elsewhere, or whose usage was limited to a few expressions or slang were excluded.
E28: Source: Vital Statistics of NYS | F28: https://www.cdc.gov/std/statistics/2021/default.htm | G28: May 2023 | H28: Note: The American Community Survey asks respondents what the highest degree or level of school the person has completed.
F29: https://www.cdc.gov/vaccines/imz-managers/coverage/teenvaxview/data-reports/index.html | G29: April 2023 | H29: Note: The American Community Survey includes a question that intends to capture current sex; there are no questions about gender, sexual orientation, or sex at birth. Respondents should respond either "male" or "female" based on how they currently identify their sex.
F30: https://gis.cdc.gov/grasp/diabetes/diabetesatlas-surveillance.html | G30: March 2023 | H30: Note: The American Community Survey utilized industry titles based on the North American Industry Classification System from 2018.
F31: https://www.cdc.gov/hepatitis/statistics/SurveillanceRpts.htm | G31: February 2023 | H31: Note: The Census Bureau collects racial data in accordance with guidelines provide by the US Office of Management and Budget, and these data are based on self-identification. People who identify with more than one race may choose to provide multiple races in response to the race question. For ethnicity, the OMB standards classify individuals in one of two categories: “Hispanic or Latino” or “Not Hispanic or Latino.” The Census Bureau uses the term “Hispanic or Latino” interchangeably with the term “Hispanic,” and also refer to this concept as “ethnicity.”
F32: https://www.ghrconnects.org/indicators | G32: January 2023 | H32: Note: The Census Bureau collects racial data in accordance with guidelines provided by the US Office of Management and Budget (OMB) and these data are based on self-identification. People who identify with more than one race may choose to provide multiple races in response to the race question. For ethnicity, the OMB standards classify individuals in one of two categories: “Hispanic or Latino” or “Not Hispanic or Latino.” The Census Bureau uses the term “Hispanic or Latino” interchangeably with the term “Hispanic,” and also refer to this concept as “ethnicity.” The American Community Survey asks respondents their income in the past 12 months including joint income. This is for income that is received on a regular basis before payments for taxes, social security, etc. If a family’s total income is less than the official poverty threshold for a family of that size and composition, then they are considered to be in poverty.
F33: https://www.kff.org/ | G33: December 2022 | H33: Note: The Census Bureau defines educational attainment as the highest level of education that an individual has completed. This is distinct from the level of schooling that an individual is attending.
F34: https://progressreport.cancer.gov/detection | G34: November 2022 | H34: Note: The most recent data are from 2019.
F35: https://statecancerprofiles.cancer.gov/index.html | G35: October 2022 | H35: Note: The number of cases is determined using sentinel surveillance, which is extrapolated from samples of positive laboratory results to generate estimates of the total number of cases. Sentinel surveillance was conducted in all Mid-Hudson counties in 2017.
F36: https://nces.ed.gov/ | G36: September 2022 | H36: Note: The overall violent crime rate of a county is calculated by dividing the total number of violent crimes submitted by police agencies in each county by the county’s population and multiplying the result by 100,000. The US Census Bureau is the source of county population data. Includes all reports received as of May 16, 2022.
F37: https://www.niaaa.nih.gov/ | G37: August 2022 | H37: Note: The previous Mid-Hudson Region Community Health Assessment, 2019-2021, reported this data on populations aged 5-17 years.
F38: https://data.oecd.org/ | G38: July 2022 | H38: Note: The rate for 2015 is excluded due to SPARCS data transitioning on October 1, 2015 from ICD-9-CM to ICD-10-CM diagnosis codes. Since ICD-9-CM and ICD-10-CM are not comparable, an annual rate for 2015 cannot be calculated, and data for 2016-andforward should not be compared with data for 2014-and-prior.
F39: https://data.census.gov/cedsci/ | G39: June 2022 | H39: Note: The rate for 2015 is excluded due to SPARCS data transitioning on October 1, 2015, from ICD-9-CM to ICD-10-CM diagnosis codes. Since ICD-9-CM and ICD-10-CM are not comparable, an annual rate for 2015 cannot be calculated, and data for 2016-andforward should not be compared with data for 2014-and-prior.
F40: https://www.bls.gov/cps/data-overview.htm | G40: May 2022 | H40: Note: The US Census asks respondents if they are currently covered by any type of health insurance or health coverage plans.
F41: https://health.gov/healthypeople | G41: April 2022 | H41: Note: The US Census Bureau gathers data called the Comprehensive Housing Affordability Strategy, and these data are shared with the US Department of Housing and Urban Development for reporting purposes. Incomplete kitchen facilities are defined as a unit which lacks a sink with running water, a stove or range, or a refrigerator. Incomplete plumbing facilities is defined as lacking hot and cold piped water, a flush toilet, or a bathtub/shower. Overcrowding is defined as more than one person per room. Severe cost burden is defined as monthly housing costs, including utilities, that exceed 50% of monthly income. Graph reflects the percentage of households with at least one of these four housing problems.
G42: March 2022 | H42: Note: This is a measure of the average daily density of fine particulate matter. Fine particulate matter is defined as particles of air pollutants with an aerodynamic diameter less than 2.5 micrometers. The Environmental Public Health Tracking Network data come from the US Environmental Protection Agency's Air Quality System.
G43: February 2022 | H43: Note: This is a measure of the percentage of children in a single birth cohort tested at least twice for lead before 36 months of age.
G44: January 2022 | H44: Note: Three-year age-adjusted rates for counties and single-year age-adjusted rates for NYS and NYS excluding NYC are used in both the table and graph above.
G45: December 2021 | H45: Note: Three-year age-adjusted rates.
G46: November 2021 | H46: Note: Three-year averages are used for counties and single-year estimates are used for Mid-Hudson and NYS.
G47: October 2021 | H47: Note: Three-year averages were used for counties, while single-year estimates were used for NYS and NYS excluding NYC.
G48: September 2021 | H48: Note: Three-year averages are used for counties and single-year rates are used for NYS and NYS excluding NYC.
G49: August 2021 | H49: Note: Trend data for incidence and mortality rates can be found on NYS Community Health Indicator Reports (CHIRS).
G50: July 2021 | H50: Note: Two-year crude rates.
H51: Note: Y-axis does not begin at zero in order to clearly display trend lines.
H52: Note: Y-axis does not begin at zero in order to clearly display trend lines. Graduates include students who received a local diploma or a local diploma with Regents endorsement (Regents diploma). All students who received a Regents diploma (with or without Advanced Designation or Career and Technical Education endorsement) are included in the number of students with Regents diploma.
H53: Note: Only the crude rate for 2017-2019 is available for this measure.
H54: Note: The 2019 ED data in New York City may be incomplete and subject to change. Thus, the state rate may be underestimated and subject to change.
H55: Note: The rate for 2015 is excluded due to SPARCS data transitioning on October 1, 2015 from ICD-9-CM to ICD-10-CM diagnosis codes. Since ICD-9-CM and ICD-10-CM are not comparable, an annual rate for 2015 cannot be calculated, and data for 2016-and-forward should not be compared with data for 2014-and-prior. On the graph, the distinction is signified by a dotted line for ICD-9-CM years and a solid line for ICD-10-CM years.
H56: Note: 2021 population estimates not available. Rates determined with 2020 population estimates.
H57: Note: Data for Westchester provided by NYC Poison Center.
H58: Note: Data totals for 2020 are preliminary at the time of this report.
H59: Note: Domestic animals include dogs, cats, ferrets, horses, donkeys, mules, cattle, sheep, goats, and pigs.
H60: Note: Wild animals include bats, bears, bobcats, coyote, deer, fox, opossum, porcupine, rabbit, raccoon, rat, skunk, squirrel, weasel, woodchuck.

Sheet _Demographics

Sheet Population Demographic Characte
A1: Name | B1: Population Demographic Characteristics, 2023
A2: Table/Figure/Both | B2: Table
A3: Object ID | B3: tbl-population-demographics
G4: integer | H4: percent1 | I4: percent1
A5: Table Rules | E5: Enter Data | F5: County | G5: Total Population | H5: Percent of Mid-Hudson Region | I5: Percent of NYS
A6: Multilevel Headers | F6: Dutchess | G6: 297144 | H6: 12.4 | I6: 1.5
A7: Data Type | F7: Orange | G7: 403840 | H7: 16.9 | I7: 2
F8: Putnam | G8: 97988 | H8: 4.1 | I8: 0.5
A9: Figure Rules | F9: Rockland | G9: 338936 | H9: 14.1 | I9: 1.7
A10: Figure Type | F10: Sullivan | G10: 79147 | H10: 3.3 | I10: 0.4
A11: X Column | F11: Ulster | G11: 182109 | H11: 7.6 | I11: 0.9
A12: Y Column | F12: Westchester | G12: 996888 | H12: 41.6 | I12: 5
A13: X Axis Title | F13: Mid-Hudson | G13: 2396052 | H13: 100 | I13: 12.1
A14: Y Axis Title | F14: NYS excl NYC | G14: 11356117 | H14: N/A | I14: 57.1
A15: Start at Zero | F15: NYS | G15: 19872318 | H15: N/A | I15: 100
A18: Source Specifications
A19: Table ID
A20: URL
A21: Data Year
A22: Estimate Type
A23: Citation Month
A24: Citation Year
A25: Custom Text
A27: Note Specfications

Sheet Sex-Population
A1: Name | B1: Population by Sex, 2023
A2: Table/Figure/Both | B2: Table
A3: Object ID | B3: =IF($B$1="","",_xlfn.XLOOKUP($B$1,Master!$F$2:$F$308,Master!$G$2:$G$308,"")) -> tbl-sex
G4: integer | H4: percent1 | I4: integer | J4: percent1
A5: Table Rules | E5: Enter Data | F5: Area | G5: Male | I5: Female
A6: Multilevel Headers | B6: TRUE | G6: Total Population | H6: % | I6: Total Population | J6: %
F7: Dutchess | G7: 147902 | H7: 49.8 | I7: 149242 | J7: 50.2
F8: Orange | G8: 201512 | H8: 49.9 | I8: 202328 | J8: 50.1
A9: Figure Rules | F9: Putnam | G9: 49503 | H9: 50.5 | I9: 48485 | J9: 49.5
A10: Figure Type | F10: Rockland | G10: 167624 | H10: 49.5 | I10: 171312 | J10: 50.5
A11: X Column | F11: Sullivan | G11: 40993 | H11: 51.8 | I11: 38154 | J11: 48.2
A12: Y Column | F12: Ulster | G12: 90719 | H12: 49.8 | I12: 91390 | J12: 50.2
A13: X Axis Title | F13: Westchester | G13: 485985 | H13: 48.8 | I13: 510903 | J13: 51.2
A14: Y Axis Title | F14: Mid-Hudson | G14: 1184238 | H14: 49.4 | I14: 1211814 | J14: 50.6
A15: Start at Zero | F15: NYS excl NYC | G15: 5614391 | H15: 49.4 | I15: 5741726 | J15: 50.6
F16: NYS | G16: 9702417 | H16: 48.8 | I16: 10169902 | J16: 51.2
A18: Source Specifications
A19: Table ID
A20: URL
A21: Data Year
A22: Estimate Type
A23: Citation Month
A24: Citation Year
A25: Custom Text
A27: Note Specfications

Sheet Age-Population
A1: Name | B1: Population by Age, 2023
A2: Table/Figure/Both | B2: Table
A3: Object ID | B3: =IF($B$1="","",_xlfn.XLOOKUP($B$1,Master!$F$2:$F$308,Master!$G$2:$G$308,"")) -> tbl-age
G4: integer | H4: percent1 | I4: integer | J4: percent1 | K4: integer | L4: percent1 | M4: integer | N4: percent1 | O4: integer | P4: percent1 | Q4: integer | R4: percent1 | S4: integer | T4: percent1 | U4: integer | V4: percent1 | W4: integer | X4: percent1 | Y4: integer | Z4: percent1 | AA4: integer | AB4: percent1
A5: Table Rules | E5: Enter Data | G5: <5 years | I5: 5-9 years | K5: 10-19 years | M5: 20-29 years | O5: 30-39 years | Q5: 40-49 years | S5: 50-59 years | U5: 60-69 years | W5: 70-79 years | Y5: >80 years | AA5: <18 years
A6: Multilevel Headers | B6: TRUE | G6: Total Population | H6: % | I6: Total Population | J6: % | K6: Total Population | L6: % | M6: Total Population | N6: % | O6: Total Population | P6: % | Q6: Total Population | R6: % | S6: Total Population | T6: % | U6: Total Population | V6: % | W6: Total Population | X6: % | Y6: Total Population | Z6: % | AA6: Total Population | AB6: %
A7: Data Type | B7: Percent | F7: Dutchess | G7: 13613 | H7: 4.6 | I7: 14448 | J7: 4.9 | K7: 37031 | L7: 12.5 | M7: 38178 | N7: 12.8 | O7: 35520 | P7: 12 | Q7: 36796 | R7: 12.4 | S7: 43025 | T7: 14.5 | U7: 41707 | V7: 14 | W7: 23935 | X7: 8.1 | Y7: 12891 | Z7: 4.3 | AA7: 55342 | AB7: 18.6
F8: Orange | G8: 27143 | H8: 6.7 | I8: 27679 | J8: 6.9 | K8: 61718 | L8: 15.3 | M8: 52658 | N8: 13 | O8: 48459 | P8: 12 | Q8: 49782 | R8: 12.3 | S8: 52995 | T8: 13.1 | U8: 45285 | V8: 11.2 | W8: 25081 | X8: 6.2 | Y8: 13040 | Z8: 3.2 | AA8: 103740 | AB8: 25.7
A9: Figure Rules | F9: Putnam | G9: 4521 | H9: 4.6 | I9: 4320 | J9: 4.4 | K9: 12426 | L9: 12.7 | M9: 10922 | N9: 11.1 | O9: 11264 | P9: 11.5 | Q9: 13032 | R9: 13.3 | S9: 15538 | T9: 15.9 | U9: 13386 | V9: 13.7 | W9: 8739 | X9: 8.9 | Y9: 3840 | Z9: 3.9 | AA9: 19180 | AB9: 19.6
A10: Figure Type | F10: Rockland | G10: 28957 | H10: 8.5 | I10: 27051 | J10: 8 | K10: 52692 | L10: 15.5 | M10: 41742 | N10: 12.3 | O10: 38885 | P10: 11.5 | Q10: 36560 | R10: 10.8 | S10: 40115 | T10: 11.8 | U10: 35529 | V10: 10.5 | W10: 23713 | X10: 7 | Y10: 13692 | Z10: 4 | AA10: 99733 | AB10: 29.4
A11: X Column | F11: Sullivan | G11: 4656 | H11: 5.9 | I11: 4969 | J11: 6.3 | K11: 9343 | L11: 11.8 | M11: 9032 | N11: 11.4 | O11: 9668 | P11: 12.2 | Q11: 9486 | R11: 12 | S11: 11009 | T11: 13.9 | U11: 10980 | V11: 13.9 | W11: 7087 | X11: 9 | Y11: 2917 | Z11: 3.7 | AA11: 16947 | AB11: 21.4
A12: Y Column | F12: Ulster | G12: 7926 | H12: 4.4 | I12: 8802 | J12: 4.8 | K12: 19831 | L12: 10.9 | M12: 22175 | N12: 12.2 | O12: 23060 | P12: 12.7 | Q12: 22177 | R12: 12.2 | S12: 26342 | T12: 14.5 | U12: 26250 | V12: 14.4 | W12: 16546 | X12: 9.1 | Y12: 9000 | Z12: 4.9 | AA12: 31636 | AB12: 17.4
A13: X Axis Title | F13: Westchester | G13: 53282 | H13: 5.3 | I13: 57324 | J13: 5.8 | K13: 129780 | L13: 13 | M13: 115269 | N13: 11.6 | O13: 121312 | P13: 12.2 | Q13: 133617 | R13: 13.4 | S13: 141210 | T13: 14.2 | U13: 121875 | V13: 12.2 | W13: 74727 | X13: 7.5 | Y13: 48492 | Z13: 4.9 | AA13: 214739 | AB13: 21.5
A14: Y Axis Title | F14: Mid-Hudson | G14: 140098 | H14: 5.8 | I14: 144593 | J14: 6 | K14: 322821 | L14: 13.5 | M14: 289976 | N14: 12.1 | O14: 288168 | P14: 12 | Q14: 301450 | R14: 12.6 | S14: 330234 | T14: 13.8 | U14: 295012 | V14: 12.3 | W14: 179828 | X14: 7.5 | Y14: 103872 | Z14: 4.3 | AA14: 541317 | AB14: 22.6
A15: Start at Zero | F15: NYS excl NYC | G15: 604728 | H15: 5.3 | I15: 640751 | J15: 5.6 | K15: 1454784 | L15: 12.8 | M15: 1442397 | N15: 12.7 | O15: 1393651 | P15: 12.3 | Q15: 1343897 | R15: 11.8 | S15: 1566110 | T15: 13.8 | U15: 1485429 | V15: 13.1 | W15: 919800 | X15: 8.1 | Y15: 504570 | Z15: 4.4 | AA15: 2369080 | AB15: 20.9
F16: NYS | G16: 1102961 | H16: 5.6 | I16: 1102946 | J16: 5.6 | K16: 2413200 | L16: 12.1 | M16: 2658703 | N16: 13.4 | O16: 2751639 | P16: 13.8 | Q16: 2422399 | R16: 12.2 | S16: 2638363 | T16: 13.3 | U16: 2425309 | V16: 12.2 | W16: 1511287 | X16: 7.6 | Y16: 845512 | Z16: 4.3 | AA16: 4109277 | AB16: 20.7
A18: Source Specifications
A19: Table ID
A20: URL
A21: Data Year
A22: Estimate Type
A23: Citation Month
A24: Citation Year
A25: Custom Text
A27: Note Specfications

Sheet Ethnicity-Population
A1: Name | B1: Population by Ethnicity, 2023
A2: Table/Figure/Both | B2: Table
A3: Object ID | B3: =IF($B$1="","",_xlfn.XLOOKUP($B$1,Master!$F$2:$F$308,Master!$G$2:$G$308,"")) -> tbl-ethnicity
G4: integer | H4: percent1 | I4: integer | J4: percent1
A5: Table Rules | E5: Enter Data | F5: Area | G5: Hispanic | I5: Non-Hispanic
A6: Multilevel Headers | B6: TRUE | G6: Total Population | H6: % | I6: Total Population | J6: %
A7: Data Type | B7: Percent | F7: Dutchess | G7: 44153 | H7: 14.9 | I7: 252991 | J7: 85.1
F8: Orange | G8: 93608 | H8: 23.2 | I8: 310232 | J8: 76.8
A9: Figure Rules | F9: Putnam | G9: 18676 | H9: 19.1 | I9: 79312 | J9: 80.9
A10: Figure Type | F10: Rockland | G10: 67951 | H10: 20 | I10: 270985 | J10: 80
A11: X Column | F11: Sullivan | G11: 14544 | H11: 18.4 | I11: 64603 | J11: 81.6
A12: Y Column | F12: Ulster | G12: 21562 | H12: 11.8 | I12: 160547 | J12: 88.2
A13: X Axis Title | F13: Westchester | G13: 269085 | H13: 27 | I13: 727803 | J13: 73
A14: Y Axis Title | F14: Mid-Hudson | G14: 529579 | H14: 22.1 | I14: 1866473 | J14: 77.9
A15: Start at Zero | F15: NYS excl NYC | G15: 1478113 | H15: 13 | I15: 9878004 | J15: 87
F16: NYS | G16: 3898652 | H16: 19.6 | I16: 15973667 | J16: 80.4
A18: Source Specifications
A19: Table ID
A20: URL
A21: Data Year
A22: Estimate Type
A23: Citation Month
A24: Citation Year
A25: Custom Text
A27: Note Specfications

Sheet Race-Population
A1: Name | B1: Population by Race, 2023
A2: Table/Figure/Both | B2: Table
A3: Object ID | B3: =IF($B$1="","",_xlfn.XLOOKUP($B$1,Master!$F$2:$F$308,Master!$G$2:$G$308,"")) -> tbl-race
G4: integer | H4: percent1 | I4: integer | J4: percent1 | K4: integer | L4: percent2 | M4: integer | N4: percent1 | O4: integer | P4: percent2 | Q4: integer | R4: percent2 | S4: integer | T4: percent1
A5: Table Rules | E5: Enter Data | F5: Area | G5: Non-Hispanic White | I5: Non-Hispanic Black or African American | K5: Non-Hispanic American Indian and Alaskan Native | M5: Non-Hispanic Asian | O5: Non-Hispanic Native Hawaiian and Other Pacific Islander | Q5: Non-Hispanic Other | S5: Non-Hispanic Two or More Races
A6: Multilevel Headers | B6: TRUE | G6: Total Population | H6: % | I6: Total Population | J6: % | K6: Total Population | L6: % | M6: Total Population | N6: % | O6: Total Population | P6: % | Q6: Total Population | R6: % | S6: Total Population | T6: %
F7: Dutchess | G7: 199670 | H7: 67.2 | I7: 28024 | J7: 9.4 | K7: 222 | L7: 0.07 | M7: 10044 | N7: 3.4 | O7: 117 | P7: 0.04 | Q7: 2206 | R7: 0.7 | S7: 12708 | T7: 4.3
F8: Orange | G8: 239186 | H8: 59.2 | I8: 42478 | J8: 10.5 | K8: 438 | L8: 0.11 | M8: 11223 | N8: 2.8 | O8: 26 | P8: 0.01 | Q8: 2563 | R8: 0.6 | S8: 14318 | T8: 3.5
A9: Figure Rules | F9: Putnam | G9: 70948 | H9: 72.4 | I9: 2894 | J9: 3 | K9: 81 | L9: 0.08 | M9: 2255 | N9: 2.3 | O9: 24 | P9: 0.02 | Q9: 788 | R9: 0.8 | S9: 2322 | T9: 2.4
A10: Figure Type | F10: Rockland | G10: 205539 | H10: 60.6 | I10: 35626 | J10: 10.5 | K10: 181 | L10: 0.05 | M10: 19772 | N10: 5.8 | O10: 38 | P10: 0.01 | Q10: 1921 | R10: 0.6 | S10: 7908 | T10: 2.3
A11: X Column | F11: Sullivan | G11: 53145 | H11: 67.1 | I11: 6263 | J11: 7.9 | K11: 120 | L11: 0.15 | M11: 1584 | N11: 2 | O11: 11 | P11: 0.01 | Q11: 533 | R11: 0.7 | S11: 2947 | T11: 3.7
A12: Y Column | F12: Ulster | G12: 133874 | H12: 73.5 | I12: 10347 | J12: 5.7 | K12: 66 | L12: 0.04 | M12: 3675 | N12: 2 | O12: 40 | P12: 0.02 | Q12: 2242 | R12: 1.2 | S12: 10303 | T12: 5.7
A13: X Axis Title | F13: Westchester | G13: 498855 | H13: 50 | I13: 128199 | J13: 12.9 | K13: 1197 | L13: 0.12 | M13: 59912 | N13: 6 | O13: 96 | P13: 0.01 | Q13: 10638 | R13: 1.1 | S13: 28906 | T13: 2.9
A14: Y Axis Title | F14: Mid-Hudson | G14: 1401217 | H14: 58.5 | I14: 253831 | J14: 10.6 | K14: 2305 | L14: 0.1 | M14: 108465 | N14: 4.5 | O14: 352 | P14: 0.01 | Q14: 20891 | R14: 0.9 | S14: 79412 | T14: 3.3
A15: Start at Zero | F15: NYS excl NYC | G15: 7942876 | H15: 69.9 | I15: 934322 | J15: 8.2 | K15: 21069 | L15: 0.19 | M15: 518716 | N15: 4.6 | O15: 2610 | P15: 0.02 | Q15: 70553 | R15: 0.6 | S15: 387858 | T15: 3.4
F16: NYS | G16: 10608842 | H16: 53.4 | I16: 2708094 | J16: 13.6 | K16: 37212 | L16: 0.19 | M16: 1754957 | N16: 8.8 | O16: 6220 | P16: 0.03 | Q16: 178956 | R16: 0.9 | S16: 679386 | T16: 3.4
A18: Source Specifications
A19: Table ID
A20: URL
A21: Data Year
A22: Estimate Type
A23: Citation Month
A24: Citation Year
A25: Custom Text
A27: Note Specfications

Sheet Spoken Lang-Population
A1: Name | B1: Population by Spoken Language, 2023
A2: Table/Figure/Both | B2: Table
A3: Object ID | B3: =IF($B$1="","",_xlfn.XLOOKUP($B$1,Master!$F$2:$F$308,Master!$G$2:$G$308,"")) -> tbl-language
G4: integer | H4: percent1 | I4: integer | J4: percent1 | K4: integer | L4: percent1 | M4: integer | N4: percent1 | O4: integer | P4: percent1 | Q4: integer | R4: percent2
A5: Table Rules | E5: Enter Data | F5: Area | G5: Only English | I5: Language other than English | K5: Spanish | M5: Other Indo-European languages | O5: Asian and Pacific Islander languages | Q5: Other languages
A6: Multilevel Headers | B6: TRUE | G6: Total Population | H6: % | I6: Total Population | J6: % | K6: Total Population | L6: % | M6: Total Population | N6: % | O6: Total Population | P6: % | Q6: Total Population | R6: %
F7: Dutchess | G7: 238585 | H7: 84.1 | I7: 44946 | J7: 15.9 | K7: 26003 | L7: 9.2 | M7: 10769 | N7: 3.8 | O7: 5267 | P7: 1.9 | Q7: 2907 | R7: 1
F8: Orange | G8: 266545 | H8: 70.8 | I8: 110152 | J8: 29.2 | K8: 55418 | L8: 15 | M8: 45346 | N8: 12 | O8: 6298 | P8: 1.7 | Q8: 3090 | R8: 0.8
A9: Figure Rules | F9: Putnam | G9: 73860 | H9: 79 | I9: 19607 | J9: 21 | K9: 11733 | L9: 13 | M9: 5687 | N9: 6.1 | O9: 1504 | P9: 1.6 | Q9: 683 | R9: 0.7
A10: Figure Type | F10: Rockland | G10: 174907 | H10: 56.4 | I10: 135072 | J10: 43.6 | K10: 46360 | L10: 15 | M10: 69600 | N10: 22.5 | O10: 12024 | P10: 3.9 | Q10: 7088 | R10: 2.3
A11: X Column | F11: Sullivan | G11: 59484 | H11: 79.9 | I11: 15007 | J11: 20.1 | K11: 8639 | L11: 12 | M11: 4877 | N11: 6.5 | O11: 819 | P11: 1.1 | Q11: 672 | R11: 0.9
A12: Y Column | F12: Ulster | G12: 152966 | H12: 87.8 | I12: 21217 | J12: 12.2 | K12: 11924 | L12: 6.8 | M12: 5602 | N12: 3.2 | O12: 2679 | P12: 1.5 | Q12: 1012 | R12: 0.6
A13: X Axis Title | F13: Westchester | G13: 619503 | H13: 65.7 | I13: 324103 | J13: 34.3 | K13: 196271 | L13: 21 | M13: 78915 | N13: 8.4 | O13: 32889 | P13: 3.5 | Q13: 16028 | R13: 1.7
A14: Y Axis Title | F14: Mid-Hudson | G14: 1585850 | H14: 54.2 | I14: 670104 | J14: 22.9 | K14: 356348 | L14: 12.2 | M14: 220796 | N14: 7.5 | O14: 61480 | P14: 2.1 | Q14: 31480 | R14: 1.1
A15: Start at Zero | F15: NYS excl NYC | G15: 8808643 | H15: 69.4 | I15: 1942746 | J15: 15.3 | K15: 940527 | L15: 12.2 | M15: 632717 | N15: 5 | O15: 258104 | P15: 2 | Q15: 111398 | R15: 0.9
F16: NYS | G16: 13017480 | H16: 69.4 | I16: 5751878 | J16: 30.6 | K16: 2762664 | L16: 15 | M16: 1679571 | N16: 8.9 | O16: 958133 | P16: 5.1 | Q16: 351510 | R16: 1.9
A18: Source Specifications
A19: Table ID
A20: URL
A21: Data Year
A22: Estimate Type
A23: Citation Month
A24: Citation Year
A25: Custom Text
A27: Note Specfications

Sheet 25 Years+-Population
A1: Name | B1: Population 25 Years and Older, 2023
A2: Table/Figure/Both | B2: Table
A3: Object ID | B3: =IF($B$1="","",_xlfn.XLOOKUP($B$1,Master!$F$2:$F$308,Master!$G$2:$G$308,"")) -> tbl-pop-25
G4: integer
A5: Table Rules | E5: Enter Data | F5: Area | G5: Total Population
A6: Multilevel Headers | B6: FALSE | F6: Dutchess | G6: 211380
F7: Orange | G7: 258632
F8: Putnam | G8: 71149
A9: Figure Rules | F9: Rockland | G9: 208594
A10: Figure Type | F10: Sullivan | G10: 55761
A11: X Column | F11: Ulster | G11: 134325
A12: Y Column | F12: Westchester | G12: 697202
A13: X Axis Title | F13: Mid-Hudson | G13: 1637043
A14: Y Axis Title | F14: NYS excl NYC | G14: 7905485
A15: Start at Zero | F15: NYS | G15: 13996138
A18: Source Specifications
A19: Table ID
A20: URL
A21: Data Year
A22: Estimate Type
A23: Citation Month
A24: Citation Year
A25: Custom Text
A27: Note Specfications

Sheet Educational Attainment-Pop
A1: Name | B1: Population by Educational Attainment, 2023
A2: Table/Figure/Both | B2: Table
A3: Object ID | B3: =IF($B$1="","",_xlfn.XLOOKUP($B$1,Master!$F$2:$F$308,Master!$G$2:$G$308,"")) -> tbl-education-base
G4: integer | H4: percent1 | I4: integer | J4: percent1 | K4: integer | L4: percent1 | M4: integer | N4: percent1 | O4: integer | P4: percent1 | Q4: integer | R4: percent1 | S4: integer | T4: percent1
A5: Table Rules | E5: Enter Data | F5: Area | G5: Less than 9th grade | I5: 9th to 12th grade, no diploma | K5: High school graduate or equivalent | M5: Some college, no degree | O5: Associate degree | Q5: Bachelor's degree | S5: Graduate or professional degree
A6: Multilevel Headers | B6: TRUE | G6: N | H6: % | I6: N | J6: % | K6: N | L6: % | M6: N | N6: % | O6: N | P6: % | Q6: N | R6: % | S6: N | T6: %
F7: Dutchess | G7: 6262 | H7: 3 | I7: 11055 | J7: 5.2 | K7: 52992 | L7: 25.1 | M7: 35689 | N7: 16.9 | O7: 21410 | P7: 10.1 | Q7: 44414 | R7: 21 | S7: 39558 | T7: 18.7
F8: Orange | G8: 10091 | H8: 3.9 | I8: 16609 | J8: 6.4 | K8: 72466 | L8: 28 | M8: 49355 | N8: 19.1 | O8: 26722 | P8: 10.3 | Q8: 46977 | R8: 18.2 | S8: 36412 | T8: 14.1
A9: Figure Rules | F9: Putnam | G9: 2255 | H9: 3.2 | I9: 2536 | J9: 3.6 | K9: 17647 | L9: 24.8 | M9: 11728 | N9: 16.5 | O9: 6002 | P9: 8.4 | Q9: 17222 | R9: 24.2 | S9: 13759 | T9: 19.3
A10: Figure Type | F10: Rockland | G10: 11800 | H10: 5.7 | I10: 13858 | J10: 6.6 | K10: 45118 | L10: 21.6 | M10: 33790 | N10: 16.2 | O10: 16169 | P10: 7.8 | Q10: 48405 | R10: 23.2 | S10: 39454 | T10: 18.9
A11: X Column | F11: Sullivan | G11: 2755 | H11: 4.9 | I11: 4129 | J11: 7.4 | K11: 16623 | L11: 29.8 | M11: 9973 | N11: 17.9 | O11: 5728 | P11: 10.3 | Q11: 9476 | R11: 17 | S11: 7077 | T11: 12.7
A12: Y Column | F12: Ulster | G12: 3463 | H12: 2.6 | I12: 7622 | J12: 5.7 | K12: 37570 | L12: 28 | M12: 22968 | N12: 17.1 | O12: 12934 | P12: 9.6 | Q12: 27094 | R12: 20.2 | S12: 22674 | T12: 16.9
A13: X Axis Title | F13: Westchester | G13: 37761 | H13: 5.4 | I13: 36459 | J13: 5.2 | K13: 124954 | L13: 17.9 | M13: 87534 | N13: 12.6 | O13: 44393 | P13: 6.4 | Q13: 181482 | R13: 26 | S13: 184619 | T13: 26.5
A14: Y Axis Title | F14: Mid-Hudson | G14: 74387 | H14: 4.5 | I14: 92268 | J14: 5.6 | K14: 367370 | L14: 22.4 | M14: 251037 | N14: 15.3 | O14: 133358 | P14: 8.1 | Q14: 375070 | R14: 22.9 | S14: 343553 | T14: 21
A15: Start at Zero | F15: NYS excl NYC | G15: 300738 | H15: 3.8 | I15: 403754 | J15: 5.1 | K15: 2039454 | L15: 25.8 | M15: 1277348 | N15: 16.2 | O15: 847708 | P15: 10.7 | Q15: 1643943 | R15: 20.8 | S15: 1392540 | T15: 17.6
F16: NYS | G16: 836124 | H16: 6 | I16: 862413 | J16: 6.2 | K16: 3437438 | L16: 24.6 | M16: 2081783 | N16: 14.9 | O16: 1242877 | P16: 8.9 | Q16: 3083769 | R16: 22 | S16: 2451734 | T16: 17.5
A18: Source Specifications
A19: Table ID
A20: URL
A21: Data Year
A22: Estimate Type
A23: Citation Month
A24: Citation Year
A25: Custom Text
A27: Note Specfications

Sheet Total Households
A1: Name | B1: Total Households, 2023
A2: Table/Figure/Both | B2: Table
A3: Object ID | B3: =IF($B$1="","",_xlfn.XLOOKUP($B$1,Master!$F$2:$F$308,Master!$G$2:$G$308,"")) -> tbl-households
G4: integer
A5: Table Rules | E5: Enter Data | G5: Households
A6: Multilevel Headers | B6: FALSE | F6: Dutchess | G6: 115184
F7: Orange | G7: 137311
F8: Putnam | G8: 35054
A9: Figure Rules | F9: Rockland | G9: 103284
A10: Figure Type | F10: Sullivan | G10: 30215
A11: X Column | F11: Ulster | G11: 73105
A12: Y Column | F12: Westchester | G12: 370256
A13: X Axis Title | F13: Mid-Hudson | G13: 864409
A14: Y Axis Title | F14: NYS excl NYC | G14: 4355640
A15: Start at Zero | F15: NYS | G15: 7668956
A18: Source Specifications
A19: Table ID
A20: URL
A21: Data Year
A22: Estimate Type
A23: Citation Month
A24: Citation Year
A25: Custom Text
A27: Note Specfications

Sheet Households by Income
A1: Name | B1: Households by Income, 2023
A2: Table/Figure/Both | B2: Table
A3: Object ID | B3: =IF($B$1="","",_xlfn.XLOOKUP($B$1,Master!$F$2:$F$308,Master!$G$2:$G$308,"")) -> tbl-income
G4: integer | H4: percent1 | I4: integer | J4: percent1 | K4: integer | L4: percent1 | M4: integer | N4: percent1 | O4: integer | P4: percent1 | Q4: integer | R4: percent1 | S4: integer | T4: percent1 | U4: integer | V4: percent1 | W4: integer | X4: percent1 | Y4: integer | Z4: percent1
A5: Table Rules | E5: Enter Data | F5: Area | G5: <$10,000 | I5: $10,000-$14,999 | K5: $15,000-$24,999 | M5: $25,000-$34,999 | O5: $35,000-$49,999 | Q5: $50,000-$74,999 | S5: $75,000-$99,999 | U5: $100,000-$149,999 | W5: $150,000-$199,999 | Y5: >$200,000
A6: Multilevel Headers | B6: TRUE | G6: Total Population | H6: % | I6: Total Population | J6: % | K6: Total Population | L6: % | M6: Total Population | N6: % | O6: Total Population | P6: % | Q6: Total Population | R6: % | S6: Total Population | T6: % | U6: Total Population | V6: % | W6: Total Population | X6: % | Y6: Total Population | Z6: %
F7: Dutchess | G7: 4723 | H7: 4.1 | I7: 2649 | J7: 2.3 | K7: 5298 | L7: 4.6 | M7: 6105 | N7: 5.3 | O7: 9906 | P7: 8.6 | Q7: 15780 | R7: 13.7 | S7: 14513 | T7: 12.6 | U7: 22346 | V7: 19.4 | W7: 13822 | X7: 12 | Y7: 20042 | Z7: 17.4
F8: Orange | G8: 5492 | H8: 4 | I8: 4119 | J8: 3 | K8: 8651 | L8: 6.3 | M8: 7003 | N8: 5.1 | O8: 10985 | P8: 8 | Q8: 18125 | R8: 13.2 | S8: 16340 | T8: 11.9 | U8: 27188 | V8: 19.8 | W8: 18125 | X8: 13.2 | Y8: 21421 | Z8: 15.6
A9: Figure Rules | F9: Putnam | G9: 841 | H9: 2.4 | I9: 631 | J9: 1.8 | K9: 1472 | L9: 4.2 | M9: 1402 | N9: 4 | O9: 2033 | P9: 5.8 | Q9: 3926 | R9: 11.2 | S9: 3365 | T9: 9.6 | U9: 7326 | V9: 20.9 | W9: 5503 | X9: 15.7 | Y9: 8553 | Z9: 24.4
A10: Figure Type | F10: Rockland | G10: 3822 | H10: 3.7 | I10: 2169 | J10: 2.1 | K10: 5784 | L10: 5.6 | M10: 5474 | N10: 5.3 | O10: 7746 | P10: 7.5 | Q10: 11878 | R10: 11.5 | S10: 10328 | T10: 10 | U10: 18281 | V10: 17.7 | W10: 12394 | X10: 12 | Y10: 25408 | Z10: 24.6
A11: X Column | F11: Sullivan | G11: 1420 | H11: 4.7 | I11: 1481 | J11: 4.9 | K11: 2327 | L11: 7.7 | M11: 2447 | N11: 8.1 | O11: 3384 | P11: 11.2 | Q11: 5137 | R11: 17 | S11: 3807 | T11: 12.6 | U11: 4442 | V11: 14.7 | W11: 2478 | X11: 8.2 | Y11: 3293 | Z11: 10.9
A12: Y Column | F12: Ulster | G12: 4021 | H12: 5.5 | I12: 2778 | J12: 3.8 | K12: 4606 | L12: 6.3 | M12: 4752 | N12: 6.5 | O12: 7384 | P12: 10.1 | Q12: 10527 | R12: 14.4 | S12: 8334 | T12: 11.4 | U12: 13378 | V12: 18.3 | W12: 7384 | X12: 10.1 | Y12: 9942 | Z12: 13.6
A13: X Axis Title | F13: Westchester | G13: 17402 | H13: 4.7 | I13: 9997 | J13: 2.7 | K13: 17032 | L13: 4.6 | M13: 15180 | N13: 4.1 | O13: 27029 | P13: 7.3 | Q13: 37766 | R13: 10.2 | S13: 36285 | T13: 9.8 | U13: 59241 | V13: 16 | W13: 39988 | X13: 10.8 | Y13: 110336 | Z13: 29.8
A14: Y Axis Title | F14: Mid-Hudson | G14: 37721 | H14: 4.4 | I14: 23824 | J14: 2.8 | K14: 45169 | L14: 5.2 | M14: 42364 | N14: 4.9 | O14: 68467 | P14: 7.9 | Q14: 103139 | R14: 11.9 | S14: 92973 | T14: 10.8 | U14: 152202 | V14: 17.6 | W14: 99694 | X14: 11.5 | Y14: 198996 | Z14: 23
A15: Start at Zero | F15: NYS excl NYC | G15: 201885 | H15: 4.6 | I15: 142135 | J15: 3.3 | K15: 266550 | L15: 6.1 | M15: 266736 | N15: 6.1 | O15: 402990 | P15: 9.3 | Q15: 617645 | R15: 14.2 | S15: 516423 | T15: 11.9 | U15: 781447 | V15: 17.9 | W15: 466426 | X15: 10.7 | Y15: 701072 | Z15: 16.1
F16: NYS | G16: 437130 | H16: 5.7 | I16: 314427 | J16: 4.1 | K16: 498482 | L16: 6.5 | M16: 475475 | N16: 6.2 | O16: 697875 | P16: 9.1 | Q16: 1058316 | R16: 13.8 | S16: 874261 | T16: 11.4 | U16: 1288385 | V16: 16.8 | W16: 774565 | X16: 10.1 | Y16: 1257709 | Z16: 16.4
A18: Source Specifications
A19: Table ID
A20: URL
A21: Data Year
A22: Estimate Type
A23: Citation Month
A24: Citation Year
A25: Custom Text
A27: Note Specfications

Sheet Veteran Status-Population
A1: Name | B1: Population by Veteran Status, 2023
A2: Table/Figure/Both | B2: Table
A3: Object ID | B3: =IF($B$1="","",_xlfn.XLOOKUP($B$1,Master!$F$2:$F$308,Master!$G$2:$G$308,"")) -> tbl-veteran
G4: integer | H4: integer | I4: percent1
A5: Table Rules | E5: Enter Data | F5: Area | G5: Civilian Population 18 Years and Older | H5: Civilian Veterans
A6: Multilevel Headers | B6: TRUE | G6: Total Population | H6: Total Population | I6: %
F7: Dutchess | G7: 241517 | H7: 11694 | I7: 4.8
F8: Orange | G8: 296319 | H8: 16695 | I8: 5.6
A9: Figure Rules | F9: Putnam | G9: 78712 | H9: 3320 | I9: 4.2
A10: Figure Type | F10: Rockland | G10: 239088 | H10: 7130 | I10: 3
A11: X Column | F11: Sullivan | G11: 62181 | H11: 3713 | I11: 6
A12: Y Column | F12: Ulster | G12: 150409 | H12: 6711 | I12: 4.5
A13: X Axis Title | F13: Westchester | G13: 781837 | H13: 23744 | I13: 3
A14: Y Axis Title | F14: Mid-Hudson | G14: 1850063 | H14: 73007 | I14: 3.9
A15: Start at Zero | F15: NYS excl NYC | G15: 8964773 | H15: 478417 | I15: 5.3
F16: NYS | G16: 15737168 | H16: 607728 | I16: 3.9
A18: Source Specifications
A19: Table ID
A20: URL
A21: Data Year
A22: Estimate Type
A23: Citation Month
A24: Citation Year
A25: Custom Text
A27: Note Specfications

Sheet Type of Disability-Population
A1: Name | B1: Percentage of Population by Type of Disability, 2023
A2: Table/Figure/Both | B2: Table
A3: Object ID | B3: =IF($B$1="","",_xlfn.XLOOKUP($B$1,Master!$F$2:$F$308,Master!$G$2:$G$308,"")) -> tbl-disability
G4: percent1 | H4: percent1 | I4: percent1 | J4: percent1 | K4: percent1 | L4: percent1 | M4: percent1
A5: Table Rules | E5: Enter Data | G5: Total with Any Disability | H5: Hearing Difficulty | I5: Vision Difficulty | J5: Cognitive Difficulty | K5: Ambulatory Difficulty | L5: Self-Care Difficulty | M5: Independent Living Difficulty
A6: Multilevel Headers | B6: FALSE | F6: Dutchess | G6: 12.2 | H6: 3.5 | I6: 2 | J6: 4.7 | K6: 6.3 | L6: 2.6 | M6: 5.9
F7: Orange | G7: 11.7 | H7: 3.2 | I7: 2.1 | J7: 5.4 | K7: 6.3 | L7: 2.9 | M7: 6.2
F8: Putnam | G8: 9.6 | H8: 2.8 | I8: 1.4 | J8: 3.5 | K8: 5.4 | L8: 2.4 | M8: 4.6
A9: Figure Rules | F9: Rockland | G9: 8.7 | H9: 2.7 | I9: 1.4 | J9: 3.4 | K9: 4.4 | L9: 2.2 | M9: 4.5
A10: Figure Type | F10: Sullivan | G10: 15.9 | H10: 4.4 | I10: 3 | J10: 6.4 | K10: 9.1 | L10: 3.7 | M10: 7.2
A11: X Column | F11: Ulster | G11: 14.4 | H11: 4.2 | I11: 2.3 | J11: 5.1 | K11: 7.4 | L11: 3 | M11: 6
A12: Y Column | F12: Westchester | G12: 9.5 | H12: 2.5 | I12: 1.6 | J12: 3.7 | K12: 5.3 | L12: 2.3 | M12: 4.8
A13: X Axis Title | F13: Mid-Hudson | G13: 10.2 | H13: 2.8 | I13: 1.7 | J13: 3.8 | K13: 5.2 | L13: 2.3 | M13: 3.9
A14: Y Axis Title | F14: NYS | G14: 11.6 | H14: 2.8 | I14: 2.1 | J14: 4.5 | K14: 6.6 | L14: 2.7 | M14: 5.7
A15: Start at Zero
A18: Source Specifications
A19: Table ID
A20: URL
A21: Data Year
A22: Estimate Type
A23: Citation Month
A24: Citation Year
A25: Custom Text
A27: Note Specfications

Sheet No Vehicle
A1: Name | B1: Percentage of Households with No Vehicles Available, 2021–2023
A2: Table/Figure/Both | B2: Figure
A3: Object ID | B3: =IF($B$1="","",_xlfn.XLOOKUP($B$1,Master!$F$2:$F$308,Master!$G$2:$G$308,"")) -> tbl-no-vehicles
A4: Figure ID | B4: =IF($B$1="","",_xlfn.XLOOKUP($B$1,Master!$F$2:$F$308,Master!$H$2:$H$308,"")) -> fig-no-vehicles | F4: integer | G4: percent1 | H4: percent1 | I4: percent1 | J4: percent1 | K4: percent1 | L4: percent1 | M4: percent1 | N4: percent1
A5: Table Rules | E5: Enter Data | F5: Year | G5: Dutchess | H5: Orange | I5: Putnam | J5: Rockland | K5: Sullivan | L5: Ulster | M5: Westchester | N5: NYS
A6: Multilevel Headers | B6: FALSE | F6: 2017–2021 | G6: 7.2 | H6: 8.9 | I6: 4.7 | J6: 10.4 | K6: 10.4 | L6: 6.8 | M6: 14.3 | N6: 28.9
F7: 2018–2022 | G7: 7.2 | H7: 8.6 | I7: 4.1 | J7: 9.9 | K7: 9.9 | L7: 7.2 | M7: 14.2 | N7: 29
F8: 2019–2023 | G8: 7 | H8: 8.6 | I8: 4.2 | J8: 9.7 | K8: 8.8 | L8: 7.5 | M8: 14.2 | N8: 29
A9: Figure Rules
A10: Figure Type | B10: Line
A11: X Column | B11: Year
A12: Y Column | B12: Percent
A13: X Axis Title | B13: =F5 -> Year
A14: Y Axis Title | B14: Percent
A15: Start at Zero | B15: TRUE
A18: Source Specifications
A19: Table ID
A20: URL | B20: https://data.census.gov/table/ACSDP5Y2022.DP04?q=dp04&g=050XX00US36105,36027,36071,36119,36087,36079,36111_04 0XX00US36
A21: Data Year | B21: 2021–2023
A22: Estimate Type
A23: Citation Month | B23: April
A24: Citation Year | B24: 2025
A25: Custom Text
A27: Note Specifications
A28: The American Community Survey asks respondents how many automobiles, vans, and trucks of one-ton capacity or less are kept at home for use by members of the household. 2023 ACS includes 2019–2023

Sheet Mode To Work
A1: Name | B1: Percentage of Workers by Mode of Transportation to Work, 2023
A2: Table/Figure/Both | B2: Figure
A3: Object ID | B3: =IF($B$1="","",_xlfn.XLOOKUP($B$1,Master!$F$2:$F$308,Master!$G$2:$G$308,"")) -> tbl-mode-to-work
A4: Figure ID | B4: =IF($B$1="","",_xlfn.XLOOKUP($B$1,Master!$F$2:$F$308,Master!$H$2:$H$308,"")) -> fig-mode-to-work | G4: percent1 | H4: percent1 | I4: percent1 | J4: percent1 | K4: percent1 | L4: percent1 | M4: percent1 | N4: percent1
A5: Table Rules | E5: Enter Data | G5: Dutchess | H5: Orange | I5: Putnam | J5: Rockland | K5: Sullivan | L5: Ulster | M5: Westchester | N5: NYS
A6: Multilevel Headers | B6: FALSE | F6: Drove Alone | G6: 71.4 | H6: 69.8 | I6: 70.6 | J6: 66.6 | K6: 74.1 | L6: 71.7 | M6: 51.9 | N6: 50
F7: Carpooled | G7: 7.5 | H7: 9.6 | I7: 7.6 | J7: 8.5 | K7: 8.8 | L7: 6.7 | M7: 7.2 | N7: 6.3
F8: Public transportation | G8: 3.7 | H8: 4.4 | I8: 5.6 | J8: 6.2 | K8: 1.2 | L8: 2.1 | M8: 17.8 | N8: 22.4
A9: Figure Rules | F9: Walked | G9: 2.3 | H9: 3.1 | I9: 1.5 | J9: 3.1 | K9: 2.4 | L9: 2.4 | M9: 3.7 | N9: 5.3
A10: Figure Type | B10: Clustered Bar | F10: Taxicab, motorcycle, bicycle, or other means | G10: 1.7 | H10: 2 | I10: 1 | J10: 2.8 | K10: 1.9 | L10: 1.8 | M10: 2.1 | N10: 2.6
A11: X Column | B11: Category | F11: Worked from home | G11: 13.4 | H11: 11.1 | I11: 13.7 | J11: 12.7 | K11: 11.6 | L11: 15.3 | M11: 17.3 | N11: 13.3
A12: Y Column | B12: Percent
A13: X Axis Title
A14: Y Axis Title | B14: Percent
A15: Start at Zero | B15: TRUE
A18: Source Specifications
A19: Table ID
A20: URL | B20: https://data.census.gov/table/ACSDT5Y2023.B08141?q=b08141&g=050XX00US36105,36027,36071,36119,36087,36079,3611 1_040XX00US36
A21: Data Year | B21: 2023
A22: Estimate Type
A23: Citation Month | B23: April
A24: Citation Year | B24: 2025
A25: Custom Text
A27: Note Specifications
A28: The American Community Survey asks respondents how they usually got to work last week. For respondents who use multiple transportation modes they are restricted to the single method of transportation used for the longest distance. 2023 ACS includes 2019–2023

Sheet Mean Time Work
A1: Name | B1: Mean Travel Time to Work, 2021–2023
A2: Table/Figure/Both | B2: Figure
A3: Object ID | B3: =IF($B$1="","",_xlfn.XLOOKUP($B$1,Master!$F$2:$F$308,Master!$G$2:$G$308,"")) -> tbl-mean-time-work
A4: Figure ID | B4: =IF($B$1="","",_xlfn.XLOOKUP($B$1,Master!$F$2:$F$308,Master!$H$2:$H$308,"")) -> fig-mean-time-work | F4: integer | G4: percent1 | H4: percent1 | I4: percent1 | J4: percent1 | K4: percent1 | L4: percent1 | M4: percent1 | N4: percent1
A5: Table Rules | E5: Enter Data | G5: Dutchess | H5: Orange | I5: Putnam | J5: Rockland | K5: Sullivan | L5: Ulster | M5: Westchester | N5: NYS
A6: Multilevel Headers | B6: FALSE | F6: 2017–2021 | G6: 32 | H6: 34.1 | I6: 39.2 | J6: 31.2 | K6: 28.6 | L6: 28.6 | M6: 34.8 | N6: 33.3
F7: 2018–2022 | G7: 32.3 | H7: 34.1 | I7: 39.9 | J7: 31 | K7: 28.1 | L7: 28.1 | M7: 34.8 | N7: 33.2
F8: 2019–2023 | G8: 31.4 | H8: 34.2 | I8: 39.5 | J8: 30.3 | K8: 27.8 | L8: 27.8 | M8: 34.7 | N8: 32.8
A9: Figure Rules
A10: Figure Type | B10: Line
A11: X Column | B11: Period
A12: Y Column | B12: Minutes
A13: X Axis Title
A14: Y Axis Title | B14: Minutes
A15: Start at Zero | B15: TRUE
A18: Source Specifications
A19: Table ID
A20: URL | B20: https://data.census.gov/table/ACSDP5Y2023.DP03?q=DP03&g=050XX00US36105,36027,36071,36119,36087,36079,36111_04 0XX00US36
A21: Data Year | B21: 2021–2023
A22: Estimate Type
A23: Citation Month | B23: April
A24: Citation Year | B24: 2025
A25: Custom Text
A27: Note Specifications
A28: The American Community Survey asks respondents in the workforce how many minutes it usually takes them to get from home to work. The travel time refers to a one-way trip on a typical day. This includes time spent waiting for public transportation, picking up passengers in carpools, and time spent in other activities related to getting to work. Sullivan County and Ulster County do have the same data according to the Census. 2023 ACS includes 2019–2023.

Sheet DC Top Affect Health
A1: Name | B1: Top Rated Issues That Affect Health in Dutchess County (n = 109)
A2: Table/Figure/Both | B2: Figure
A3: Object ID | B3: =IF($B$1="","",_xlfn.XLOOKUP($B$1,Master!$F$2:$F$308,Master!$G$2:$G$308,"")) -> tbl-DC-affect-health
A4: Figure ID | B4: =IF($B$1="","",_xlfn.XLOOKUP($B$1,Master!$F$2:$F$308,Master!$H$2:$H$308,"")) -> fig-DC-affect-health | F4: percent1 | G4: percent1 | H4: percent1 | I4: percent1 | J4: percent1 | K4: percent1 | L4: percent1 | M4: percent1 | N4: percent1 | O4: percent1
A5: Table Rules | E5: Enter Data | F5: Access to affordable, nutritious food | G5: Access to mental health providers | H5: Access to affordable, decent and safe housing | I5: Access to specialty services/providers | J5: Access to affordable, reliable transportation | K5: Access to affordable health insurance | L5: Access to medical providers | M5: Access to culturally sensitive health care providers | N5: Access to high quality education | O5: Access to clean water and non-polluted air
A6: Multilevel Headers | B6: FALSE | F6: 48.6 | G6: 47.7 | H6: 46.8 | I6: 42.2 | J6: 40.4 | K6: 34.9 | L6: 18.4 | M6: 12 | N6: 8.3 | O6: 0.9
A9: Figure Rules
A10: Figure Type | B10: Bar
A11: X Column | B11: Category
A12: Y Column | B12: Percent
A13: X Axis Title
A14: Y Axis Title | B14: Percent
A15: Start at Zero | B15: TRUE
A18: Source Specifications
A19: Table ID
A20: URL
A21: Data Year
A22: Estimate Type
A23: Citation Month
A24: Citation Year
A25: Custom Text
A27: Note Specifications

Sheet DC Top Barriers
A1: Name | B1: Top Rated Barriers to Achieving Better Health in Dutchess County (n = 109)
A2: Table/Figure/Both | B2: Figure
A3: Object ID | B3: =IF($B$1="","",_xlfn.XLOOKUP($B$1,Master!$F$2:$F$308,Master!$G$2:$G$308,"")) -> tbl-DC-achieve-health
A4: Figure ID | B4: =IF($B$1="","",_xlfn.XLOOKUP($B$1,Master!$F$2:$F$308,Master!$H$2:$H$308,"")) -> fig-DC-achieve-health | F4: percent1 | G4: percent1 | H4: percent1 | I4: percent1 | J4: percent1 | K4: percent1 | L4: percent1 | M4: percent1 | N4: percent1 | O4: percent1 | P4: percent1 | Q4: percent1
A5: Table Rules | E5: Enter Data | F5: Knowledge of existing resources | G5: Health literacy | H5: Geographic location living in a rural area | I5: Having someone to help them understand their medical condition | J5: Having someone help them understand insurance | K5: Substance Use Disorder (SUD) or Alcohol Use Disorder (AUD) | L5: Other | M5: Geographic location- living in an urban area | N5: Attainment of education | O5: Having a safe place to play and/or exercise | P5: Quality of education | Q5: Cultural customs
A6: Multilevel Headers | B6: FALSE | F6: 77.1 | G6: 51.4 | H6: 34.9 | I6: 32.1 | J6: 25.7 | K6: 25.7 | L6: 17.4 | M6: 9.2 | N6: 7.3 | O6: 6.4 | P6: 6.4 | Q6: 6.4
A9: Figure Rules
A10: Figure Type | B10: Bar
A11: X Column | B11: Category
A12: Y Column | B12: Percent
A13: X Axis Title
A14: Y Axis Title | B14: Percent
A15: Start at Zero | B15: TRUE
A18: Source Specifications
A19: Table ID
A20: URL
A21: Data Year
A22: Estimate Type
A23: Citation Month
A24: Citation Year
A25: Custom Text
A27: Note Specifications

Sheet DC Impact Health
A1: Name | B1: The Impact of Health Issues in Dutchess County (n = 106)
A2: Table/Figure/Both | B2: Both
A3: Object ID | B3: =IF($B$1="","",_xlfn.XLOOKUP($B$1,Master!$F$2:$F$308,Master!$G$2:$G$308,"")) -> tbl-DC-impact-hlth-issue
A4: Figure ID | B4: =IF($B$1="","",_xlfn.XLOOKUP($B$1,Master!$F$2:$F$308,Master!$H$2:$H$308,"")) -> fig-DC-impact-hlth-issue | G4: percent1 | H4: percent1 | I4: percent1 | J4: percent1 | K4: percent1 | L4: percent1
A5: Table Rules | E5: Enter Data | F5: Likert Scale | G5: Chronic Disease | H5: Health Disparities | I5: Mental Health and Substance Use Issues | J5: Maternal and Child Health Issues | K5: Environmental Factors | L5: Communicable Diseases
A6: Multilevel Headers | B6: FALSE | F6: 1 | G6: 6.7 | H6: 3.9 | I6: 4.9 | J6: 22.3 | K6: 17.6 | L6: 21.2
F7: 2 | G7: 3.8 | H7: 8.7 | I7: 6.9 | J7: 12.6 | K7: 17.7 | L7: 19.2
F8: 3 | G8: 21 | H8: 18.5 | I8: 13.7 | J8: 26.2 | K8: 24.5 | L8: 28.9
A9: Figure Rules | F9: 4 | G9: 16.2 | H9: 25.2 | I9: 22.6 | J9: 14.6 | K9: 19.6 | L9: 14.4
A10: Figure Type | B10: Clustered Bar | F10: 5 | G10: 52.4 | H10: 43.7 | I10: 52 | J10: 24.3 | K10: 19.6 | L10: 14.4
A11: X Column | B11: Likert Scale (1 = Very Little Impact and 5 = Highly Impacted)
A12: Y Column
A13: X Axis Title | B13: Likert Scale (1 = Very Little Impact and 5 = Highly Impacted)
A14: Y Axis Title | B14: Percent
A15: Start at Zero | B15: TRUE
A16: Pivot for Chart | B16: TRUE
A18: Source Specifications
A19: Table ID
A20: URL
A21: Data Year
A22: Estimate Type
A23: Citation Month
A24: Citation Year
A25: Custom Text
A27: Note Specifications
A28: 1 is Very Listtle to 5 is highly impacted

Sheet DC Impact SDOH
A1: Name | B1: The Impact of the Social Determinants of Health in Dutchess County (n = 103)
A2: Table/Figure/Both | B2: Figure
A3: Object ID | B3: =IF($B$1="","",_xlfn.XLOOKUP($B$1,Master!$F$2:$F$308,Master!$G$2:$G$308,"")) -> tbl-DC-impact-sdoh
A4: Figure ID | B4: =IF($B$1="","",_xlfn.XLOOKUP($B$1,Master!$F$2:$F$308,Master!$H$2:$H$308,"")) -> fig-DC-impact-sdoh | F4: percent1 | G4: percent1 | H4: percent1 | I4: percent1 | J4: percent1 | K4: percent1
A5: Table Rules | E5: Enter Data | F5: Economic | G5: Mental Wellbeing & Substance Use | H5: Health Insurance Coverage & Access to Care | I5: Safe & Healthy Communities | J5: Healthy Children | K5: Pre K - Grade 12 Student Success & Educational Attainment
A6: Multilevel Headers | B6: FALSE | F6: 77.7 | G6: 73.8 | H6: 50 | I6: 48.5 | J6: 28.2 | K6: 25.2
A9: Figure Rules
A10: Figure Type | B10: Bar
A11: X Column | B11: Category
A12: Y Column | B12: Percent
A13: X Axis Title
A14: Y Axis Title | B14: Percent
A15: Start at Zero | B15: TRUE
A18: Source Specifications
A19: Table ID
A20: URL
A21: Data Year
A22: Estimate Type
A23: Citation Month
A24: Citation Year
A25: Custom Text
A27: Note Specifications

Sheet DC Impact Eco Wellbeing
A1: Name | B1: The Impact of Economic Wellbeing in Dutchess County (n = 103)
A2: Table/Figure/Both | B2: Both
A3: Object ID | B3: =IF($B$1="","",_xlfn.XLOOKUP($B$1,Master!$F$2:$F$308,Master!$G$2:$G$308,"")) -> tbl-DC-eco-wellbeing
A4: Figure ID | B4: =IF($B$1="","",_xlfn.XLOOKUP($B$1,Master!$F$2:$F$308,Master!$H$2:$H$308,"")) -> fig-DC-eco-wellbeing | G4: percent1 | H4: percent1 | I4: percent1 | J4: percent1
A5: Table Rules | E5: Enter Data | F5: Likert Scale | G5: Poverty | H5: Unemployment | I5: Nutrition Security | J5: Housing Stability & Affordability
A6: Multilevel Headers | B6: FALSE | F6: 1 | G6: 3.9 | H6: 7 | I6: 5 | J6: 3.6
F7: 2 | G7: 5.8 | H7: 10.2 | I7: 7 | J7: 8.8
F8: 3 | G8: 24.3 | H8: 26.3 | I8: 28 | J8: 19.5
A9: Figure Rules | F9: 4 | G9: 12.6 | H9: 29 | I9: 23 | J9: 21.1
A10: Figure Type | B10: Clustered Bar | F10: 5 | G10: 53.4 | H10: 27.6 | I10: 37 | J10: 47.1
A11: X Column | B11: Likert Scale (1 = Very Little Impact and 5 = Highly Impacted)
A12: Y Column
A13: X Axis Title | B13: Likert Scale (1 = Very Little Impact and 5 = Highly Impacted)
A14: Y Axis Title | B14: Percent
A15: Start at Zero | B15: TRUE
A16: Pivot for Chart | B16: TRUE
A18: Source Specifications
A19: Table ID
A20: URL
A21: Data Year
A22: Estimate Type
A23: Citation Month
A24: Citation Year
A25: Custom Text
A27: Note Specifications

Sheet DC Impact MH & SU
A1: Name | B1: The Impact of Mental Wellbeing & Substance Use in Dutchess County (n = 101)
A2: Table/Figure/Both | B2: Both
A3: Object ID | B3: =IF($B$1="","",_xlfn.XLOOKUP($B$1,Master!$F$2:$F$308,Master!$G$2:$G$308,"")) -> tbl-DC-impact-mhsu
A4: Figure ID | B4: =IF($B$1="","",_xlfn.XLOOKUP($B$1,Master!$F$2:$F$308,Master!$H$2:$H$308,"")) -> fig-DC-impact-mhsu | G4: percent1 | H4: percent1 | I4: percent1 | J4: percent1 | K4: percent1 | L4: percent1
A5: Table Rules | E5: Enter Data | F5: Likert Scale | G5: Anxiety & Stress | H5: Suicide | I5: Depression | J5: Substance Use | K5: Adverse Childhood Experiences | L5: Healthy Eating
A6: Multilevel Headers | B6: FALSE | F6: 1 | G6: 0 | H6: 20.4 | I6: 2 | J6: 11.1 | K6: 4 | L6: 5
F7: 2 | G7: 2.6 | H7: 17.4 | I7: 12 | J7: 11.1 | K7: 10.1 | L7: 5.9
F8: 3 | G8: 12.4 | H8: 27.6 | I8: 17 | J8: 23.2 | K8: 24.2 | L8: 23.8
A9: Figure Rules | F9: 4 | G9: 23.8 | H9: 19.4 | I9: 28 | J9: 15.2 | K9: 28.3 | L9: 27.7
A10: Figure Type | B10: Clustered Bar | F10: 5 | G10: 60.9 | H10: 15.3 | I10: 41 | J10: 39.4 | K10: 33.3 | L10: 37.6
A11: X Column | B11: Likert Scale (1 = Very Little Impact and 5 = Highly Impacted)
A12: Y Column
A13: X Axis Title | B13: Likert Scale (1 = Very Little Impact and 5 = Highly Impacted)
A14: Y Axis Title | B14: Percent
A15: Start at Zero | B15: TRUE
A16: Pivot for Chart | B16: TRUE
A18: Source Specifications
A19: Table ID
A20: URL
A21: Data Year
A22: Estimate Type
A23: Citation Month
A24: Citation Year
A25: Custom Text
A27: Note Specifications

Sheet DC ImpSct Hlth Ins & Access 
A1: Name | B1: The Impact of Health Insurance Coverage & Access to Care in Dutchess County (n = 100)
A2: Table/Figure/Both | B2: Both
A3: Object ID | B3: =IF($B$1="","",_xlfn.XLOOKUP($B$1,Master!$F$2:$F$308,Master!$G$2:$G$308,"")) -> tbl-DC-impact-hlthinsur-access
A4: Figure ID | B4: =IF($B$1="","",_xlfn.XLOOKUP($B$1,Master!$F$2:$F$308,Master!$H$2:$H$308,"")) -> fig-DC-impact-hlthinsur-access | G4: percent1 | H4: percent1 | I4: percent1 | J4: percent1
A5: Table Rules | E5: Enter Data | F5: Likert Scale | G5: Access To & Use of Prenatal Care | H5: Prevention of Infant & Maternal Mortality | I5: Preventive Services for Chronic Disease Prevention & Control | J5: Oral Health Care
A6: Multilevel Headers | B6: FALSE | F6: 1 | G6: 27.5 | H6: 29.6 | I6: 3 | J6: 7
F7: 2 | G7: 14.3 | H7: 14.3 | I7: 11.1 | J7: 12
F8: 3 | G8: 24.5 | H8: 26.5 | I8: 18.2 | J8: 19
A9: Figure Rules | F9: 4 | G9: 13.3 | H9: 11.2 | I9: 22.2 | J9: 23
A10: Figure Type | B10: Clustered Bar | F10: 5 | G10: 20.4 | H10: 18.4 | I10: 45.5 | J10: 39
A11: X Column | B11: Likert Scale (1 = Very Little Impact and 5 = Highly Impacted)
A12: Y Column
A13: X Axis Title | B13: Likert Scale (1 = Very Little Impact and 5 = Highly Impacted)
A14: Y Axis Title | B14: Percent
A15: Start at Zero | B15: TRUE
A16: Pivot for Chart | B16: TRUE
A17: Group By | B17: x_col
A18: Source Specifications
A19: Table ID
A20: URL
A21: Data Year
A22: Estimate Type
A23: Citation Month
A24: Citation Year
A25: Custom Text
A27: Note Specifications

Sheet OC Top Affect Health
A1: Name | B1: Top Rated Issues That Affect Health in Orange County (n = 170)
A2: Table/Figure/Both | B2: Figure
A3: Object ID | B3: =IF($B$1="","",_xlfn.XLOOKUP($B$1,Master!$F$2:$F$308,Master!$G$2:$G$308,"")) -> tbl-OC-affect-health
A4: Figure ID | B4: =IF($B$1="","",_xlfn.XLOOKUP($B$1,Master!$F$2:$F$308,Master!$H$2:$H$308,"")) -> fig-OC-affect-health | F4: percent1 | G4: percent1 | H4: percent1 | I4: percent1 | J4: percent1 | K4: percent1 | L4: percent1 | M4: percent1 | N4: percent1 | O4: percent1
A5: Table Rules | E5: Enter Data | F5: Access to mental health providers | G5: Access to affordable, decent and safe housing | H5: Access to specialty services/providers | I5: Access to affordable, reliable transportation | J5: Access to affordable health insurance | K5: Access to affordable, nutritious food | L5: Access to medical providers | M5: Access to culturally sensitive health care providers | N5: Access to high quality education | O5: Access to clean water and non-polluted air
A6: Multilevel Headers | B6: FALSE | F6: 58.2 | G6: 42.4 | H6: 40.6 | I6: 37.7 | J6: 36.5 | K6: 34.1 | L6: 30 | M6: 10.6 | N6: 10 | O6: 0
A9: Figure Rules
A10: Figure Type | B10: Bar
A11: X Column | B11: Category
A12: Y Column
A13: X Axis Title
A14: Y Axis Title | B14: Percent
A15: Start at Zero | B15: TRUE
A18: Source Specifications
A19: Table ID
A20: URL
A21: Data Year
A22: Estimate Type
A23: Citation Month
A24: Citation Year
A25: Custom Text
A27: Note Specifications

Sheet OC Top Barriers
A1: Name | B1: Top Rated Barriers to Achieving Better Health in Orange County (n = 170)
A2: Table/Figure/Both | B2: Figure
A3: Object ID | B3: =IF($B$1="","",_xlfn.XLOOKUP($B$1,Master!$F$2:$F$308,Master!$G$2:$G$308,"")) -> tbl-OC-achieve-health
A4: Figure ID | B4: =IF($B$1="","",_xlfn.XLOOKUP($B$1,Master!$F$2:$F$308,Master!$H$2:$H$308,"")) -> fig-OC-achieve-health | F4: percent1 | G4: percent1 | H4: percent1 | I4: percent1 | J4: percent1 | K4: percent1 | L4: percent1 | M4: percent1 | N4: percent1 | O4: percent1 | P4: percent1 | Q4: percent1
A5: Table Rules | E5: Enter Data | F5: Knowledge of existing resources | G5: Health literacy | H5: Geographic location living in a rural area | I5: Having someone help them understand insurance | J5: Having someone to help them understand their medical condition | K5: Substance Use Disorder (SUD) or Alcohol Use Disorder (AUD) | L5: Other | M5: Cultural customs | N5: Having a safe place to play and/or exercise | O5: Quality of education | P5: Geographic location- living in an urban area | Q5: Attainment of education
A6: Multilevel Headers | B6: FALSE | F6: 67.1 | G6: 50.6 | H6: 32.4 | I6: 31.2 | J6: 28.8 | K6: 27.7 | L6: 21.2 | M6: 9.4 | N6: 8.2 | O6: 8.2 | P6: 7.7 | Q6: 7.7
A9: Figure Rules
A10: Figure Type | B10: Bar
A11: X Column | B11: Category
A12: Y Column
A13: X Axis Title
A14: Y Axis Title | B14: Percent
A15: Start at Zero | B15: TRUE
A18: Source Specifications
A19: Table ID
A20: URL
A21: Data Year
A22: Estimate Type
A23: Citation Month
A24: Citation Year
A25: Custom Text
A27: Note Specifications

Sheet OC Impact Health
A1: Name | B1: The Impact of Health Issues in Orange County (n = 163)
A2: Table/Figure/Both | B2: Figure
A3: Object ID | B3: =IF($B$1="","",_xlfn.XLOOKUP($B$1,Master!$F$2:$F$308,Master!$G$2:$G$308,"")) -> tbl-OC-impact-hlth-issue
A4: Figure ID | B4: =IF($B$1="","",_xlfn.XLOOKUP($B$1,Master!$F$2:$F$308,Master!$H$2:$H$308,"")) -> fig-OC-impact-hlth-issue | G4: percent1 | H4: percent1 | I4: percent1 | J4: percent1 | K4: percent1 | L4: percent1
A5: Table Rules | E5: Enter Data | F5: Likert Scale | G5: Chronic Disease | H5: Health Disparities | I5: Mental Health and Substance Use Issues | J5: Maternal and Child Health Issues | K5: Environmental Factors | L5: Communicable Diseases
A6: Multilevel Headers | B6: FALSE | F6: 1 | G6: 3.1 | H6: 4.4 | I6: 3.7 | J6: 16.9 | K6: 16.1 | L6: 19
F7: 2 | G7: 5.6 | H7: 5 | I7: 5 | J7: 10 | K7: 15.4 | L7: 14.7
F8: 3 | G8: 12.4 | H8: 18.9 | I8: 15.5 | J8: 31.3 | K8: 34 | L8: 32.5
A9: Figure Rules | F9: 4 | G9: 15.5 | H9: 28.3 | I9: 19.9 | J9: 18.8 | K9: 17.9 | L9: 16
A10: Figure Type | B10: Clustered Bar | F10: 5 | G10: 63.4 | H10: 43.4 | I10: 55.9 | J10: 23.1 | K10: 16.7 | L10: 17.8
A11: X Column | B11: Likert Scale (1 = Very Little Impact and 5 = Highly Impacted)
A12: Y Column
A13: X Axis Title | B13: Likert Scale (1 = Very Little Impact and 5 = Highly Impacted)
A14: Y Axis Title | B14: Percent
A15: Start at Zero | B15: TRUE
A16: Pivot For Chart | B16: TRUE
A18: Source Specifications
A19: Table ID
A20: URL
A21: Data Year
A22: Estimate Type
A23: Citation Month
A24: Citation Year
A25: Custom Text
A27: Note Specifications

Sheet OC Impact SDOH
A1: Name | B1: The Impact of the Social Determinants of Health in Orange County (n = 160)
A2: Table/Figure/Both | B2: Figure
A3: Object ID | B3: =IF($B$1="","",_xlfn.XLOOKUP($B$1,Master!$F$2:$F$308,Master!$G$2:$G$308,"")) -> tbl-OC-impact-sdoh
A4: Figure ID | B4: =IF($B$1="","",_xlfn.XLOOKUP($B$1,Master!$F$2:$F$308,Master!$H$2:$H$308,"")) -> fig-OC-impact-sdoh | F4: percent1 | G4: percent1 | H4: percent1 | I4: percent1 | J4: percent1 | K4: percent1
A5: Table Rules | E5: Enter Data | F5: Mental Wellbeing & Substance Use | G5: Economic | H5: Health Insurance Coverage & Access to Care | I5: Safe & Healthy Communities | J5: Healthy Children | K5: Pre K - Grade 12 Student Success & Educational Attainment
A6: Multilevel Headers | B6: FALSE | F6: 77.5 | G6: 76.9 | H6: 61.9 | I6: 48.8 | J6: 18.8 | K6: 16.3
A9: Figure Rules
A10: Figure Type | B10: Bar
A11: X Column | B11: Category
A12: Y Column
A13: X Axis Title
A14: Y Axis Title | B14: Percent
A15: Start at Zero | B15: TRUE
A18: Source Specifications
A19: Table ID
A20: URL
A21: Data Year
A22: Estimate Type
A23: Citation Month
A24: Citation Year
A25: Custom Text
A27: Note Specifications

Sheet OC Impact Eco Wellbeing
A1: Name | B1: The Impact of Economic Wellbeing in Orange County (n = 159)
A2: Table/Figure/Both | B2: Figure
A3: Object ID | B3: =IF($B$1="","",_xlfn.XLOOKUP($B$1,Master!$F$2:$F$308,Master!$G$2:$G$308,"")) -> tbl-OC-eco-wellbeing
A4: Figure ID | B4: =IF($B$1="","",_xlfn.XLOOKUP($B$1,Master!$F$2:$F$308,Master!$H$2:$H$308,"")) -> fig-OC-eco-wellbeing | G4: percent1 | H4: percent1 | I4: percent1 | J4: percent1
A5: Table Rules | E5: Enter Data | F5: Likert Scale | G5: Poverty | H5: Unemployment | I5: Nutrition Security | J5: Housing Stability & Affordability
A6: Multilevel Headers | B6: FALSE | F6: 1 | G6: 1.9 | H6: 5.7 | I6: 3.9 | J6: 2.5
F7: 2 | G7: 5.7 | H7: 8.9 | I7: 8.3 | J7: 5.7
F8: 3 | G8: 20.8 | H8: 28.5 | I8: 25.6 | J8: 23.3
A9: Figure Rules | F9: 4 | G9: 21.4 | H9: 31 | I9: 27.6 | J9: 18.9
A10: Figure Type | B10: Clustered Bar | F10: 5 | G10: 50.3 | H10: 26 | I10: 34.6 | J10: 50
A11: X Column | B11: Likert Scale (1 = Very Little Impact and 5 = Highly Impacted)
A12: Y Column | B12: Percent
A13: X Axis Title | B13: Likert Scale (1 = Very Little Impact and 5 = Highly Impacted)
A14: Y Axis Title | B14: Percent
A15: Start at Zero | B15: TRUE
A16: Pivot For Chart | B16: TRUE
A18: Source Specifications
A19: Table ID
A20: URL
A21: Data Year
A22: Estimate Type
A23: Citation Month
A24: Citation Year
A25: Custom Text
A27: Note Specifications

Sheet OC Impact MH & SU
A1: Name | B1: The Impact of Mental Wellbeing & Substance Use in Orange County (n = 157)
A2: Table/Figure/Both | B2: Figure
A3: Object ID | B3: =IF($B$1="","",_xlfn.XLOOKUP($B$1,Master!$F$2:$F$308,Master!$G$2:$G$308,"")) -> tbl-OC-impact-mhsu
A4: Figure ID | B4: =IF($B$1="","",_xlfn.XLOOKUP($B$1,Master!$F$2:$F$308,Master!$H$2:$H$308,"")) -> fig-OC-impact-mhsu | G4: percent1 | H4: percent1 | I4: percent1 | J4: percent1 | K4: percent1 | L4: percent1
A5: Table Rules | E5: Enter Data | F5: Likert Scale | G5: Anxiety & Stress | H5: Suicide | I5: Depression | J5: Substance Use | K5: Adverse Childhood Experiences | L5: Healthy Eating
A6: Multilevel Headers | B6: FALSE | F6: 1 | G6: 0 | H6: 14.3 | I6: 1.3 | J6: 7.7 | K6: 9.7 | L6: 3.8
F7: 2 | G7: 1.9 | H7: 20.8 | I7: 5.7 | J7: 8.4 | K7: 11.6 | L7: 9.6
F8: 3 | G8: 8.3 | H8: 26 | I8: 13.4 | J8: 21.3 | K8: 22.6 | L8: 21.7
A9: Figure Rules | F9: 4 | G9: 26.1 | H9: 23.4 | I9: 31.2 | J9: 24.5 | K9: 28.4 | L9: 27.4
A10: Figure Type | B10: Clustered Bar | F10: 5 | G10: 63.7 | H10: 15.6 | I10: 48.4 | J10: 38.1 | K10: 27.7 | L10: 37.6
A11: X Column | B11: Likert Scale (1 = Very Little Impact and 5 = Highly Impacted)
A12: Y Column | B12: Percent
A13: X Axis Title | B13: Likert Scale (1 = Very Little Impact and 5 = Highly Impacted)
A14: Y Axis Title | B14: Percent
A15: Start at Zero | B15: TRUE
A16: Pivot For Chart | B16: TRUE
A18: Source Specifications
A19: Table ID
A20: URL
A21: Data Year
A22: Estimate Type
A23: Citation Month
A24: Citation Year
A25: Custom Text
A27: Note Specifications

Sheet OC Impact Hlth Ins & Access
A1: Name | B1: The Impact of Health Insurance Coverage & Access to Care in Orange County (n = 156)
A2: Table/Figure/Both | B2: Figure
A3: Object ID | B3: =IF($B$1="","",_xlfn.XLOOKUP($B$1,Master!$F$2:$F$308,Master!$G$2:$G$308,"")) -> tbl-OC-impact-hlthinsur-access
A4: Figure ID | B4: =IF($B$1="","",_xlfn.XLOOKUP($B$1,Master!$F$2:$F$308,Master!$H$2:$H$308,"")) -> fig-OC-impact-hlthinsur-access | G4: percent1 | H4: percent1 | I4: percent1 | J4: percent1
A5: Table Rules | E5: Enter Data | F5: Likert Scale | G5: Access To & Use of Prenatal Care | H5: Prevention of Infant & Maternal Mortality | I5: Preventive Services for Chronic Disease Prevention & Control | J5: Oral Health Care
A6: Multilevel Headers | B6: FALSE | F6: 1 | G6: 18.8 | H6: 21.4 | I6: 3.2 | J6: 8.3
F7: 2 | G7: 14.3 | H7: 18.8 | I7: 8.4 | J7: 7.1
F8: 3 | G8: 30 | H8: 28.6 | I8: 20.7 | J8: 23.1
A9: Figure Rules | F9: 4 | G9: 16.9 | H9: 15.6 | I9: 27.7 | J9: 30.8
A10: Figure Type | B10: Clustered Bar | F10: 5 | G10: 20.1 | H10: 15.6 | I10: 40 | J10: 30.8
A11: X Column | B11: Likert Scale (1 = Very Little Impact and 5 = Highly Impacted)
A12: Y Column | B12: Percent
A13: X Axis Title | B13: Likert Scale (1 = Very Little Impact and 5 = Highly Impacted)
A14: Y Axis Title | B14: Percent
A15: Start at Zero | B15: TRUE
A16: Pivot For Chart | B16: TRUE
A18: Source Specifications
A19: Table ID
A20: URL
A21: Data Year
A22: Estimate Type
A23: Citation Month
A24: Citation Year
A25: Custom Text
A27: Note Specifications

Sheet PC Big Health Problem
A1: Name | B1: Biggest Health Problems in Populations Served, Putnam County (n = 128)
A2: Table/Figure/Both | B2: Figure
A3: Object ID | B3: =IF($B$1="","",_xlfn.XLOOKUP($B$1,Master!$F$2:$F$308,Master!$G$2:$G$308,"")) -> tbl-PC-big-hlth-prob
A4: Figure ID | B4: =IF($B$1="","",_xlfn.XLOOKUP($B$1,Master!$F$2:$F$308,Master!$H$2:$H$308,"")) -> fig-PC-big-hlth-prob | F4: percent1 | G4: percent1 | H4: percent1 | I4: percent1 | J4: percent1 | K4: percent1 | L4: percent1 | M4: percent1 | N4: percent1 | O4: percent1 | P4: percent1 | Q4: percent1 | R4: percent1 | S4: percent1 | T4: percent1 | U4: percent1 | V4: percent1 | W4: percent1 | X4: percent1 | Y4: percent1 | Z4: percent1
A5: Table Rules | E5: Enter Data | F5: Preventable injuries | G5: Asthma/lung disease | H5: Environmental hazards | I5: Safety | J5: Pregnancy associated health issues | K5: Communicable diseases and other infections | L5: Violence | M5: Heart Disease and Stroke | N5: Cancer | O5: Falls among the elderly | P5: Cognitive impairment | Q5: Diabetes | R5: Women's health and wellness | S5: Smoking/tobacco/nicotine use | T5: Nutrition/eating habits | U5: Obesity/weight management issues | V5: Child health & wellness | W5: Care for the elderly | X5: Substance Misuse | Y5: Access to Healthcare Providers | Z5: Mental Health
A6: Multilevel Headers | B6: FALSE | F6: 2 | G6: 2 | H6: 3 | I6: 3 | J6: 4 | K6: 5 | L6: 5 | M6: 6 | N6: 7 | O6: 7 | P6: 8 | Q6: 8 | R6: 9 | S6: 11 | T6: 12 | U6: 13 | V6: 16 | W6: 20 | X6: 31 | Y6: 39 | Z6: 68
A9: Figure Rules
A10: Figure Type | B10: Horizontal Bar
A11: X Column | B11: Category
A12: Y Column
A13: X Axis Title
A14: Y Axis Title | B14: Percent
A15: Start at Zero | B15: TRUE
A18: Source Specifications
A19: Table ID
A20: URL
A21: Data Year
A22: Estimate Type
A23: Citation Month
A24: Citation Year
A25: Custom Text
A27: Note Specifications

Sheet PC Help Improve Health
A1: Name | B1: Most Helpful to Improve Health in Populations Served, Putnam County (n = 128)
A2: Table/Figure/Both | B2: Figure
A3: Object ID | B3: =IF($B$1="","",_xlfn.XLOOKUP($B$1,Master!$F$2:$F$308,Master!$G$2:$G$308,"")) -> tbl-PC-help-improve-hlth
A4: Figure ID | B4: =IF($B$1="","",_xlfn.XLOOKUP($B$1,Master!$F$2:$F$308,Master!$H$2:$H$308,"")) -> fig-PC-help-improve-hlth | F4: percent1 | G4: percent1 | H4: percent1 | I4: percent1 | J4: percent1 | K4: percent1 | L4: percent1 | M4: percent1 | N4: percent1 | O4: percent1 | P4: percent1 | Q4: percent1 | R4: percent1 | S4: percent1 | T4: percent1 | U4: percent1 | V4: percent1 | W4: percent1
A5: Table Rules | E5: Enter Data | F5: Safer workplaces | G5: Safer places to walk/play | H5: Parks and recreation | I5: Breast feeding | J5: Weight management programs | K5: Smoking cessation programs | L5: Health insurance enrollment programs | M5: Clean air and water | N5: Improved childcare options | O5: Health screenings | P5: Investments in schools | Q5: Improved homecare options | R5: Health education | S5: Access to healthier food | T5: Drugs and alcohol rehabilitation services | U5: Affordable Housing | V5: Access to transportation | W5: Mental health services
A6: Multilevel Headers | B6: FALSE | F6: 2 | G6: 2 | H6: 2 | I6: 2 | J6: 4 | K6: 4 | L6: 4 | M6: 4 | N6: 5 | O6: 7 | P6: 8 | Q6: 16 | R6: 18 | S6: 20 | T6: 23.2 | U6: 44 | V6: 45 | W6: 51
A9: Figure Rules
A10: Figure Type | B10: Horizontal Bar
A11: X Column | B11: Category
A12: Y Column
A13: X Axis Title
A14: Y Axis Title | B14: Percent
A15: Start at Zero | B15: TRUE
A18: Source Specifications
A19: Table ID
A20: URL
A21: Data Year
A22: Estimate Type
A23: Citation Month
A24: Citation Year
A25: Custom Text
A27: Note Specifications

Sheet PC Health Screen & Education
A1: Name | B1: Most Beneficial Health Screenings or Health Education Topics for Populations Served, Putnam County (n=128)
A2: Table/Figure/Both | B2: Figure
A3: Object ID | B3: =IF($B$1="","",_xlfn.XLOOKUP($B$1,Master!$F$2:$F$308,Master!$G$2:$G$308,"")) -> tbl-PC-help-hlth-screen-education
A4: Figure ID | B4: =IF($B$1="","",_xlfn.XLOOKUP($B$1,Master!$F$2:$F$308,Master!$H$2:$H$308,"")) -> fig-PC-help-hlth-screen-education | F4: percent1 | G4: percent1 | H4: percent1 | I4: percent1 | J4: percent1 | K4: percent1 | L4: percent1 | M4: percent1 | N4: percent1 | O4: percent1 | P4: percent1 | Q4: percent1 | R4: percent1 | S4: percent1 | T4: percent1 | U4: percent1 | V4: percent1 | W4: percent1 | X4: percent1 | Y4: percent1 | Z4: percent1 | AA4: percent1 | AB4: percent1
A5: Table Rules | E5: Enter Data | F5: Hepatitis C virus | G5: Eating disorders | H5: Antibiotic resistance | I5: Pedestrian/cyclist safety | J5: Cholesterol | K5: Breastfeeding | L5: Disease outbreak prevention | M5: Prenatal care | N5: Emergency preparedness | O5: Heart disease and stroke | P5: Environments to promote physical activity | Q5: Nutrition | R5: Dental Screenings | S5: Exercise/physical activity | T5: Cancer | U5: Fall prevention for the elderly | V5: Blood pressure | W5: Food security | X5: Diabetes/pre-diabetes | Y5: Cognitive impairment | Z5: Drug and alcohol misuse | AA5: Chronic disease management | AB5: Mental health
A6: Multilevel Headers | B6: FALSE | F6: 1 | G6: 1 | H6: 1 | I6: 2 | J6: 3 | K6: 3 | L6: 4 | M6: 5 | N6: 5 | O6: 5 | P6: 6 | Q6: 8 | R6: 9 | S6: 9 | T6: 9 | U6: 11 | V6: 12 | W6: 13 | X6: 14 | Y6: 16 | Z6: 22 | AA6: 25 | AB6: 56
A9: Figure Rules
A10: Figure Type | B10: Horizontal Bar
A11: X Column | B11: Category
A12: Y Column
A13: X Axis Title
A14: Y Axis Title | B14: Percent
A15: Start at Zero | B15: TRUE
A18: Source Specifications
A19: Table ID
A20: URL
A21: Data Year
A22: Estimate Type
A23: Citation Month
A24: Citation Year
A25: Custom Text
A27: Note Specifications

Sheet PC Can't Get Healthcare
A1: Name | B1: Reasons Populations Served Can't Get Needed Healthcare, Putnam County (n = 99)
A2: Table/Figure/Both | B2: Figure
A3: Object ID | B3: =IF($B$1="","",_xlfn.XLOOKUP($B$1,Master!$F$2:$F$308,Master!$G$2:$G$308,"")) -> tbl-PC-reason-no-hlthcare
A4: Figure ID | B4: =IF($B$1="","",_xlfn.XLOOKUP($B$1,Master!$F$2:$F$308,Master!$H$2:$H$308,"")) -> fig-PC-reason-no-hlthcare | F4: percent1 | G4: percent1 | H4: percent1 | I4: percent1 | J4: percent1 | K4: percent1
A5: Table Rules | E5: Enter Data | F5: Lack of cultural/religious sensitive care | G5: Language barriers | H5: Misinformation/limited health literacy | I5: Don't know how to find provider | J5: Fear/hesitancy | K5: Lack of appointment availability | L5: Lack of transportation | M5: Cost
A6: Multilevel Headers | B6: FALSE | F6: 4 | G6: 10 | H6: 15 | I6: 23 | J6: 38 | K6: 40 | L6: 44 | M6: 52
A9: Figure Rules
A10: Figure Type | B10: Horizontal Bar
A11: X Column | B11: Category
A12: Y Column
A13: X Axis Title
A14: Y Axis Title | B14: Percent
A15: Start at Zero | B15: TRUE
A18: Source Specifications
A19: Table ID
A20: URL
A21: Data Year
A22: Estimate Type
A23: Citation Month
A24: Citation Year
A25: Custom Text
A27: Note Specifications

Sheet PC Trusted Source
A1: Name | B1: Trusted Sources of Health Information for Populations Served, Putnam County (n = 128)
A2: Table/Figure/Both | B2: Figure
A3: Object ID | B3: =IF($B$1="","",_xlfn.XLOOKUP($B$1,Master!$F$2:$F$308,Master!$G$2:$G$308,"")) -> tbl-PC-trust-hlth-source
A4: Figure ID | B4: =IF($B$1="","",_xlfn.XLOOKUP($B$1,Master!$F$2:$F$308,Master!$H$2:$H$308,"")) -> fig-PC-trust-hlth-source | F4: percent1 | G4: percent1 | H4: percent1 | I4: percent1 | J4: percent1 | K4: percent1 | L4: percent1 | M4: percent1
A5: Table Rules | E5: Enter Data | F5: Religious organizations | G5: Schools or colleges | H5: Workplace | I5: Online health sites | J5: Hospitals | K5: Health Departments | L5: Family or friends | M5: Doctors/healthcare providers
A6: Multilevel Headers | B6: FALSE | F6: 10 | G6: 16 | H6: 21 | I6: 28 | J6: 39 | K6: 45 | L6: 48 | M6: 76
A9: Figure Rules
A10: Figure Type | B10: Horizontal Bar
A11: X Column | B11: Category
A12: Y Column
A13: X Axis Title
A14: Y Axis Title | B14: Percent
A15: Start at Zero | B15: TRUE
A18: Source Specifications
A19: Table ID
A20: URL
A21: Data Year
A22: Estimate Type
A23: Citation Month
A24: Citation Year
A25: Custom Text
A27: Note Specifications

Sheet RC Top Affect Health
A1: Name | B1: Top Rated Issues That Affect Health in Rockland County (n = 135)
A2: Table/Figure/Both | B2: Figure
A3: Object ID | B3: =IF($B$1="","",_xlfn.XLOOKUP($B$1,Master!$F$2:$F$308,Master!$G$2:$G$308,"")) -> tbl-RC-affect-health
A4: Figure ID | B4: =IF($B$1="","",_xlfn.XLOOKUP($B$1,Master!$F$2:$F$308,Master!$H$2:$H$308,"")) -> fig-RC-affect-health | F4: percent1 | G4: percent1 | H4: percent1 | I4: percent1 | J4: percent1 | K4: percent1 | L4: percent1 | M4: percent1 | N4: percent1 | O4: percent1
A5: Table Rules | E5: Enter Data | F5: Access to mental health providers | G5: Access to affordable, decent and safe housing | H5: Access to specialty services/providers | I5: Access to affordable health insurance | J5: Access to affordable, reliable transportation | K5: Access to affordable, nutritious food | L5: Access to medical providers | M5: Access to culturally sensitive health care providers | N5: Access to high quality education | O5: Access to clean water and non-polluted air
A6: Multilevel Headers | B6: FALSE | F6: 50.4 | G6: 46.7 | H6: 43 | I6: 38.5 | J6: 31.9 | K6: 29.6 | L6: 27.4 | M6: 17 | N6: 14.1 | O6: 1.5
A9: Figure Rules
A10: Figure Type | B10: Bar
A11: X Column | B11: Category
A12: Y Column
A13: X Axis Title
A14: Y Axis Title | B14: Percent
A15: Start at Zero | B15: TRUE
A18: Source Specifications
A19: Table ID
A20: URL
A21: Data Year
A22: Estimate Type
A23: Citation Month
A24: Citation Year
A25: Custom Text
A27: Note Specifications

Sheet RC Top Barriers
A1: Name | B1: Top Rated Barriers to Achieving Better Health in Rockland County (n = 135)
A2: Table/Figure/Both | B2: Both
A3: Object ID | B3: =IF($B$1="","",_xlfn.XLOOKUP($B$1,Master!$F$2:$F$308,Master!$G$2:$G$308,"")) -> tbl-RC-achieve-health
A4: Figure ID | B4: =IF($B$1="","",_xlfn.XLOOKUP($B$1,Master!$F$2:$F$308,Master!$H$2:$H$308,"")) -> fig-RC-achieve-health | F4: percent1 | G4: percent1 | H4: percent1 | I4: percent1 | J4: percent1 | K4: percent1 | L4: percent1 | M4: percent1 | N4: percent1 | O4: percent1 | P4: percent1 | Q4: percent1
A5: Table Rules | E5: Enter Data | F5: Knowledge of existing resources | G5: Health literacy | H5: Having someone to help them understand their medical condition | I5: Having someone help them understand insurance | J5: Substance Use Disorder (SUD) or Alcohol Use Disorder (AUD) | K5: Other | L5: Cultural customs | M5: Geographic location living in a rural area | N5: Having a safe place to play and/or exercise | O5: Quality of education | P5: Attainment of education | Q5: Geographic location- living in an urban area
A6: Multilevel Headers | B6: FALSE | F6: 66 | G6: 59.3 | H6: 34.1 | I6: 26.7 | J6: 23.7 | K6: 21.5 | L6: 19.3 | M6: 18.5 | N6: 9.6 | O6: 9.6 | P6: 6.7 | Q6: 5.2
A9: Figure Rules
A10: Figure Type | B10: Bar
A11: X Column | B11: Category
A12: Y Column
A13: X Axis Title
A14: Y Axis Title | B14: Percent
A15: Start at Zero | B15: TRUE
A18: Source Specifications
A19: Table ID
A20: URL
A21: Data Year
A22: Estimate Type
A23: Citation Month
A24: Citation Year
A25: Custom Text
A27: Note Specifications

Sheet RC Impact Health
A1: Name | B1: The Impact of Health Issues in Rockland County (n = 132)
A2: Table/Figure/Both | B2: Both
A3: Object ID | B3: =IF($B$1="","",_xlfn.XLOOKUP($B$1,Master!$F$2:$F$308,Master!$G$2:$G$308,"")) -> tbl-RC-impact-hlth-issue
A4: Figure ID | B4: =IF($B$1="","",_xlfn.XLOOKUP($B$1,Master!$F$2:$F$308,Master!$H$2:$H$308,"")) -> fig-RC-impact-hlth-issue | F4: number | G4: percent1 | H4: percent1 | I4: percent1 | J4: percent1 | K4: percent1 | L4: percent1
A5: Table Rules | E5: Enter Data | F5: Likert Scale | G5: Chronic Disease | H5: Health Disparities | I5: Mental Health and Substance Use Issues | J5: Maternal and Child Health Issues | K5: Environmental Factors | L5: Communicable Diseases
A6: Multilevel Headers | B6: FALSE | F6: 1 | G6: 5.4 | H6: 4.7 | I6: 3.1 | J6: 14.6 | K6: 16 | L6: 21.4
F7: 2 | G7: 2.3 | H7: 6.2 | I7: 6.3 | J7: 16.2 | K7: 19.9 | L7: 16
F8: 3 | G8: 16.3 | H8: 22.5 | I8: 18 | J8: 28.5 | K8: 28.2 | L8: 30.5
A9: Figure Rules | F9: 4 | G9: 21.7 | H9: 27.1 | I9: 24.2 | J9: 20 | K9: 17.6 | L9: 18.3
A10: Figure Type | B10: Clustered Bar | F10: 5 | G10: 54.3 | H10: 40 | I10: 48.4 | J10: 20.8 | K10: 18.3 | L10: 13.7
A11: X Column | B11: Likert Scale (1 = Very Little Impact and 5 = Highly Impacted)
A12: Y Column | B12: Percent
A13: X Axis Title | B13: Likert Scale (1 = Very Little Impact and 5 = Highly Impacted)
A14: Y Axis Title | B14: Percent
A15: Start at Zero | B15: TRUE
A16: Pivot For Chart | B16: TRUE
A18: Source Specifications
A19: Table ID
A20: URL
A21: Data Year
A22: Estimate Type
A23: Citation Month
A24: Citation Year
A25: Custom Text
A27: Note Specifications

Sheet RC Impact SDOH
A1: Name | B1: The Impact of the Social Determinants of Health in Rockland County (n = 128)
A2: Table/Figure/Both | B2: Both
A3: Object ID | B3: =IF($B$1="","",_xlfn.XLOOKUP($B$1,Master!$F$2:$F$308,Master!$G$2:$G$308,"")) -> tbl-RC-impact-sdoh
A4: Figure ID | B4: =IF($B$1="","",_xlfn.XLOOKUP($B$1,Master!$F$2:$F$308,Master!$H$2:$H$308,"")) -> fig-RC-impact-sdoh | F4: percent1 | G4: percent1 | H4: percent1 | I4: percent1 | J4: percent1 | K4: percent1
A5: Table Rules | E5: Enter Data | F5: Economic | G5: Mental Wellbeing & Substance Use | H5: Health Insurance Coverage & Access to Care | I5: Safe & Healthy Communities | J5: Healthy Children | K5: Pre K - Grade 12 Student Success & Educational Attainment
A6: Multilevel Headers | B6: FALSE | F6: 79.7 | G6: 70.3 | H6: 68.8 | I6: 46.9 | J6: 17.2 | K6: 17.2
A9: Figure Rules
A10: Figure Type | B10: Bar
A11: X Column | B11: Category
A12: Y Column | B12: Percent
A13: X Axis Title
A14: Y Axis Title | B14: Percent
A15: Start at Zero | B15: TRUE
A18: Source Specifications
A19: Table ID
A20: URL
A21: Data Year
A22: Estimate Type
A23: Citation Month
A24: Citation Year
A25: Custom Text
A27: Note Specifications

Sheet RC Impact Eco Wellbeing
A1: Name | B1: The Impact of Economic Wellbeing in Rockland County (n = 127)
A2: Table/Figure/Both | B2: Both
A3: Object ID | B3: =IF($B$1="","",_xlfn.XLOOKUP($B$1,Master!$F$2:$F$308,Master!$G$2:$G$308,"")) -> tbl-RC-eco-wellbeing
A4: Figure ID | B4: =IF($B$1="","",_xlfn.XLOOKUP($B$1,Master!$F$2:$F$308,Master!$H$2:$H$308,"")) -> fig-RC-eco-wellbeing | F4: number | G4: percent1 | H4: percent1 | I4: percent1 | J4: percent1
A5: Table Rules | E5: Enter Data | F5: Likert Scale | G5: Poverty | H5: Unemployment | I5: Nutrition Security | J5: Housing Stability & Affordability
A6: Multilevel Headers | B6: FALSE | F6: 1 | G6: 2.4 | H6: 3.3 | I6: 6.4 | J6: 2.4
F7: 2 | G7: 6.3 | H7: 12.2 | I7: 14.4 | J7: 9.5
F8: 3 | G8: 22.1 | H8: 26.8 | I8: 23.2 | J8: 19.8
A9: Figure Rules | F9: 4 | G9: 21.3 | H9: 30.9 | I9: 28 | J9: 23.8
A10: Figure Type | B10: Clustered Bar | F10: 5 | G10: 48 | H10: 26.8 | I10: 28 | J10: 44.4
A11: X Column | B11: Likert Scale (1 = Very Little Impact and 5 = Highly Impacted)
A12: Y Column | B12: Percent
A13: X Axis Title | B13: Likert Scale (1 = Very Little Impact and 5 = Highly Impacted)
A14: Y Axis Title | B14: Percent
A15: Start at Zero | B15: TRUE
A16: Pivot for Chart | B16: TRUE
A18: Source Specifications
A19: Table ID
A20: URL
A21: Data Year
A22: Estimate Type
A23: Citation Month
A24: Citation Year
A25: Custom Text
A27: Note Specifications

Sheet RC Impact MH & SU
A1: Name | B1: The Impact of Mental Wellbeing & Substance Use in Rockland County (n = 125)
A2: Table/Figure/Both | B2: Figure
A3: Object ID | B3: =IF($B$1="","",_xlfn.XLOOKUP($B$1,Master!$F$2:$F$308,Master!$G$2:$G$308,"")) -> tbl-RC-impact-mhsu
A4: Figure ID | B4: =IF($B$1="","",_xlfn.XLOOKUP($B$1,Master!$F$2:$F$308,Master!$H$2:$H$308,"")) -> fig-RC-impact-mhsu | F4: number | G4: percent1 | H4: percent1 | I4: percent1 | J4: percent1 | K4: percent1 | L4: percent1
A5: Table Rules | E5: Enter Data | F5: Likert Scale | G5: Anxiety & Stress | H5: Suicide | I5: Depression | J5: Substance Use | K5: Adverse Childhood Experiences | L5: Healthy Eating
A6: Multilevel Headers | B6: FALSE | F6: 1 | G6: 0.8 | H6: 18.7 | I6: 1.6 | J6: 11.4 | K6: 12.2 | L6: 3.2
F7: 2 | G7: 2.4 | H7: 17.9 | I7: 5.7 | J7: 11.4 | K7: 10.6 | L7: 12.1
F8: 3 | G8: 15.2 | H8: 30.9 | I8: 24.4 | J8: 24.4 | K8: 23.6 | L8: 21.8
A9: Figure Rules | F9: 4 | G9: 20 | H9: 19.5 | I9: 28.5 | J9: 22 | K9: 28.5 | L9: 29
A10: Figure Type | B10: Clustered Bar | F10: 5 | G10: 61.6 | H10: 13 | I10: 39.8 | J10: 30.9 | K10: 25.2 | L10: 33.9
A11: X Column | B11: Likert Scale (1 = Very Little Impact and 5 = Highly Impacted)
A12: Y Column | B12: Percent
A13: X Axis Title | B13: Likert Scale (1 = Very Little Impact and 5 = Highly Impacted)
A14: Y Axis Title | B14: Percent
A15: Start at Zero | B15: TRUE
A16: Pivot for Chart | B16: TRUE
A18: Source Specifications
A19: Table ID
A20: URL
A21: Data Year
A22: Estimate Type
A23: Citation Month
A24: Citation Year
A25: Custom Text
A27: Note Specifications

Sheet RC Impact Hlth Ins & Access 
A1: Name | B1: The Impact of Health Insurance Coverage & Access to Care in Rockland County (n = 124)
A2: Table/Figure/Both | B2: Figure
A3: Object ID | B3: =IF($B$1="","",_xlfn.XLOOKUP($B$1,Master!$F$2:$F$308,Master!$G$2:$G$308,"")) -> tbl-RC-impact-hlthinsur-access
A4: Figure ID | B4: =IF($B$1="","",_xlfn.XLOOKUP($B$1,Master!$F$2:$F$308,Master!$H$2:$H$308,"")) -> fig-RC-impact-hlthinsur-access | F4: number | G4: percent1 | H4: percent1 | I4: percent1 | J4: percent1
A5: Table Rules | E5: Enter Data | F5: Likert Scale | G5: Access To & Use of Prenatal Care | H5: Prevention of Infant & Maternal Mortality | I5: Preventive Services for Chronic Disease Prevention & Control | J5: Oral Health Care
A6: Multilevel Headers | B6: FALSE | F6: 1 | G6: 23.6 | H6: 27.6 | I6: 8.1 | J6: 9.8
F7: 2 | G7: 15.5 | H7: 17.9 | I7: 7.3 | J7: 7.4
F8: 3 | G8: 26.8 | H8: 28.5 | I8: 23.6 | J8: 28.7
A9: Figure Rules | F9: 4 | G9: 16.3 | H9: 11.4 | I9: 25.2 | J9: 22.1
A10: Figure Type | B10: Clustered Bar | F10: 5 | G10: 17.9 | H10: 14.6 | I10: 35.8 | J10: 32
A11: X Column | B11: Likert Scale (1 = Very Little Impact and 5 = Highly Impacted)
A12: Y Column | B12: Percent
A13: X Axis Title | B13: Likert Scale (1 = Very Little Impact and 5 = Highly Impacted)
A14: Y Axis Title | B14: Percent
A15: Start at Zero | B15: TRUE
A16: Pivot for Chart | B16: TRUE
A18: Source Specifications
A19: Table ID
A20: URL
A21: Data Year
A22: Estimate Type
A23: Citation Month
A24: Citation Year
A25: Custom Text
A27: Note Specifications

Sheet SC Top Affect Health
A1: Name | B1: Top Rated Issues That Affect Health in Sullivan County (n = 102)
A2: Table/Figure/Both | B2: Both
A3: Object ID | B3: =IF($B$1="","",_xlfn.XLOOKUP($B$1,Master!$F$2:$F$308,Master!$G$2:$G$308,"")) -> tbl-SC-affect-health
A4: Figure ID | B4: =IF($B$1="","",_xlfn.XLOOKUP($B$1,Master!$F$2:$F$308,Master!$H$2:$H$308,"")) -> fig-SC-affect-health | F4: percent1 | G4: percent1 | H4: percent1 | I4: percent1 | J4: percent1 | K4: percent1 | L4: percent1 | M4: percent1 | N4: percent1 | O4: percent1
A5: Table Rules | E5: Enter Data | F5: Access to mental health providers | G5: Access to affordable, decent and safe housing | H5: Access to affordable, reliable transportation | I5: Access to affordable, nutritious food | J5: Access to specialty services/providers | K5: Access to affordable health insurance | L5: Access to medical providers | M5: Access to high quality education | N5: Access to culturally sensitive health care providers | O5: Access to clean water and non-polluted air
A6: Multilevel Headers | B6: FALSE | F6: 49 | G6: 48 | H6: 45.1 | I6: 40.2 | J6: 38.2 | K6: 32.4 | L6: 23.5 | M6: 14.7 | N6: 8.8 | O6: 0
A9: Figure Rules
A10: Figure Type | B10: Bar
A11: X Column | B11: Category
A12: Y Column
A13: X Axis Title
A14: Y Axis Title | B14: Percent
A15: Start at Zero | B15: TRUE
A18: Source Specifications
A19: Table ID
A20: URL
A21: Data Year
A22: Estimate Type
A23: Citation Month
A24: Citation Year
A25: Custom Text
A27: Note Specifications

Sheet SC Top Barriers
A1: Name | B1: Top Rated Barriers to Achieving Better Health in Sullivan County (n = 102)
A2: Table/Figure/Both | B2: Both
A3: Object ID | B3: =IF($B$1="","",_xlfn.XLOOKUP($B$1,Master!$F$2:$F$308,Master!$G$2:$G$308,"")) -> tbl-SC-achieve-health
A4: Figure ID | B4: =IF($B$1="","",_xlfn.XLOOKUP($B$1,Master!$F$2:$F$308,Master!$H$2:$H$308,"")) -> fig-SC-achieve-health | F4: percent1 | G4: percent1 | H4: percent1 | I4: percent1 | J4: percent1 | K4: percent1 | L4: percent1 | M4: percent1 | N4: percent1 | O4: percent1 | P4: percent1 | Q4: percent1
A5: Table Rules | E5: Enter Data | F5: Knowledge of existing resources | G5: Geographic locationliving in a rural area | H5: Health literacy | I5: Substance Use Disorder (SUD) or Alcohol Use Disorder (AUD) | J5: Having someone to help them understand their medical condition | K5: Having someone help them understand insurance | L5: Other | M5: Quality of education | N5: Having a safe place to play and/or exercise | O5: Attainment of education | P5: Cultural customs | Q5: Geographic location- living in an urban area
A6: Multilevel Headers | B6: FALSE | F6: 62.8 | G6: 48 | H6: 44.1 | I6: 36.3 | J6: 59.4 | K6: 22.6 | L6: 21.6 | M6: 10.8 | N6: 8.8 | O6: 5.9 | P6: 4.9 | Q6: 4.9
A9: Figure Rules
A10: Figure Type | B10: Bar
A11: X Column | B11: Category
A12: Y Column
A13: X Axis Title
A14: Y Axis Title | B14: Percent
A15: Start at Zero | B15: TRUE
A18: Source Specifications
A19: Table ID
A20: URL
A21: Data Year
A22: Estimate Type
A23: Citation Month
A24: Citation Year
A25: Custom Text
A27: Note Specfications

Sheet SC Impact Health
A1: Name | B1: The Impact of Health Issues in Sullivan County (n = 98)
A2: Table/Figure/Both | B2: Both
A3: Object ID | B3: =IF($B$1="","",_xlfn.XLOOKUP($B$1,Master!$F$2:$F$308,Master!$G$2:$G$308,"")) -> tbl-SC-impact-hlth-issue
A4: Figure ID | B4: =IF($B$1="","",_xlfn.XLOOKUP($B$1,Master!$F$2:$F$308,Master!$H$2:$H$308,"")) -> fig-SC-impact-hlth-issue | F4: number | G4: percent1 | H4: percent1 | I4: percent1 | J4: percent1 | K4: percent1 | L4: percent1
A5: Table Rules | E5: Enter Data | F5: Likert Scale | G5: Chronic Disease | H5: Health Disparities | I5: Mental Health and Substance Use Issues | J5: Maternal and Child Health Issues | K5: Environmental Factors | L5: Communicable Diseases
A6: Multilevel Headers | B6: FALSE | F6: 1 | G6: 5.2 | H6: 3.1 | I6: 4.1 | J6: 9.3 | K6: 12.4 | L6: 17.4
F7: 2 | G7: 4.1 | H7: 5.2 | I7: 6.2 | J7: 10.3 | K7: 19.6 | L7: 14.3
F8: 3 | G8: 14.4 | H8: 19.8 | I8: 13.4 | J8: 35.1 | K8: 32 | L8: 30
A9: Figure Rules | F9: 4 | G9: 19.6 | H9: 27.1 | I9: 19.6 | J9: 16.5 | K9: 14.4 | L9: 21.4
A10: Figure Type | B10: Clustered Bar | F10: 5 | G10: 56.7 | H10: 44.8 | I10: 56.7 | J10: 28.9 | K10: 21.7 | L10: 17.4
A11: X Column | B11: Likert Scale (1 = Very Little Impact and 5 = Highly Impacted)
A12: Y Column | B12: Percent
A13: X Axis Title | B13: Likert Scale (1 = Very Little Impact and 5 = Highly Impacted)
A14: Y Axis Title | B14: Percent
A15: Start at Zero | B15: TRUE
A16: Pivot for Chart | B16: TRUE
A18: Source Specifications
A19: Table ID
A20: URL
A21: Data Year
A22: Estimate Type
A23: Citation Month
A24: Citation Year
A25: Custom Text
A27: Note Specifications

Sheet SC Impact SDOH
A1: Name | B1: The Impact of the Social Determinants of Health in Sullivan County (n = 96)
A2: Table/Figure/Both | B2: Both
A3: Object ID | B3: =IF($B$1="","",_xlfn.XLOOKUP($B$1,Master!$F$2:$F$308,Master!$G$2:$G$308,"")) -> tbl-SC-impact-sdoh
A4: Figure ID | B4: =IF($B$1="","",_xlfn.XLOOKUP($B$1,Master!$F$2:$F$308,Master!$H$2:$H$308,"")) -> fig-SC-impact-sdoh | F4: percent1 | G4: percent1 | H4: percent1 | I4: percent1 | J4: percent1 | K4: percent1
A5: Table Rules | E5: Enter Data | F5: Mental Wellbeing & Substance Use | G5: Economic | H5: Health Insurance Coverage & Access to Care | I5: Safe & Healthy Communities | J5: Healthy Children | K5: Pre K - Grade 12 Student Success & Educational Attainment
A6: Multilevel Headers | B6: FALSE | F6: 83.3 | G6: 80.2 | H6: 56.3 | I6: 44.8 | J6: 20.8 | K6: 14.6
A9: Figure Rules
A10: Figure Type | B10: Bar
A11: X Column | B11: Category
A12: Y Column | B12: Percent
A13: X Axis Title
A14: Y Axis Title | B14: Percent
A15: Start at Zero | B15: TRUE
A18: Source Specifications
A19: Table ID
A20: URL
A21: Data Year
A22: Estimate Type
A23: Citation Month
A24: Citation Year
A25: Custom Text
A27: Note Specifications

Sheet SC Impact Eco Wellbeing
A1: Name | B1: The Impact of Economic Wellbeing in Sullivan County (n = 95)
A2: Table/Figure/Both | B2: Both
A3: Object ID | B3: =IF($B$1="","",_xlfn.XLOOKUP($B$1,Master!$F$2:$F$308,Master!$G$2:$G$308,"")) -> tbl-SC-eco-wellbeing
A4: Figure ID | B4: =IF($B$1="","",_xlfn.XLOOKUP($B$1,Master!$F$2:$F$308,Master!$H$2:$H$308,"")) -> fig-SC-eco-wellbeing | F4: number | G4: percent1 | H4: percent1 | I4: percent1 | J4: percent1
A5: Table Rules | E5: Enter Data | F5: Likert Scale | G5: Poverty | H5: Unemployment | I5: Nutrition Security | J5: Housing Stability & Affordability
A6: Multilevel Headers | B6: FALSE | F6: 1 | G6: 1.1 | H6: 4.2 | I6: 2.1 | J6: 2.1
F7: 2 | G7: 5.3 | H7: 7.4 | I7: 5.3 | J7: 6.3
F8: 3 | G8: 20 | H8: 24.2 | I8: 31.9 | J8: 24.2
A9: Figure Rules | F9: 4 | G9: 16.8 | H9: 34.7 | I9: 24.5 | J9: 16.8
A10: Figure Type | B10: Clustered Bar | F10: 5 | G10: 56.8 | H10: 29.5 | I10: 36.2 | J10: 50.5
A11: X Column | B11: Likert Scale (1 = Very Little Impact and 5 = Highly Impacted)
A12: Y Column | B12: Percent
A13: X Axis Title | B13: Likert Scale (1 = Very Little Impact and 5 = Highly Impacted)
A14: Y Axis Title | B14: Percent
A15: Start at Zero | B15: TRUE
A16: Pivot for Chart | B16: TRUE
A18: Source Specifications
A19: Table ID
A20: URL
A21: Data Year
A22: Estimate Type
A23: Citation Month
A24: Citation Year
A25: Custom Text
A27: Note Specifications

Sheet SC Impact MH & SU
A1: Name | B1: The Impact of Mental Wellbeing & Substance Use in Sullivan County (n = 93)
A2: Table/Figure/Both | B2: Figure
A3: Object ID | B3: =IF($B$1="","",_xlfn.XLOOKUP($B$1,Master!$F$2:$F$308,Master!$G$2:$G$308,"")) -> tbl-SC-impact-mhsu
A4: Figure ID | B4: =IF($B$1="","",_xlfn.XLOOKUP($B$1,Master!$F$2:$F$308,Master!$H$2:$H$308,"")) -> fig-SC-impact-mhsu | F4: number | G4: percent1 | H4: percent1 | I4: percent1 | J4: percent1 | K4: percent1 | L4: percent1
A5: Table Rules | E5: Enter Data | F5: Likert Scale | G5: Anxiety & Stress | H5: Suicide | I5: Depression | J5: Substance Use | K5: Adverse Childhood Experiences | L5: Healthy Eating
A6: Multilevel Headers | B6: FALSE | F6: 1 | G6: 0 | H6: 10.9 | I6: 0 | J6: 5.5 | K6: 7.6 | L6: 3.2
F7: 2 | G7: 1.1 | H7: 14.1 | I7: 6.5 | J7: 8.8 | K7: 13 | L7: 7.5
F8: 3 | G8: 10.8 | H8: 32.6 | I8: 17.2 | J8: 22 | K8: 21.7 | L8: 18.3
A9: Figure Rules | F9: 4 | G9: 20.4 | H9: 27.2 | I9: 31.2 | J9: 24.2 | K9: 24 | L9: 33.3
A10: Figure Type | B10: Clustered Bar | F10: 5 | G10: 67.7 | H10: 15.2 | I10: 45.2 | J10: 39.6 | K10: 33.7 | L10: 37.6
A11: X Column | B11: Likert Scale (1 = Very Little Impact and 5 = Highly Impacted)
A12: Y Column | B12: Percent
A13: X Axis Title | B13: Likert Scale (1 = Very Little Impact and 5 = Highly Impacted)
A14: Y Axis Title | B14: Percent
A15: Start at Zero | B15: TRUE
A16: Pivot for Chart | B16: TRUE
A18: Source Specifications
A19: Table ID
A20: URL
A21: Data Year
A22: Estimate Type
A23: Citation Month
A24: Citation Year
A25: Custom Text
A27: Note Specifications

Sheet SC Impact Hlth Ins & Access
A1: Name | B1: The Impact of Health Insurance Coverage & Access to Care in Sullivan County (n = 92)
A2: Table/Figure/Both | B2: Figure
A3: Object ID | B3: =IF($B$1="","",_xlfn.XLOOKUP($B$1,Master!$F$2:$F$308,Master!$G$2:$G$308,"")) -> tbl-SC-impact-hlthinsur-access
A4: Figure ID | B4: =IF($B$1="","",_xlfn.XLOOKUP($B$1,Master!$F$2:$F$308,Master!$H$2:$H$308,"")) -> fig-SC-impact-hlthinsur-access | F4: number | G4: percent1 | H4: percent1 | I4: percent1 | J4: percent1
A5: Table Rules | E5: Enter Data | F5: Likert Scale | G5: Access To & Use of Prenatal Care | H5: Prevention of Infant & Maternal Mortality | I5: Preventive Services for Chronic Disease Prevention & Control | J5: Oral Health Care
A6: Multilevel Headers | B6: FALSE | F6: 1 | G6: 9.8 | H6: 12 | I6: 1.1 | J6: 5.4
F7: 2 | G7: 13 | H7: 19.6 | I7: 8.7 | J7: 7.6
F8: 3 | G8: 35.9 | H8: 31.5 | I8: 20.7 | J8: 23.9
A9: Figure Rules | F9: 4 | G9: 25 | H9: 22.8 | I9: 31.5 | J9: 34.8
A10: Figure Type | B10: Clustered Bar | F10: 5 | G10: 16.3 | H10: 14.1 | I10: 38 | J10: 28.3
A11: X Column | B11: Likert Scale (1 = Very Little Impact and 5 = Highly Impacted)
A12: Y Column | B12: Percent
A13: X Axis Title | B13: Likert Scale (1 = Very Little Impact and 5 = Highly Impacted)
A14: Y Axis Title | B14: Percent
A15: Start at Zero | B15: TRUE
A16: Pivot for Chart | B16: TRUE
A18: Source Specifications
A19: Table ID
A20: URL
A21: Data Year
A22: Estimate Type
A23: Citation Month
A24: Citation Year
A25: Custom Text
A27: Note Specifications

Sheet UC Top Affect Health
A1: Name | B1: Top Rated Issues That Affect Health in Ulster County (n = 73)
A2: Table/Figure/Both | B2: Figure
A3: Object ID | B3: =IF($B$1="","",_xlfn.XLOOKUP($B$1,Master!$F$2:$F$308,Master!$G$2:$G$308,"")) -> tbl-UC-affect-health
A4: Figure ID | B4: =IF($B$1="","",_xlfn.XLOOKUP($B$1,Master!$F$2:$F$308,Master!$H$2:$H$308,"")) -> fig-UC-affect-health | F4: percent1 | G4: percent1 | H4: percent1 | I4: percent1 | J4: percent1 | K4: percent1 | L4: percent1 | M4: percent1 | N4: percent1 | O4: percent1
A5: Table Rules | E5: Enter Data | F5: Access to affordable, decent and safe housing | G5: Access to mental health providers | H5: Access to specialty services/providers | I5: Access to affordable, nutritious food | J5: Access to affordable, reliable transportation | K5: Access to affordable health insurance | L5: Access to medical providers | M5: Access to high quality education | N5: Access to culturally sensitive health care providers | O5: Access to clean water and non-polluted air
A6: Multilevel Headers | B6: FALSE | F6: 52.1 | G6: 50.7 | H6: 43.8 | I6: 40 | J6: 37 | K6: 30.1 | L6: 24.7 | M6: 11 | N6: 11 | O6: 0
A9: Figure Rules
A10: Figure Type | B10: Clustered Bar
A11: X Column | B11: Category
A12: Y Column | B12: Percent
A13: X Axis Title
A14: Y Axis Title | B14: Percent
A15: Start at Zero | B15: TRUE
A18: Source Specifications
A19: Table ID
A20: URL
A21: Data Year
A22: Estimate Type
A23: Citation Month
A24: Citation Year
A25: Custom Text
A27: Note Specifications

Sheet UC Top Barriers
A1: Name | B1: Top Rated Barriers to Achieving Better Health in Ulster County (n = 73)
A2: Table/Figure/Both | B2: Figure
A3: Object ID | B3: =IF($B$1="","",_xlfn.XLOOKUP($B$1,Master!$F$2:$F$308,Master!$G$2:$G$308,"")) -> tbl-UC-achieve-health
A4: Figure ID | B4: =IF($B$1="","",_xlfn.XLOOKUP($B$1,Master!$F$2:$F$308,Master!$H$2:$H$308,"")) -> fig-UC-achieve-health | F4: percent1 | G4: percent1 | H4: percent1 | I4: percent1 | J4: percent1 | K4: percent1 | L4: percent1 | M4: percent1 | N4: percent1 | O4: percent1 | P4: percent1 | Q4: percent1
A5: Table Rules | E5: Enter Data | F5: Knowledge of existing resources | G5: Health literacy | H5: Substance Use Disorder (SUD) or Alcohol Use Disorder (AUD) | I5: Having someone to help them understand their medical condition | J5: Geographic location living in a rural area | K5: Having someone help them understand insurance | L5: Other | M5: Quality of education | N5: Having a safe place to play and/or exercise | O5: Geographic location- living in an urban area | P5: Cultural customs | Q5: Attainment of education
A6: Multilevel Headers | B6: FALSE | F6: 65.8 | G6: 46.6 | H6: 38.4 | I6: 37 | J6: 35.6 | K6: 27.4 | L6: 20.6 | M6: 9.6 | N6: 6.9 | O6: 5.5 | P6: 4.1 | Q6: 2.7
A9: Figure Rules
A10: Figure Type | B10: Clustered Bar
A11: X Column | B11: Category
A12: Y Column | B12: Percent
A13: X Axis Title
A14: Y Axis Title | B14: Percent
A15: Start at Zero | B15: TRUE
A18: Source Specifications
A19: Table ID
A20: URL
A21: Data Year
A22: Estimate Type
A23: Citation Month
A24: Citation Year
A25: Custom Text
A27: Note Specifications

Sheet UC Impact Health
A1: Name | B1: The Impact of Health Issues in Ulster County (n = 73)
A2: Table/Figure/Both | B2: Figure
A3: Object ID | B3: =IF($B$1="","",_xlfn.XLOOKUP($B$1,Master!$F$2:$F$308,Master!$G$2:$G$308,"")) -> tbl-UC-impact-hlth-issue
A4: Figure ID | B4: =IF($B$1="","",_xlfn.XLOOKUP($B$1,Master!$F$2:$F$308,Master!$H$2:$H$308,"")) -> fig-UC-impact-hlth-issue | F4: number | G4: percent1 | H4: percent1 | I4: percent1 | J4: percent1 | K4: percent1 | L4: percent1
A5: Table Rules | E5: Enter Data | F5: Likert Scale | G5: Chronic Disease | H5: Health Disparities | I5: Mental Health and Substance Use Issues | J5: Maternal and Child Health Issues | K5: Environmental Factors | L5: Communicable Diseases
A6: Multilevel Headers | B6: FALSE | F6: 1 | G6: 2.9 | H6: 2.9 | I6: 2.9 | J6: 13 | K6: 15.7 | L6: 16.9
F7: 2 | G7: 4.3 | H7: 5.7 | I7: 5.7 | J7: 8.7 | K7: 15.7 | L7: 19.7
F8: 3 | G8: 14.3 | H8: 10 | I8: 14.3 | J8: 34.8 | K8: 30 | L8: 31
A9: Figure Rules | F9: 4 | G9: 18.6 | H9: 31.4 | I9: 20 | J9: 14.5 | K9: 18.6 | L9: 14.1
A10: Figure Type | B10: Clustered Bar | F10: 5 | G10: 60 | H10: 50 | I10: 57.1 | J10: 29 | K10: 20 | L10: 18.3
A11: X Column | B11: Likert Scale (1 = Very Little Impact and 5 = Highly Impacted)
A12: Y Column | B12: Percent
A13: X Axis Title | B13: Likert Scale (1 = Very Little Impact and 5 = Highly Impacted)
A14: Y Axis Title | B14: Percent
A15: Start at Zero | B15: TRUE
A16: Pivot For Chart | B16: TRUE
A18: Source Specifications
A19: Table ID
A20: URL
A21: Data Year
A22: Estimate Type
A23: Citation Month
A24: Citation Year
A25: Custom Text
A27: Note Specifications

Sheet UC Impact SDOH
A1: Name | B1: The Impact of the Social Determinants of Health in Ulster County (n = 70)
A2: Table/Figure/Both | B2: Figure
A3: Object ID | B3: =IF($B$1="","",_xlfn.XLOOKUP($B$1,Master!$F$2:$F$308,Master!$G$2:$G$308,"")) -> tbl-UC-impact-sdoh
A4: Figure ID | B4: =IF($B$1="","",_xlfn.XLOOKUP($B$1,Master!$F$2:$F$308,Master!$H$2:$H$308,"")) -> fig-UC-impact-sdoh | F4: percent1 | G4: percent1 | H4: percent1 | I4: percent1 | J4: percent1 | K4: percent1
A5: Table Rules | E5: Enter Data | F5: Economic | G5: Mental Wellbeing & Substance Use | H5: Health Insurance Coverage & Access to Care | I5: Safe & Healthy Communities | J5: Healthy Children | K5: Pre K - Grade 12 Student Success & Educational Attainment
A6: Multilevel Headers | B6: FALSE | F6: 84.3 | G6: 78.6 | H6: 60 | I6: 47.1 | J6: 18.6 | K6: 11.4
A9: Figure Rules
A10: Figure Type | B10: Clustered Bar
A11: X Column | B11: Category
A12: Y Column | B12: Percent
A13: X Axis Title
A14: Y Axis Title | B14: Percent
A15: Start at Zero | B15: TRUE
A18: Source Specifications
A19: Table ID
A20: URL
A21: Data Year
A22: Estimate Type
A23: Citation Month
A24: Citation Year
A25: Custom Text
A27: Note Specfications

Sheet UC Impact Eco Wellbeing
A1: Name | B1: The Impact of Economic Wellbeing in Ulster County (n = 69)
A2: Table/Figure/Both | B2: Figure
A3: Object ID | B3: =IF($B$1="","",_xlfn.XLOOKUP($B$1,Master!$F$2:$F$308,Master!$G$2:$G$308,"")) -> tbl-UC-eco-wellbeing
A4: Figure ID | B4: =IF($B$1="","",_xlfn.XLOOKUP($B$1,Master!$F$2:$F$308,Master!$H$2:$H$308,"")) -> fig-UC-eco-wellbeing | F4: number | G4: percent1 | H4: percent1 | I4: percent1 | J4: percent1
A5: Table Rules | E5: Enter Data | F5: Likert Scale | G5: Poverty | H5: Unemployment | I5: Nutrition Security | J5: Housing Stability & Affordability
A6: Multilevel Headers | B6: FALSE | F6: 1 | G6: 1.5 | H6: 1.5 | I6: 3 | J6: 2.9
F7: 2 | G7: 1.5 | H7: 7.4 | I7: 6 | J7: 2.9
F8: 3 | G8: 20.3 | H8: 22.1 | I8: 23.9 | J8: 20.3
A9: Figure Rules | F9: 4 | G9: 20.3 | H9: 38.2 | I9: 29.9 | J9: 20.3
A10: Figure Type | B10: Clustered Bar | F10: 5 | G10: 56.5 | H10: 30.9 | I10: 37.3 | J10: 53.6
A11: X Column | B11: Likert Scale (1 = Very Little Impact and 5 = Highly Impacted)
A12: Y Column | B12: Percent
A13: X Axis Title | B13: Likert Scale (1 = Very Little Impact and 5 = Highly Impacted)
A14: Y Axis Title | B14: Percent
A15: Start at Zero | B15: TRUE
A16: Pivot For Chart | B16: TRUE
A18: Source Specifications
A19: Table ID
A20: URL
A21: Data Year
A22: Estimate Type
A23: Citation Month
A24: Citation Year
A25: Custom Text
A27: Note Specifications

Sheet UC Impact MH & SU
A1: Name | B1: The Impact of Mental Wellbeing & Substance Use in Ulster County (n = 67)
A2: Table/Figure/Both | B2: Figure
A3: Object ID | B3: =IF($B$1="","",_xlfn.XLOOKUP($B$1,Master!$F$2:$F$308,Master!$G$2:$G$308,"")) -> tbl-UC-impact-mhsu
A4: Figure ID | B4: =IF($B$1="","",_xlfn.XLOOKUP($B$1,Master!$F$2:$F$308,Master!$H$2:$H$308,"")) -> fig-UC-impact-mhsu | F4: number | G4: percent1 | H4: percent1 | I4: percent1 | J4: percent1 | K4: percent1 | L4: percent1
A5: Table Rules | E5: Enter Data | F5: Likert Scale | G5: Anxiety & Stress | H5: Suicide | I5: Depression | J5: Substance Use | K5: Adverse Childhood Experiences | L5: Healthy Eating
A6: Multilevel Headers | B6: FALSE | F6: 1 | G6: 0 | H6: 12.3 | I6: 0 | J6: 3.1 | K6: 4.6 | L6: 6
F7: 2 | G7: 1.5 | H7: 13.9 | I7: 4.5 | J7: 6.2 | K7: 9.2 | L7: 9
F8: 3 | G8: 6 | H8: 29.2 | I8: 14.9 | J8: 26.2 | K8: 27.7 | L8: 22.4
A9: Figure Rules | F9: 4 | G9: 31.3 | H9: 30.8 | I9: 32.8 | J9: 23.1 | K9: 27.7 | L9: 30
A10: Figure Type | B10: Clustered Bar | F10: 5 | G10: 61.2 | H10: 13.9 | I10: 47.8 | J10: 41.6 | K10: 30.8 | L10: 32.8
A11: X Column | B11: Likert Scale (1 = Very Little Impact and 5 = Highly Impacted)
A12: Y Column | B12: Percent
A13: X Axis Title | B13: Likert Scale (1 = Very Little Impact and 5 = Highly Impacted)
A14: Y Axis Title | B14: Percent
A15: Start at Zero | B15: TRUE
A16: Pivot For Chart | B16: TRUE
A18: Source Specifications
A19: Table ID
A20: URL
A21: Data Year
A22: Estimate Type
A23: Citation Month
A24: Citation Year
A25: Custom Text
A27: Note Specfications

Sheet UC Impact Hlth Ins & Access
A1: Name | B1: The Impact of Health Insurance Coverage & Access to Care in Ulster County (n = 66)
A2: Table/Figure/Both | B2: Figure
A3: Object ID | B3: =IF($B$1="","",_xlfn.XLOOKUP($B$1,Master!$F$2:$F$308,Master!$G$2:$G$308,"")) -> tbl-UC-impact-hlthinsur-access
A4: Figure ID | B4: =IF($B$1="","",_xlfn.XLOOKUP($B$1,Master!$F$2:$F$308,Master!$H$2:$H$308,"")) -> fig-UC-impact-hlthinsur-access | F4: number | G4: percent1 | H4: percent1 | I4: percent1 | J4: percent1
A5: Table Rules | E5: Enter Data | F5: Likert Scale | G5: Access To & Use of Prenatal Care | H5: Prevention of Infant & Maternal Mortality | I5: Preventive Services for Chronic Disease Prevention & Control | J5: Oral Health Care
A6: Multilevel Headers | B6: FALSE | F6: 1 | G6: 16.9 | H6: 20 | I6: 3 | J6: 10.6
F7: 2 | G7: 13.9 | H7: 13.9 | I7: 12.1 | J7: 6.1
F8: 3 | G8: 30.8 | H8: 30.8 | I8: 13.6 | J8: 19.7
A9: Figure Rules | F9: 4 | G9: 20 | H9: 20 | I9: 31.8 | J9: 31.8
A10: Figure Type | B10: Clustered Bar | F10: 5 | G10: 18.5 | H10: 15.4 | I10: 39.4 | J10: 31.8
A11: X Column | B11: Likert Scale (1 = Very Little Impact and 5 = Highly Impacted)
A12: Y Column | B12: Percent
A13: X Axis Title | B13: Likert Scale (1 = Very Little Impact and 5 = Highly Impacted)
A14: Y Axis Title | B14: Percent
A15: Start at Zero | B15: TRUE
A16: Pivot For Chart | B16: TRUE
A18: Source Specifications
A19: Table ID
A20: URL
A21: Data Year
A22: Estimate Type
A23: Citation Month
A24: Citation Year
A25: Custom Text
A27: Note Specfications

Sheet WC Top Affect Health
A1: Name | B1: Top Rated Issues That Affect Health in Westchester County (n = 40)
A2: Table/Figure/Both | B2: Figure
A3: Object ID | B3: =IF($B$1="","",_xlfn.XLOOKUP($B$1,Master!$F$2:$F$308,Master!$G$2:$G$308,"")) -> tbl-WC-affect-health
A4: Figure ID | B4: =IF($B$1="","",_xlfn.XLOOKUP($B$1,Master!$F$2:$F$308,Master!$H$2:$H$308,"")) -> fig-WC-affect-health | F4: percent1 | G4: percent1 | H4: percent1 | I4: percent1 | J4: percent1 | K4: percent1 | L4: percent1 | M4: percent1 | N4: percent1 | O4: percent1
A5: Table Rules | E5: Enter Data | F5: Access to mental health providers | G5: Access to specialty services/providers | H5: Access to affordable, decent and safe housing | I5: Access to affordable, reliable transportation | J5: Access to affordable, nutritious food | K5: Access to medical providers | L5: Access to affordable health insurance | M5: Access to culturally sensitive health care providers | N5: Access to high quality education | O5: Access to clean water and non-polluted air
A6: Multilevel Headers | B6: FALSE | F6: 57.5 | G6: 50 | H6: 42.5 | I6: 35 | J6: 32.5 | K6: 27.5 | L6: 22.5 | M6: 17.5 | N6: 15 | O6: 0
A9: Figure Rules
A10: Figure Type | B10: Clustered Bar
A11: X Column | B11: Category
A12: Y Column | B12: Percent
A13: X Axis Title
A14: Y Axis Title | B14: Percent
A15: Start at Zero | B15: TRUE
A18: Source Specifications
A19: Table ID
A20: URL
A21: Data Year
A22: Estimate Type
A23: Citation Month
A24: Citation Year
A25: Custom Text
A27: Note Specifications

Sheet WC Top Barriers
A1: Name | B1: Top Rated Barriers to Achieving Better Health in Westchester County (n = 40)
A2: Table/Figure/Both | B2: Figure
A3: Object ID | B3: =IF($B$1="","",_xlfn.XLOOKUP($B$1,Master!$F$2:$F$308,Master!$G$2:$G$308,"")) -> tbl-WC-achieve-health
A4: Figure ID | B4: =IF($B$1="","",_xlfn.XLOOKUP($B$1,Master!$F$2:$F$308,Master!$H$2:$H$308,"")) -> fig-WC-achieve-health | F4: percent1 | G4: percent1 | H4: percent1 | I4: percent1 | J4: percent1 | K4: percent1 | L4: percent1 | M4: percent1 | N4: percent1 | O4: percent1 | P4: percent1 | Q4: percent1
A5: Table Rules | E5: Enter Data | F5: Knowledge of existing resources | G5: Health literacy | H5: Having someone help them understand insurance | I5: Having someone to help them understand their medical condition | J5: Geographic locationliving in a rural area | K5: Substance Use Disorder (SUD) or Alcohol Use Disorder (AUD) | L5: Other | M5: Quality of education | N5: Cultural customs | O5: Having a safe place to play and/or exercise | P5: Geographic location- living in an urban area | Q5: Attainment of education
A6: Multilevel Headers | B6: FALSE | F6: 62.5 | G6: 50 | H6: 35 | I6: 32.5 | J6: 30 | K6: 27.5 | L6: 25 | M6: 15 | N6: 10 | O6: 7.5 | P6: 5 | Q6: 0
A9: Figure Rules
A10: Figure Type | B10: Clustered Bar
A11: X Column | B11: Category
A12: Y Column | B12: Percent
A13: X Axis Title
A14: Y Axis Title | B14: Percent
A15: Start at Zero | B15: TRUE
A18: Source Specifications
A19: Table ID
A20: URL
A21: Data Year
A22: Estimate Type
A23: Citation Month
A24: Citation Year
A25: Custom Text
A27: Note Specfications

Sheet WC Impact Health
A1: Name | B1: The Impact of Health Issues in Westchester County (n = 39)
A2: Table/Figure/Both | B2: Figure
A3: Object ID | B3: =IF($B$1="","",_xlfn.XLOOKUP($B$1,Master!$F$2:$F$308,Master!$G$2:$G$308,"")) -> tbl-WC-impact-hlth-issue
A4: Figure ID | B4: =IF($B$1="","",_xlfn.XLOOKUP($B$1,Master!$F$2:$F$308,Master!$H$2:$H$308,"")) -> fig-WC-impact-hlth-issue | F4: number | G4: percent1 | H4: percent1 | I4: percent1 | J4: percent1 | K4: percent1 | L4: percent1
A5: Table Rules | E5: Enter Data | F5: Likert Scale | G5: Chronic Disease | H5: Health Disparities | I5: Mental Health and Substance Use Issues | J5: Maternal and Child Health Issues | K5: Environmental Factors | L5: Communicable Diseases
A6: Multilevel Headers | B6: FALSE | F6: 1 | G6: 5.3 | H6: 2.6 | I6: 2.6 | J6: 10.3 | K6: 15.8 | L6: 15.4
F7: 2 | G7: 2.6 | H7: 2.6 | I7: 7.9 | J7: 10.3 | K7: 13.2 | L7: 18
F8: 3 | G8: 18.4 | H8: 18.4 | I8: 7.9 | J8: 38.5 | K8: 34.2 | L8: 38.5
A9: Figure Rules | F9: 4 | G9: 18.4 | H9: 21.1 | I9: 21.1 | J9: 12.8 | K9: 23.7 | L9: 7.7
A10: Figure Type | B10: Clustered Bar | F10: 5 | G10: 55.3 | H10: 55.3 | I10: 60.5 | J10: 28.2 | K10: 13.2 | L10: 20.5
A11: X Column | B11: Likert Scale (1 = Very Little Impact and 5 = Highly Impacted)
A12: Y Column | B12: Percent
A13: X Axis Title | B13: Likert Scale (1 = Very Little Impact and 5 = Highly Impacted)
A14: Y Axis Title | B14: Percent
A15: Start at Zero | B15: TRUE
A16: Pivot for Chart | B16: TRUE
A18: Source Specifications
A19: Table ID
A20: URL
A21: Data Year
A22: Estimate Type
A23: Citation Month
A24: Citation Year
A25: Custom Text
A27: Note Specifications

Sheet WC Impact SDOH
A1: Name | B1: The Impact of the Social Determinants of Health in Westchester County (n = 38)
A2: Table/Figure/Both | B2: Figure
A3: Object ID | B3: =IF($B$1="","",_xlfn.XLOOKUP($B$1,Master!$F$2:$F$308,Master!$G$2:$G$308,"")) -> tbl-WC-impact-sdoh
A4: Figure ID | B4: =IF($B$1="","",_xlfn.XLOOKUP($B$1,Master!$F$2:$F$308,Master!$H$2:$H$308,"")) -> fig-WC-impact-sdoh | F4: percent1 | G4: percent1 | H4: percent1 | I4: percent1 | J4: percent1 | K4: percent1
A5: Table Rules | E5: Enter Data | F5: Mental Wellbeing & Substance Use | G5: Economic | H5: Health Insurance Coverage & Access to Care | I5: Safe & Healthy Communities | J5: Healthy Children | K5: Pre K - Grade 12 Student Success & Educational Attainment
A6: Multilevel Headers | B6: FALSE | F6: 81.6 | G6: 79 | H6: 68.4 | I6: 36.8 | J6: 18.4 | K6: 15.8
A9: Figure Rules
A10: Figure Type | B10: Clustered Bar
A11: X Column | B11: Category
A12: Y Column | B12: Percent
A13: X Axis Title
A14: Y Axis Title | B14: Percent
A15: Start at Zero | B15: TRUE
A18: Source Specifications
A19: Table ID
A20: URL
A21: Data Year
A22: Estimate Type
A23: Citation Month
A24: Citation Year
A25: Custom Text
A27: Note Specfications

Sheet WC Impact Eco Wellbeing
A1: Name | B1: The Impact of Economic Wellbeing in Westchester County (n = 37)
A2: Table/Figure/Both | B2: Figure
A3: Object ID | B3: =IF($B$1="","",_xlfn.XLOOKUP($B$1,Master!$F$2:$F$308,Master!$G$2:$G$308,"")) -> tbl-WC-eco-wellbeing
A4: Figure ID | B4: =IF($B$1="","",_xlfn.XLOOKUP($B$1,Master!$F$2:$F$308,Master!$H$2:$H$308,"")) -> fig-WC-eco-wellbeing | F4: number | G4: percent1 | H4: percent1 | I4: percent1 | J4: percent1
A5: Table Rules | E5: Enter Data | F5: Likert Scale | G5: Poverty | H5: Unemployment | I5: Nutrition Security | J5: Housing Stability & Affordability
A6: Multilevel Headers | B6: FALSE | F6: 1 | G6: 0 | H6: 2.8 | I6: 0 | J6: 0
F7: 2 | G7: 5.4 | H7: 2.8 | I7: 11.1 | J7: 2.7
F8: 3 | G8: 21.6 | H8: 22.2 | I8: 27.8 | J8: 24.3
A9: Figure Rules | F9: 4 | G9: 16.2 | H9: 50 | I9: 36.1 | J9: 13.5
A10: Figure Type | B10: Clustered Bar | F10: 5 | G10: 56.8 | H10: 22.2 | I10: 25 | J10: 59.5
A11: X Column | B11: Likert Scale (1 = Very Little Impact and 5 = Highly Impacted)
A12: Y Column | B12: Percent
A13: X Axis Title | B13: Likert Scale (1 = Very Little Impact and 5 = Highly Impacted)
A14: Y Axis Title | B14: Percent
A15: Start at Zero | B15: TRUE
A16: Pivot for Chart | B16: TRUE
A18: Source Specifications
A19: Table ID
A20: URL
A21: Data Year
A22: Estimate Type
A23: Citation Month
A24: Citation Year
A25: Custom Text
A27: Note Specifications

Sheet WC Impact MH & SU
A1: Name | B1: The Impact of Mental Wellbeing & Substance Use in Westchester County (n = 35)
A2: Table/Figure/Both | B2: Figure
A3: Object ID | B3: =IF($B$1="","",_xlfn.XLOOKUP($B$1,Master!$F$2:$F$308,Master!$G$2:$G$308,"")) -> tbl-WC-impact-mhsu
A4: Figure ID | B4: =IF($B$1="","",_xlfn.XLOOKUP($B$1,Master!$F$2:$F$308,Master!$H$2:$H$308,"")) -> fig-WC-impact-mhsu | F4: number | G4: percent1 | H4: percent1 | I4: percent1 | J4: percent1 | K4: percent1 | L4: percent1
A5: Table Rules | E5: Enter Data | F5: Likert Scale | G5: Anxiety & Stress | H5: Suicide | I5: Depression | J5: Substance Use | K5: Adverse Childhood Experiences | L5: Healthy Eating
A6: Multilevel Headers | B6: FALSE | F6: 1 | G6: 0 | H6: 14.3 | I6: 0 | J6: 11.8 | K6: 8.6 | L6: 2.9
F7: 2 | G7: 2.9 | H7: 20 | I7: 5.7 | J7: 5.9 | K7: 11.4 | L7: 11.4
F8: 3 | G8: 2.9 | H8: 25.7 | I8: 11.4 | J8: 17.7 | K8: 17.1 | L8: 22.9
A9: Figure Rules | F9: 4 | G9: 28.6 | H9: 22.9 | I9: 37.1 | J9: 32.4 | K9: 31.4 | L9: 25.7
A10: Figure Type | B10: Clustered Bar | F10: 5 | G10: 65.7 | H10: 17.1 | I10: 45.7 | J10: 32.4 | K10: 31.4 | L10: 37.1
A11: X Column | B11: Likert Scale (1 = Very Little Impact and 5 = Highly Impacted)
A12: Y Column | B12: Percent
A13: X Axis Title | B13: Likert Scale (1 = Very Little Impact and 5 = Highly Impacted)
A14: Y Axis Title | B14: Percent
A15: Start at Zero | B15: TRUE
A16: Pivot for Chart | B16: TRUE
A18: Source Specifications
A19: Table ID
A20: URL
A21: Data Year
A22: Estimate Type
A23: Citation Month
A24: Citation Year
A25: Custom Text
A27: Note Specfications

Sheet WC Impact Hlth Ins & Access
A1: Name | B1: The Impact of Health Insurance Coverage & Access to Care in Westchester County (n = 35)
A2: Table/Figure/Both | B2: Figure
A3: Object ID | B3: =IF($B$1="","",_xlfn.XLOOKUP($B$1,Master!$F$2:$F$308,Master!$G$2:$G$308,"")) -> tbl-WC-impact-hlthinsur-access
A4: Figure ID | B4: =IF($B$1="","",_xlfn.XLOOKUP($B$1,Master!$F$2:$F$308,Master!$H$2:$H$308,"")) -> fig-WC-impact-hlthinsur-access | F4: number | G4: percent1 | H4: percent1 | I4: percent1 | J4: percent1
A5: Table Rules | E5: Enter Data | F5: Likert Scale | G5: Access To & Use of Prenatal Care | H5: Prevention of Infant & Maternal Mortality | I5: Preventive Services for Chronic Disease Prevention & Control | J5: Oral Health Care
A6: Multilevel Headers | B6: FALSE | F6: 1 | G6: 11.4 | H6: 17.1 | I6: 5.9 | J6: 8.6
F7: 2 | G7: 20 | H7: 20 | I7: 8.8 | J7: 5.7
F8: 3 | G8: 28.6 | H8: 28.6 | I8: 14.7 | J8: 20
A9: Figure Rules | F9: 4 | G9: 17.1 | H9: 14.3 | I9: 29.4 | J9: 34.3
A10: Figure Type | B10: Clustered Bar | F10: 5 | G10: 22.9 | H10: 20 | I10: 41.2 | J10: 31.4
A11: X Column | B11: Likert Scale (1 = Very Little Impact and 5 = Highly Impacted)
A12: Y Column | B12: Percent
A13: X Axis Title | B13: Likert Scale (1 = Very Little Impact and 5 = Highly Impacted)
A14: Y Axis Title | B14: Percent
A15: Start at Zero | B15: TRUE
A16: Pivot for Chart | B16: TRUE
A18: Source Specifications
A19: Table ID
A20: URL
A21: Data Year
A22: Estimate Type
A23: Citation Month
A24: Citation Year
A25: Custom Text
A27: Note Specfications

Sheet HEALTH BEHAVIORS INDICATORS

Sheet Leisure Time Physical Act Adult
A1: Name | B1: Percentage of Adults Who Participated in Leisure Time Physical Activity in the Past 30 Days, 2016, 2018, and 2021
A2: Table/Figure/Both | B2: Both
A3: Object ID | B3: =IF($B$1="","",_xlfn.XLOOKUP($B$1,Master!$F$2:$F$308,Master!$G$2:$G$308,"")) -> tbl-BRFSS-adult-leisure-PA
A4: Figure ID | B4: =IF($B$1="","",_xlfn.XLOOKUP($B$1,Master!$F$2:$F$308,Master!$H$2:$H$308,"")) -> fig-BRFSS-leisure-PA | F4: number | G4: percent1 | H4: percent1 | I4: percent1 | J4: percent1 | K4: percent1 | L4: percent1 | M4: percent1 | N4: percent1 | O4: percent1
A5: Table Rules | E5: Enter Data | F5: Year | G5: Dutchess | H5: Orange | I5: Putnam | J5: Rockland | K5: Sullivan | L5: Ulster | M5: Westchester | N5: NYS excl NYC | O5: NYS
A6: Multilevel Headers | B6: FALSE | F6: 2016 | G6: 74.7 | H6: 70.7 | I6: 75 | J6: 73.5 | K6: 72.4 | L6: 81.9 | M6: 77.1 | N6: 75 | O6: 74
F7: 2018 | G7: 80.2 | H7: 70.5 | I7: 83.4 | J7: 76.9 | K7: 67.9 | L7: 79.9 | M7: 81.6 | N7: 78.3 | O7: 76.4
F8: 2021 | G8: 76.8 | H8: 75.5 | I8: 78.7 | J8: 70.6 | K8: 75.7 | L8: 82.6 | M8: 78.4 | N8: 76.3 | O8: 74.6
A9: Figure Rules
A10: Figure Type | B10: Line
A11: X Column | B11: Year
A12: Y Column | B12: Percent
A13: X Axis Title
A14: Y Axis Title | B14: Percent
A15: Start at Zero | B15: TRUE
A18: Source Specifications
A19: Table ID
A20: URL | B20: https://health.data.ny.gov/Health/Behavioral-Risk-Factor-Surveillance-System-BRFSS-H/jsy7-eb4n/data
A21: Data Year
A22: Estimate Type
A23: Citation Month | B23: May
A24: Citation Year | B24: 2025
A25: Custom Text
A27: Note Specfications
A28: Note: The percentage is age-adjusted. An adult is a person aged 18 years or older. The Behavioral Risk Factor Surveillance System asks respondents “During the past month, other than your regular job, did you participate in any physical activities or exercises such as running, calisthenics, golf, gardening, or walking for exercise?”

Sheet Consuming Less Fruit-Veg
A1: Name | B1: Percentage of Adults Who Report Consuming Less Than One Fruit and Less Than One Vegetable Daily, 2016, 2018, and 2021
A2: Table/Figure/Both | B2: Both
A3: Object ID | B3: =IF($B$1="","",_xlfn.XLOOKUP($B$1,Master!$F$2:$F$308,Master!$G$2:$G$308,"")) -> tbl-BRFSS-adult-fruit-veg
A4: Figure ID | B4: =IF($B$1="","",_xlfn.XLOOKUP($B$1,Master!$F$2:$F$308,Master!$H$2:$H$308,"")) -> fig-BRFSS-fruit-veg | F4: number | G4: percent1 | H4: percent1 | I4: percent1 | J4: percent1 | K4: percent1 | L4: percent1 | M4: percent1 | N4: percent1 | O4: percent1
A5: Table Rules | E5: Enter Data | F5: Year | G5: Dutchess | H5: Orange | I5: Putnam | J5: Rockland | K5: Sullivan | L5: Ulster | M5: Westchester | N5: NYS excl NYC | O5: NYS
A6: Multilevel Headers | B6: FALSE | F6: 2016 | G6: 24.2 | H6: 24.5 | I6: 27 | J6: 25.9 | K6: 28.7 | L6: 22.9 | M6: 28.6 | N6: 29 | O6: 31.5
F7: 2018 | G7: 25.4 | H7: 23.3 | I7: 22.9 | J7: 28.5 | K7: 23.5 | L7: 25.5 | M7: 25 | N7: 26.1 | O7: 28.1
F8: 2021 | G8: 39.2* | H8: 31.9 | I8: 30.1 | J8: 35.1 | K8: 30.5 | L8: 30.4 | M8: 30.5 | N8: 32.6 | O8: 34.2
A9: Figure Rules
A10: Figure Type | B10: Line
A11: X Column | B11: Year
A12: Y Column | B12: Percent
A13: X Axis Title
A14: Y Axis Title | B14: Percent
A15: Start at Zero | B15: TRUE
A18: Source Specifications
A19: Table ID
A20: URL | B20: https://health.data.ny.gov/Health/Behavioral-Risk-Factor-Surveillance-System-BRFSS-H/jsy7-eb4n/data
A21: Data Year
A22: Estimate Type
A23: Citation Month | B23: May
A24: Citation Year | B24: 2025
A25: Custom Text
A27: Note Specfications
A28: *: Percentage is unreliable due to large standard error. Note: The percentage is age-adjusted. An adult is a person aged 18 years or older. The Behavioral Risk Factor Surveillance System asks respondents “How often do you eat fruits, excluding juice?" and "How often do you eat vegetables or salad (excluding juices and potatoes)?”

Sheet Consume Sugary Bev
A1: Name | B1: Percentage of Adults Who Consume One or More Sugary Beverages Daily, 2016, 2018, and 2021
A2: Table/Figure/Both | B2: Both
A3: Object ID | B3: =IF($B$1="","",_xlfn.XLOOKUP($B$1,Master!$F$2:$F$308,Master!$G$2:$G$308,"")) -> tbl-BRFSS-adult-sug-bev
A4: Figure ID | B4: =IF($B$1="","",_xlfn.XLOOKUP($B$1,Master!$F$2:$F$308,Master!$H$2:$H$308,"")) -> fig-BRFSS-sug-bev | F4: number | G4: percent1 | H4: percent1 | I4: percent1 | J4: percent1 | K4: percent1 | L4: percent1 | M4: percent1 | N4: percent1 | O4: percent1
A5: Table Rules | E5: Enter Data | F5: Year | G5: Dutchess | H5: Orange | I5: Putnam | J5: Rockland | K5: Sullivan | L5: Ulster | M5: Westchester | N5: NYS excl NYC | O5: NYS
A6: Multilevel Headers | B6: FALSE | F6: 2016 | G6: 21.9 | H6: 25.5 | I6: 22.9 | J6: 23.1 | K6: 27 | L6: 23.6 | M6: 18.5 | N6: 24.6 | O6: 24.2
F7: 2018 | G7: 23.5 | H7: 22.5 | I7: 25.6 | J7: 18.1 | K7: 31.5 | L7: 23.5 | M7: 20.3 | N7: 25.5 | O7: 24.7
F8: 2021 | G8: 24.9 | H8: 21.3 | I8: 17.8 | J8: 21.7 | K8: 19.9 | L8: 19.4 | M8: 11.4 | N8: 20.2 | O8: 19.6
A9: Figure Rules
A10: Figure Type | B10: Line
A11: X Column | B11: Year
A12: Y Column | B12: Percent
A13: X Axis Title
A14: Y Axis Title | B14: Percent
A15: Start at Zero | B15: TRUE
A18: Source Specifications
A19: Table ID
A20: URL | B20: https://health.data.ny.gov/Health/Behavioral-Risk-Factor-Surveillance-System-BRFSS-H/jsy7-eb4n/data
A21: Data Year
A22: Estimate Type
A23: Citation Month | B23: May
A24: Citation Year | B24: 2025
A25: Custom Text
A27: Note Specfications
A28: Note: The percentage is age-adjusted. An adult is a person aged 18 years or older. The Behavioral Risk Factor Surveillance System asks respondents "During the past 30 days, how often did you drink regular soda or pop that contains sugar? Do not include diet soda or diet pop." and "During the past 30 days, how often did you drink sugar-sweetened fruit drinks (such as Kool-aid™ and lemonade), sweet tea, and sports or energy drinks (such as Gatorade™ and Red Bull™)? Do not include 100% fruit juice, diet drinks, or artificially sweetened drinks."

Sheet Health Indicators

Sheet Top 5 Leading Cause Death
A1: Name | B1: Top Five Leading Causes of Death, by Count and Age-Adjusted Rate per 100,000 Population, 2022
A2: Table/Figure/Both | B2: Table
A3: Object ID | B3: =IF($B$1="","",_xlfn.XLOOKUP($B$1,Master!$F$2:$F$308,Master!$G$2:$G$308,"")) -> tbl-five-lead-death-aar
A4: Figure ID | B4: =IF($B$1="","",_xlfn.XLOOKUP($B$1,Master!$F$2:$F$308,Master!$H$2:$H$308,"")) -> fig-five-lead-death | F4: number | G4: percent1 | H4: percent1 | I4: percent1 | J4: percent1 | K4: percent1 | L4: percent1 | M4: percent1 | N4: percent1 | O4: percent1
A5: Table Rules | E5: Enter Data | F5: County | G5: All Deaths | H5: #1 Cause of Death | I5: #2 Cause of Death | J5: #3 Cause of Death | K5: #4 Cause of Death | L5: #5 Cause of Death
A6: Multilevel Headers | B6: TRUE | F6: Dutchess | H6: Heart Disease | I6: Cancer | J6: Unintentional Injury | K6: COVID-19 | L6: CLRD
F7: Count: | G7: 2912 | H7: 771 | I7: 554 | J7: 204 | K7: 183 | L7: 109
F8: Rate: | G8: 718.7 | H8: 183.8 | I8: 131.6 | J8: 65 | K8: 42.8 | L8: 26.3
A9: Figure Rules | F9: Orange | H9: Heart Disease | I9: Cancer | J9: Unintentional Injury | K9: COVID-19 | L9: CLRD
A10: Figure Type | F10: Count: | G10: 3220 | H10: 650 | I10: 609 | J10: 251 | K10: 230 | L10: 124
A11: X Column | F11: Rate: | G11: 744.8 | H11: 150 | I11: 132.5 | J11: 61.7 | K11: 53.2 | L11: 29.3
A12: Y Column | F12: Putnam | H12: Heart Disease | I12: Cancer | J12: Unintentional Injury | K12: COVID-19 | L12: Cerebrovascular Disease
A13: X Axis Title | F13: Count: | G13: 846 | H13: 194 | I13: 169 | J13: 49 | K13: 37 | L13: 31
A14: Y Axis Title | F14: Rate: | G14: 637.1 | H14: 144.7 | I14: 118.6 | J14: 46.2 | K14: 28.9 | L14: 22.7
A15: Start at Zero | F15: Rockland | H15: Heart Disease | I15: Cancer | J15: COVID-19 | K15: Unintentional Injury | L15: Cerebrovascular Disease
F16: Count: | G16: 2347 | H16: 542 | I16: 456 | J16: 194 | K16: 123 | L16: 83
F17: Rate: | G17: 562.4 | H17: 125.1 | I17: 110.9 | J17: 45.5 | K17: 35.1 | L17: 19.3
A18: Source Specifications | F18: Sullivan | H18: Heart Disease | I18: Cancer | J18: Unintentional Injury | K18: COVID-19 | L18: CLRD
A19: Table ID | F19: Count: | G19: 888 | H19: 195 | I19: 165 | J19: 75 | K19: 62 | L19: 44
A20: URL | F20: Rate: | G20: 908.5 | H20: 199.1 | I20: 153.2 | J20: 94.6 | K20: 60 | L20: 41.5
A21: Data Year | F21: Ulster | H21: Heart Disease | I21: Cancer | J21: Unintentional Injury | K21: COVID-19 | L21: CLRD
A22: Estimate Type | F22: Count: | G22: 1977 | H22: 512 | I22: 396 | J22: 128 | K22: 93 | L22: 92
A23: Citation Month | F23: Rate: | G23: 745 | H23: 187.6 | I23: 140.5 | J23: 61.6 | K23: 34 | L23: 32
A24: Citation Year | F24: Westchester | H24: Heart Disease | I24: Cancer | J24: COVID-19 | K24: Cerebrovascular Disease | L24: Unintentional Injury
A25: Custom Text | F25: Count: | G25: 7666 | H25: 1915 | I25: 1402 | J25: 511 | K25: 340 | L25: 339
F26: Rate: | G26: 548 | H26: 130.3 | I26: 100.2 | J26: 35.5 | K26: 23.6 | L26: 30.4
A27: Note Specfications | F27: NYS excl NYC | H27: Heart Disease | I27: Cancer | J27: COVID-19 | K27: Unintentional Injury | L27: CLRD
F28: Count: | G28: 113504 | H28: 26138 | I28: 21715 | J28: 6607 | K28: 6596 | L28: 4595
F29: Rate: | G29: 744.2 | H29: 165.9 | I29: 137 | J29: 42.3 | K29: 54.1 | L29: 28.7
F30: NYS | H30: Heart Disease | I30: Cancer | J30: COVID-19 | K30: Unintentional Injury | L30: Cerebrovascular Disease
F31: Count: | G31: 173958 | H31: 43029 | I31: 32517 | J31: 11167 | K31: 10811 | L31: 6556
F32: Rate: | G32: 679.5 | H32: 163.1 | I32: 123.4 | J32: 42.6 | K32: 50 | L32: 25.1

Sheet Premature Deaths
A1: Name | B1: Percentage of Deaths That are Premature, 2019–2022
A2: Table/Figure/Both | B2: Both
A3: Object ID | B3: =IF($B$1="","",_xlfn.XLOOKUP($B$1,Master!$F$2:$F$308,Master!$G$2:$G$308,"")) -> tbl-premature-death-percent
A4: Figure ID | B4: =IF($B$1="","",_xlfn.XLOOKUP($B$1,Master!$F$2:$F$308,Master!$H$2:$H$308,"")) -> fig-premature-death-percent | F4: number | G4: percent1 | H4: percent1 | I4: percent1 | J4: percent1 | K4: percent1 | L4: percent1 | M4: percent1 | N4: percent1 | O4: percent1 | P4: percent1
A5: Table Rules | E5: Enter Data | F5: Year | G5: Dutchess | H5: Orange | I5: Putnam | J5: Rockland | K5: Sullivan | L5: Ulster | M5: Westchester | N5: Mid-Hudson | O5: NYS excl NYC | P5: NYS
A6: Multilevel Headers | B6: FALSE | F6: 2019 | G6: 21.1 | H6: 25.3 | I6: 18.9 | J6: 19.4 | K6: 26.8 | L6: 20.5 | M6: 18 | N6: 20.4 | O6: 21 | P6: 22.7
F7: 2020 | G7: 23.5 | H7: 24.5 | I7: 19.7 | J7: 21.4 | K7: 27.3 | L7: 23 | M7: 19.2 | N7: 21.5 | O7: 21.5 | P7: 23.3
F8: 2021 | G8: 22.3 | H8: 27.3 | I8: 17.4 | J8: 21.1 | K8: 29.7 | L8: 22.8 | M8: 19.7 | N8: 22.1 | O8: 22.7 | P8: 24.4
A9: Figure Rules | F9: 2022 | G9: 22.7 | H9: 25.1 | I9: 20.6 | J9: 18.5 | K9: 28.8 | L9: 21.9 | M9: 18.4 | N9: 21 | O9: 22 | P9: 23.6
A10: Figure Type | B10: Line
A11: X Column | B11: Year
A12: Y Column | B12: Percent
A13: X Axis Title | B13: Year
A14: Y Axis Title | B14: Percent
A15: Start at Zero | B15: FALSE
A18: Source Specifications
A19: Table ID
A20: URL
A21: Data Year
A22: Estimate Type
A23: Citation Month
A24: Citation Year
A25: Custom Text
A27: Note Specfications
A29: Note: Y-axis does not begin at zero in order to clearly display trend lines. The American Community Survey asks respondents if they have worked in the past week. If the answer is no, they are asked why they are not working. For those who are not working, they are asked whether they plan to return to work, and when they last worked. Labor Force refers to the total number of people who are either employed or unemployed and actively seeking work, plus members of the US Armed Forces.

Sheet Premature Deaths BH-WH
A1: Name | B1: Premature Deaths, Percentage Difference Between Black Non-Hispanics and White Non-Hispanics, 2019–2022
A2: Table/Figure/Both | B2: Both
A3: Object ID | B3: =IF($B$1="","",_xlfn.XLOOKUP($B$1,Master!$F$2:$F$308,Master!$G$2:$G$308,"")) -> tbl-premature-death-percent-diff-BNHvsWNH
A4: Figure ID | B4: =IF($B$1="","",_xlfn.XLOOKUP($B$1,Master!$F$2:$F$308,Master!$H$2:$H$308,"")) -> fig-premature-death-percent-diff-BNHvsWNH | F4: number | G4: percent1 | H4: percent1 | I4: percent1 | J4: percent1 | K4: percent1 | L4: percent1 | M4: percent1 | N4: percent1 | O4: percent1 | P4: percent1
A5: Table Rules | E5: Enter Data | F5: Year | G5: Dutchess | H5: Orange | I5: Putnam | J5: Rockland | K5: Sullivan | L5: Ulster | M5: Westchester | N5: Mid-Hudson | O5: NYS excl NYC | P5: NYS
A6: Multilevel Headers | B6: FALSE | F6: 2019 | G6: 13.7 | H6: 19.3 | I6: 32.4* | J6: 10.1 | K6: 4.2 | L6: 19.8 | M6: 19.3 | N6: 15.9 | O6: 20.2 | P6: 17.7
F7: 2020 | G7: 19.8 | H7: 23.3 | I7: 22.3* | J7: 9.3 | K7: 10.1 | L7: 25.7 | M7: 18.9 | N7: 16.8 | O7: 19.7 | P7: 16.5
F8: 2021 | G8: 21.9 | H8: 15.8 | I8: 1.9* | J8: 16.6 | K8: 15.4 | L8: 23.4 | M8: 21 | N8: 18.5 | O8: 22.2 | P8: 19.5
A9: Figure Rules | F9: 2022 | G9: 18.5 | H9: 20.6 | I9: 16.7* | J9: 16.2 | K9: 8 | L9: 25.3 | M9: 20.5 | N9: 18.2 | O9: 21.7 | P9: 19.4
A10: Figure Type | B10: Line
A11: X Column | B11: Year
A12: Y Column | B12: Percent
A13: X Axis Title | B13: Year
A14: Y Axis Title | B14: Percent
A15: Start at Zero | B15: TRUE
A18: Source Specifications
A19: Table ID
A20: URL
A21: Data Year
A22: Estimate Type
A23: Citation Month
A24: Citation Year
A25: Custom Text | B25: Source: NYS Prevention Agenda Tracking Dashboard, March 2025 sourced from Vital Statistics of NYS https://apps.health.ny.gov/public/tabvis/PHIG_Public/pa/
A27: Note Specfications
A29: *: The rate is unstable. Note: Premature death includes deaths occurring before the age of 65. The percentage of premature deaths is calculated for both Black non-Hispanics and White non-Hispanics. Then, the difference is the Black non-Hispanic rate minus the White non-Hispanic rate.

Sheet Premature Deaths His-WNH
A1: Name | B1: Premature Deaths, Percentage Difference Between Hispanics and White Non-Hispanics, 2019–2022
A2: Table/Figure/Both | B2: Both
A3: Object ID | B3: =IF($B$1="","",_xlfn.XLOOKUP($B$1,Master!$F$2:$F$308,Master!$G$2:$G$308,"")) -> tbl-premature-death-percent-diff-HvsWNH
A4: Figure ID | B4: =IF($B$1="","",_xlfn.XLOOKUP($B$1,Master!$F$2:$F$308,Master!$H$2:$H$308,"")) -> fig-premature-death-percent-diff-HvsWNH | F4: number | G4: percent1 | H4: percent1 | I4: percent1 | J4: percent1 | K4: percent1 | L4: percent1 | M4: percent1 | N4: percent1 | O4: percent1 | P4: percent1
A5: Table Rules | E5: Enter Data | F5: Year | G5: Dutchess | H5: Orange | I5: Putnam | J5: Rockland | K5: Sullivan | L5: Ulster | M5: Westchester | N5: Mid-Hudson | O5: NYS excl NYC | P5: NYS
A6: Multilevel Headers | B6: FALSE | F6: 2019 | G6: 18 | H6: 16.6 | I6: 9.7 | J6: 22.8 | K6: 14 | L6: 8.9 | M6: 23.4 | N6: 19.3 | O6: 21.1 | P6: 16.4
F7: 2020 | G7: 22 | H7: 15.5 | I7: 19.1 | J7: 28.4 | K7: 14.9 | L7: 14.7 | M7: 25.5 | N7: 21.9 | O7: 23.9 | P7: 17.2
F8: 2021 | G8: 18.9 | H8: 16.2 | I8: 11.2 | J8: 24.4 | K8: 19.6 | L8: 18.3 | M8: 25.7 | N8: 21.4 | O8: 23.7 | P8: 18
A9: Figure Rules | F9: 2022 | G9: 23.6 | H9: 17.2 | I9: 28.9 | J9: 26.3 | K9: 29.6 | L9: 23.7 | M9: 25.8 | N9: 23.1 | O9: 24.6 | P9: 17.9
A10: Figure Type | B10: Line
A11: X Column | B11: Year
A12: Y Column | B12: Percent
A13: X Axis Title | B13: Year
A14: Y Axis Title | B14: Percent
A15: Start at Zero | B15: TRUE
A18: Source Specifications
A19: Table ID
A20: URL
A21: Data Year
A22: Estimate Type
A23: Citation Month
A24: Citation Year
A25: Custom Text | B25: Source: NYS Prevention Agenda Tracking Dashboard, March 2025 sourced from Vital Statistics of NYS https://apps.health.ny.gov/public/tabvis/PHIG_Public/pa/
A27: Note Specfications
A29: Note: Premature death includes deaths occurring before the age of 65. The percentage of premature deaths is calculated for Hispanics and White non-Hispanics. Then, the difference is the Hispanic rate minus the White non-Hispanic rate.

Sheet CLRD Hosp AAR
A1: Name | B1: Chronic Lower Respiratory Disease Hospitalization, Age-Adjusted Rate per 10,000 Population, 2020–2022
A2: Table/Figure/Both | B2: Both
A3: Object ID | B3: =IF($B$1="","",_xlfn.XLOOKUP($B$1,Master!$F$2:$F$308,Master!$G$2:$G$308,"")) -> tbl-clrd-hospital-aar
A4: Figure ID | B4: =IF($B$1="","",_xlfn.XLOOKUP($B$1,Master!$F$2:$F$308,Master!$H$2:$H$308,"")) -> fig-clrd-hospital-aar | F4: number | G4: percent1 | H4: percent1 | I4: percent1 | J4: percent1 | K4: percent1 | L4: percent1 | M4: percent1 | N4: percent1 | O4: percent1 | P4: percent1
A5: Table Rules | E5: Enter Data | F5: Year | G5: Dutchess | H5: Orange | I5: Putnam | J5: Rockland | K5: Sullivan | L5: Ulster | M5: Westchester | N5: Mid-Hudson | O5: NYS excl NYC | P5: NYS
A6: Multilevel Headers | B6: FALSE | F6: 2020–2022 | G6: 12 | H6: 13.8 | I6: 8.1 | J6: 8.9 | K6: 11.8 | L6: 11.6 | M6: 11.1 | N6: 11.2 | O6: 12 | P6: 14.3
A9: Figure Rules
A10: Figure Type | B10: Bar
A11: X Column | B11: Year
A12: Y Column | B12: Rate per 10,000
A13: X Axis Title | B13: Year
A14: Y Axis Title | B14: Rate per 10,000
A15: Start at Zero | B15: TRUE
A18: Source Specifications
A19: Table ID
A20: URL
A21: Data Year
A22: Estimate Type
A23: Citation Month
A24: Citation Year
A25: Custom Text | B25: Source: NYS Community Health Indicator Reports Dashboard, June 2025 sourced from NY Statewide Planning and Research Cooperative System https://apps.health.ny.gov/public/tabvis/PHIG_Public/chirs/reports/#county
A27: Note Specfications
A29: Note: The 2018 population estimates are also used to calculate 2019 and 2020 rates. The ICD-10 codes for CLRD are: J40-J47

Sheet CLRD Hosp AAR-RE
A1: Name | B1: Chronic Lower Respiratory Disease Hospitalization, Age-Adjusted Rate per 10,000 by Race and Ethnicity, 2020–2022
A2: Table/Figure/Both | B2: Both
A3: Object ID | B3: =IF($B$1="","",_xlfn.XLOOKUP($B$1,Master!$F$2:$F$308,Master!$G$2:$G$308,"")) -> tbl-clrd-hospital-rande-aar
A4: Figure ID | B4: =IF($B$1="","",_xlfn.XLOOKUP($B$1,Master!$F$2:$F$308,Master!$H$2:$H$308,"")) -> fig-clrd-hospital-rande-aar | F4: number | G4: percent1 | H4: percent1 | I4: percent1 | J4: percent1 | K4: percent1 | L4: percent1 | M4: percent1 | N4: percent1 | O4: percent1
A5: Table Rules | E5: Enter Data | F5: Race and Ethnicity | G5: Dutchess | H5: Orange | I5: Putnam | J5: Rockland | K5: Sullivan | L5: Ulster | M5: Westchester | N5: NYS excl NYC | O5: NYS
A6: Multilevel Headers | B6: FALSE | F6: Non-Hispanic White | G6: 10.4 | H6: 11.7 | I6: 7.4 | J6: 7.4 | K6: 10.8 | L6: 11 | M6: 6.1 | N6: 9.8 | O6: 9.1
F7: Non-Hispanic Black | G7: 9 | H7: 22.5 | I7: 10.8 | J7: 13 | K7: 25.7 | L7: 17.3 | M7: 19 | N7: 24 | O7: 24.5
F8: Non-Hispanic Asian/Pacific Islander | G8: s | H8: 2.9 | I8: s | J8: 3.4 | K8: s | L8: s | M8: 2.6 | N8: 4.1 | O8: 4.4
A9: Figure Rules | F9: Hispanic | G9: 6.2 | H9: 10.8 | I9: 7.2 | J9: 8.4 | K9: 6.8 | L9: 10.6 | M9: 8.3 | N9: 9.9 | O9: 16.6
A10: Figure Type | B10: Clustered Bar
A11: X Column | B11: Race and Ethnicity
A12: Y Column | B12: Rate per 10,000
A13: X Axis Title | B13: Race and Ethnicity
A14: Y Axis Title | B14: Rate per 10,000
A15: Start at Zero | B15: TRUE
A18: Source Specifications
A19: Table ID
A20: URL
A21: Data Year
A22: Estimate Type
A23: Citation Month
A24: Citation Year
A25: Custom Text | B25: Source: NYS County Health Indicators by Race and Ethnicity Dashboard, June 2025 sourced from NY Statewide Planning and Research Cooperative System https://www.health.ny.gov/statistics/community/minority/county/orange.htm
A27: Note Specfications
A29: s: Data are suppressed due to not meeting confidentiality criteria. Note: The ICD-10-CM codes for CLRD are: J40-J47.

Sheet Adults Asthma
A1: Name | B1: Percentage of Adults with Current Asthma, 2016, 2018, and 2021
A2: Table/Figure/Both | B2: Both
A3: Object ID | B3: =IF($B$1="","",_xlfn.XLOOKUP($B$1,Master!$F$2:$F$308,Master!$G$2:$G$308,"")) -> tbl-brfss-adult-asthma
A4: Figure ID | B4: =IF($B$1="","",_xlfn.XLOOKUP($B$1,Master!$F$2:$F$308,Master!$H$2:$H$308,"")) -> fig-brfss-adult-asthma | F4: number | G4: percent1 | H4: percent1 | I4: percent1 | J4: percent1 | K4: percent1 | L4: percent1 | M4: percent1 | N4: percent1 | O4: percent1 | P4: percent1
A5: Table Rules | E5: Enter Data | F5: Year | G5: Dutchess | H5: Orange | I5: Putnam | J5: Rockland | K5: Sullivan | L5: Ulster | M5: Westchester | N5: Mid-Hudson | O5: NYS excl NYC | P5: NYS
A6: Multilevel Headers | B6: FALSE | F6: 2016 | G6: 10.6 | H6: 9 | I6: 13.2 | J6: 4.6 | K6: 12.3 | L6: 5.7 | M6: 9.6 | N6: 8.8 | O6: 10.4 | P6: 9.6
F7: 2018 | G7: 9.9 | H7: 8.9 | I7: 8.9 | J7: 7.3 | K7: 12.7 | L7: 12.3 | M7: 11.5 | N7: 9.7 | O7: 10.8 | P7: 10.1
F8: 2021 | G8: 11.3 | H8: 9.6 | I8: 10.1 | J8: 7.4 | K8: 12.3 | L8: 11.8 | M8: 7.9 | N8: 8.9 | O8: 10.8 | P8: 10.1
A9: Figure Rules
A10: Figure Type | B10: Line
A11: X Column | B11: Year
A12: Y Column | B12: Percent
A13: X Axis Title | B13: Year
A14: Y Axis Title | B14: Percent
A15: Start at Zero | B15: TRUE
A18: Source Specifications
A19: Table ID
A20: URL
A21: Data Year
A22: Estimate Type
A23: Citation Month
A24: Citation Year
A25: Custom Text | B25: Source: NYS County Health Indicators by Race and Ethnicity Dashboard, June 2025 sourced from Vital Statistics of NYS https://www.health.ny.gov/statistics/community/minority/county/orange.htm
A27: Note Specfications
A29: Note: The percentage is age-adjusted. An adult is a person aged 18 years or older. The Behavioral Risk Factor Surveillance System asks respondents, “Has a doctor, nurse, or other health professional ever told you had asthma?” and “Do you still have asthma?”

Sheet Asthma Hosp
A1: Name | B1: Asthma Hospitalization, Age-Adjusted Rate per 10,000 Population, 2020–2022
A2: Table/Figure/Both | B2: Both
A3: Object ID | B3: =IF($B$1="","",_xlfn.XLOOKUP($B$1,Master!$F$2:$F$308,Master!$G$2:$G$308,"")) -> tbl-asthma-hopsital-aar
A4: Figure ID | B4: =IF($B$1="","",_xlfn.XLOOKUP($B$1,Master!$F$2:$F$308,Master!$H$2:$H$308,"")) -> fig-asthma-hopsital-aar | F4: number | G4: percent1 | H4: percent1 | I4: percent1 | J4: percent1 | K4: percent1 | L4: percent1 | M4: percent1 | N4: percent1 | O4: percent1 | P4: percent1
A5: Table Rules | E5: Enter Data | F5: Period | G5: Dutchess | H5: Orange | I5: Putnam | J5: Rockland | K5: Sullivan | L5: Ulster | M5: Westchester | N5: Mid-Hudson | O5: NYS excl NYC | P5: NYS
A6: Multilevel Headers | B6: FALSE | F6: 2020–2022 | G6: 4.7 | H6: 5.1 | I6: 3.5 | J6: 3.2 | K6: 4.3 | L6: 3.8 | M6: 5.9 | N6: 4.9 | O6: 4.2 | P6: 6.6
A9: Figure Rules
A10: Figure Type | B10: Bar
A11: X Column | B11: Year
A12: Y Column
A13: X Axis Title
A14: Y Axis Title
A15: Start at Zero | B15: TRUE
A18: Source Specifications
A19: Table ID
A20: URL
A21: Data Year
A22: Estimate Type
A23: Citation Month
A24: Citation Year
A25: Custom Text | B25: Source: NYS Community Health Indicator Reports Dashboard, June 2025 sourced from NY Statewide Planning and Research Cooperative System https://webbi1.health.ny.gov/SASStoredProcess/guest?_program=%2FEBI%2FPHIG%2Fapps%2Fchir_dashboard%2Fchir_dashboard& p=ch&cos=33
A27: Note Specfications
A29: Note: The 2018 population estimates are also used to calculate 2019 and 2020 rates. The ICD-10 code for asthma is: J45.

Sheet Asthma Hosp RE
A1: Name | B1: Asthma Hospitalization, Age-Adjusted Rate per 10,000 Population by Race and Ethnicity, 2020–2022
A2: Table/Figure/Both | B2: Both
A3: Object ID | B3: =IF($B$1="","",_xlfn.XLOOKUP($B$1,Master!$F$2:$F$308,Master!$G$2:$G$308,"")) -> tbl-asthma-hopsital-rande-aar
A4: Figure ID | B4: =IF($B$1="","",_xlfn.XLOOKUP($B$1,Master!$F$2:$F$308,Master!$H$2:$H$308,"")) -> fig-asthma-hopsital-rande-aar | F4: number | G4: percent1 | H4: percent1 | I4: percent1 | J4: percent1 | K4: percent1 | L4: percent1 | M4: percent1 | N4: percent1 | O4: percent1 | P4: percent1
A5: Table Rules | E5: Enter Data | F5: Race and Ethnicity | G5: Dutchess | H5: Orange | I5: Putnam | J5: Rockland | K5: Sullivan | L5: Ulster | M5: Westchester | N5: NYS excl NYC | O5: NYS
A6: Multilevel Headers | B6: FALSE | F6: Non-Hispanic White | G6: 3 | H6: 3.4 | I6: 2.9 | J6: 2.3 | K6: 3 | L6: 3.4 | M6: 2.6 | N6: 2.4 | O6: 2.3
F7: Non-Hispanic Black | G7: 5.4 | H7: 10.8 | I7: 10.8 | J7: 6.9 | K7: 17.1 | L7: 7.3 | M7: 11.4 | N7: 11.9 | O7: 13.8
F8: Non-Hispanic Asian/Pacific Islander | G8: s | H8: 1.8* | I8: s | J8: 1.3 | K8: 0.0* | L8: s | M8: 1.8 | N8: 2.4 | O8: 2.4
A9: Figure Rules | F9: Hispanic | G9: 3.9 | H9: 5.1 | I9: 3.5 | J9: 3.3 | K9: 3 | L9: 3.2 | M9: 4.4 | N9: 5.4 | O9: 9.9
A10: Figure Type | B10: Clustered Bar
A11: X Column | B11: Race and Ethnicity
A12: Y Column | B12: Rate per 10,000
A13: X Axis Title | B13: Race and Ethnicity
A14: Y Axis Title | B14: Rate per 10,000
A15: Start at Zero | B15: TRUE
A18: Source Specifications
A19: Table ID
A20: URL
A21: Data Year
A22: Estimate Type
A23: Citation Month
A24: Citation Year
A25: Custom Text | B25: Source: NYS County Health Indicators by Race and Ethnicity Dashboard, June 2025 sourced from NY Statewide Planning and Research Cooperative System https://www.health.ny.gov/statistics/community/minority/county/orange.htm
A27: Note Specfications
A29: *: The rate is unstable. s: Data are suppressed due to not meeting confidentiality criteria. Note: The ICD-10-CM code used for asthma is: J45.

Sheet Asthma ED 0-17
A1: Name | B1: Asthma Emergency Department Visits, Rate per 10,000 Population 0–17 Years Old, 2017–2023
A2: Table/Figure/Both | B2: Both
A3: Object ID | B3: =IF($B$1="","",_xlfn.XLOOKUP($B$1,Master!$F$2:$F$308,Master!$G$2:$G$308,"")) -> tbl-0to17-asthma-ed-rate
A4: Figure ID | B4: =IF($B$1="","",_xlfn.XLOOKUP($B$1,Master!$F$2:$F$308,Master!$H$2:$H$308,"")) -> fig-0to17-asthma-ed-rate | F4: number | G4: percent1 | H4: percent1 | I4: percent1 | J4: percent1 | K4: percent1 | L4: percent1 | M4: percent1 | N4: percent1 | O4: percent1 | P4: percent1
A5: Table Rules | E5: Enter Data | F5: Year | G5: Dutchess | H5: Orange | I5: Putnam | J5: Rockland | K5: Sullivan | L5: Ulster | M5: Westchester | N5: Mid-Hudson | O5: NYS | P5: Objective
A6: Multilevel Headers | B6: FALSE | F6: 2017 | G6: 56.1 | H6: 55.4 | I6: 47.3 | J6: 40.7 | K6: 83.9 | L6: 76 | M6: 89.9 | N6: 68.9 | O6: 124.1 | P6: 131.1
F7: 2018 | G7: 70.8 | H7: 64.4 | I7: 54.1 | J7: 42.8 | K7: 87.8 | L7: 72.7 | M7: 87.1 | N7: 71.2 | O7: 124.1 | P7: 131.1
F8: 2019 | G8: 62.8 | H8: 64 | I8: 34.1 | J8: 33.9 | K8: 89.1 | L8: 60.7 | M8: 82.1 | N8: 65.1 | O8: 107.5 | P8: 131.1
A9: Figure Rules | F9: 2020 | G9: 27.7 | H9: 25 | I9: 11.2 | J9: 15.3 | K9: 30.1 | L9: 27.6 | M9: 26.8 | N9: 24.1 | O9: 39 | P9: 131.1
A10: Figure Type | B10: Line | F10: 2021 | G10: 41 | H10: 40.8 | I10: 21.4 | J10: 24.5 | K10: 40.5 | L10: 54.3 | M10: 50 | N10: 41.6 | O10: 59.9 | P10: 131.1
A11: X Column | B11: Year | F11: 2022 | G11: 60.8 | H11: 63.5 | I11: 39.3 | J11: 32 | K11: 104.1 | L11: 55.6 | M11: 74.2 | N11: 61.5 | O11: 93.8 | P11: 131.1
A12: Y Column | F12: 2023 | G12: 61.9 | H12: 61.5 | I12: 39 | J12: 36.7 | K12: 102.2 | L12: 64.8 | M12: 73.8 | N12: † | O12: 94.8 | P12: 131.1
A13: X Axis Title | B13: Year
A14: Y Axis Title | B14: Rate per 10,000
A15: Start at Zero | B15: TRUE
A18: Source Specifications
A19: Table ID
A20: URL
A21: Data Year
A22: Estimate Type
A23: Citation Month
A24: Citation Year
A25: Custom Text | B25: Source: NYS Asthma Dashboard, June 2025 sourced from NY Statewide Planning and Research Cooperative System https://apps.health.ny.gov/public/tabvis/PHIG_Public/asthma/reports/#county
A27: Note Specfications
A29: † 2023 data not available for Mid-Hudson Note: The 2018 population estimates are used to calculate rates for 2019 and 2020. Population estimates for 2021 and later are from the US Census Bureau's most recently published estimates. Changes seen in 2020 and subsequent data years are possibly due to impacts of the COVID-19 pandemic. The ICD-10 code for asthma is: J45.

Sheet CVD Adults
A1: Name | B1: Percentage of Adults with Cardiovascular Disease, 2016, 2018, and 2021
A2: Table/Figure/Both | B2: Both
A3: Object ID | B3: =IF($B$1="","",_xlfn.XLOOKUP($B$1,Master!$F$2:$F$308,Master!$G$2:$G$308,"")) -> tbl-adult-cardiovasdz-percent
A4: Figure ID | B4: =IF($B$1="","",_xlfn.XLOOKUP($B$1,Master!$F$2:$F$308,Master!$H$2:$H$308,"")) -> fig-adult-cardiovasdz-percent | F4: number | G4: percent1 | H4: percent1 | I4: percent1 | J4: percent1 | K4: percent1 | L4: percent1 | M4: percent1 | N4: percent1 | O4: percent1
A5: Table Rules | E5: Enter Data | F5: Year | G5: Dutchess | H5: Orange | I5: Putnam | J5: Rockland | K5: Sullivan | L5: Ulster | M5: Westchester | N5: NYS excl NYC | O5: NYS
A6: Multilevel Headers | B6: FALSE | F6: 2016 | G6: 6.1 | H6: 6.4 | I6: 4.4 | J6: 6.2 | K6: 7.3 | L6: 7.3 | M6: 6.1 | N6: 7.2 | O6: 7
F7: 2018 | G7: 7 | H7: 7.8 | I7: 4.5 | J7: 8 | K7: 8.6 | L7: 4.5 | M7: 5.4 | N7: 7.4 | O7: 7
F8: 2021 | G8: 7.2 | H8: 6.6 | I8: 6.8 | J8: 5.7 | K8: 7.4 | L8: 6.7 | M8: 5.4 | N8: 6.7 | O8: 6.4
A9: Figure Rules
A10: Figure Type | B10: Stacked Bar
A11: X Column | B11: Year
A12: Y Column
A13: X Axis Title | B13: Year
A14: Y Axis Title | B14: Percent
A15: Start at Zero | B15: TRUE
A18: Source Specifications
A19: Table ID
A20: URL
A21: Data Year
A22: Estimate Type
A23: Citation Month
A24: Citation Year
A25: Custom Text | B25: Source: NYS Community Health Indicator Reports Dashboard, April 2025 sourced from NYSDOH Behavioral Risk Factor Surveillance System https://webbi1.health.ny.gov/SASStoredProcess/guest?_program=%2FEBI%2FPHIG%2Fapps%2Fchir_dashboard%2Fchir_dashboard& p=ch&cos=33
A27: Note Specfications
A29: Note: The percentage is age-adjusted. An adult is a person aged 18 years or older. The Behavioral Risk Factor Surveillance System asks respondents "Has a doctor, nurse, or other health professional ever told you that you had any of the following:” and “Ever told you that you had a heart attack also called a myocardial infarction?” and “Ever told you that you had angina or coronary heart disease?” Based on responses to these questions, a person has Cardiovascular Disease if they responded yes to either of these questions.

Sheet CVD Hosp AAR
A1: Name | B1: Percentage of Adults with Cardiovascular Disease, 2016, 2018, and 2021
A2: Table/Figure/Both | B2: Both
A3: Object ID | B3: =IF($B$1="","",_xlfn.XLOOKUP($B$1,Master!$F$2:$F$308,Master!$G$2:$G$308,"")) -> tbl-adult-cardiovasdz-percent
A4: Figure ID | B4: =IF($B$1="","",_xlfn.XLOOKUP($B$1,Master!$F$2:$F$308,Master!$H$2:$H$308,"")) -> fig-adult-cardiovasdz-percent | F4: number | G4: percent1 | H4: percent1 | I4: percent1 | J4: percent1 | K4: percent1 | L4: percent1 | M4: percent1 | N4: percent1 | O4: percent1
A5: Table Rules | E5: Enter Data | F5: Year | G5: Dutchess | H5: Orange | I5: Putnam | J5: Rockland | K5: Sullivan | L5: Ulster | M5: Westchester | N5: Mid-Hudson | O5: NYS
A6: Multilevel Headers | B6: FALSE | F6: 2019–2021 | G6: 102.3 | H6: 116.1 | I6: 76.9 | J6: 81.1 | K6: 129.9 | L6: 109.6 | M6: 90.9 | N6: 99.3 | O6: 111.2
A9: Figure Rules
A10: Figure Type | B10: Bar
A11: X Column | B11: Year
A12: Y Column
A13: X Axis Title | B13: Year
A14: Y Axis Title | B14: Rate per 10,000
A15: Start at Zero | B15: TRUE
A18: Source Specifications
A19: Table ID
A20: URL
A21: Data Year
A22: Estimate Type
A23: Citation Month
A24: Citation Year
A25: Custom Text | B25: Source: NYS Community Health Indicator Reports Dashboard, March 2025 sourced from NY Statewide Planning and Research Cooperative System https://webbi1.health.ny.gov/SASStoredProcess/guest?_program=%2FEBI%2FPHIG%2Fapps%2Fchir_dashboard%2Fchir_dashboard& p=ch&cos=33
A27: Note Specfications
A29: Note: The ICD-10 codes used for cardiovascular disease are: I00-I99.

Sheet CVD Mort AAR
A1: Name | B1: Cardiovascular Disease Mortality, Age-Adjusted Rate Per 100,000 Population, 2018–2021
A2: Table/Figure/Both | B2: Both
A3: Object ID | B3: =IF($B$1="","",_xlfn.XLOOKUP($B$1,Master!$F$2:$F$308,Master!$G$2:$G$308,"")) -> tbl-cardiovasdz-mortal-aar
A4: Figure ID | B4: =IF($B$1="","",_xlfn.XLOOKUP($B$1,Master!$F$2:$F$308,Master!$H$2:$H$308,"")) -> fig-cardiovasdz-mortal-aar | F4: number | G4: percent1 | H4: percent1 | I4: percent1 | J4: percent1 | K4: percent1 | L4: percent1 | M4: percent1 | N4: percent1 | O4: percent1
A5: Table Rules | E5: Enter Data | G5: Three Year Average | N5: Single Year
A6: Multilevel Headers | B6: TRUE | F6: Year | G6: Dutchess | H6: Orange | I6: Putnam | J6: Rockland | K6: Sullivan | L6: Ulster | M6: Westchester | N6: NYS excl NYC | O6: NYS
F7: 2018 | G7: 202.5 | H7: 197.7 | I7: 188.1 | J7: 174.5 | K7: 206 | L7: 207 | M7: 175.9 | N7: 210.3 | O7: 211.1
F8: 2019 | G8: 205.8 | H8: 201.8 | I8: 194.8 | J8: 180.6 | K8: 215.8 | L8: 208.5 | M8: 181.2 | N8: 205.5 | O8: 208.6
A9: Figure Rules | F9: 2020 | G9: 213.6 | H9: 199.5 | I9: 184.2 | J9: 180.7 | K9: 226.6 | L9: 218.6 | M9: 178 | N9: 214.2 | O9: 230.8
A10: Figure Type | B10: Line | F10: 2021 | G10: 220.2 | H10: 198.4 | I10: 177.9 | J10: 176 | K10: 235.5 | L10: 224.5 | M10: 177.2 | N10: 211.1 | O10: 206.2
A11: X Column | B11: Year
A12: Y Column
A13: X Axis Title | B13: Year
A14: Y Axis Title | B14: Rate per 10,000
A15: Start at Zero | B15: TRUE
A18: Source Specifications
A19: Table ID
A20: URL
A21: Data Year
A22: Estimate Type
A23: Citation Month
A24: Citation Year
A25: Custom Text | B25: Source: NYS Community Health Indicator Reports Dashboard, March 2025 sourced from Vital Statistics of NYS https://webbi1.health.ny.gov/SASStoredProcess/guest?_program=%2FEBI%2FPHIG%2Fapps%2Fchir_dashboard%2Fchir_dashboard& p=ch&cos=33
A27: Note Specfications
A29: Note: This indicator includes deaths with cardiovascular disease as the primary cause of death. The ICD-10 codes for cardiovascular disease are: I00-I99.

Sheet Asthma Gastro OM Pneumonia
A1: Name | B1: Asthma, Gastroenteritis, Otitis Media, and Pneumonia Hospitalizations, Rate per 10,000 Population 0–4 Years Old, 2020–2022
A2: Table/Figure/Both | B2: Both
A3: Object ID | B3: =IF($B$1="","",_xlfn.XLOOKUP($B$1,Master!$F$2:$F$308,Master!$G$2:$G$308,"")) -> tbl-0to4-hosp-asthma-gastor-om-pnu-rate
A4: Figure ID | B4: =IF($B$1="","",_xlfn.XLOOKUP($B$1,Master!$F$2:$F$308,Master!$H$2:$H$308,"")) -> fig-0to4-hosp-asthma-gastor-om-pnu-rate | G4: number | H4: number | I4: number | J4: number
A5: Table Rules | E5: Enter Data | G5: Asthma | H5: Gastroenteritis | I5: Otitis Media | J5: Pneumonia
A6: Multilevel Headers | B6: FALSE | F6: NYS | G6: 24.9 | H6: 7.7 | I6: 1 | J6: 13.4
F7: NYS excl NYC | G7: 17.2 | H7: 5.3 | I7: 0.8 | J7: 11.5
F8: Mid-Hudson | G8: 18.8 | H8: 6.8 | I8: 1 | J8: 15.2
A9: Figure Rules
A10: Figure Type | B10: Clustered Bar
A11: X Column | B11: County
A12: Y Column | B12: Rate
A13: X Axis Title
A14: Y Axis Title | B14: Rate per 10,000
A15: Start at Zero | B15: TRUE
A18: Source Specifications
A19: Table ID | B19: NYS Community Health Indicator Reports Dashboard
A20: URL | B20: https://apps.health.ny.gov/public/tabvis/PHIG_Public/chirs/reports/#county
A21: Data Year | B21: 2020-2022
A22: Estimate Type
A23: Citation Month | B23: April
A24: Citation Year | B24: 2025
A25: Custom Text | B25: Source: NYS Community Health Indicator Reports Dashboard, April 2025 sourced from NY Statewide Planning and Research Cooperative System https://apps.health.ny.gov/public/tabvis/PHIG_Public/chirs/reports/#county
A27: Note Specfications
A29: The ICD-10 codes for otitis media are: H65.0, H65.1, H65.2, H65.3, H66.0, H66.1, and H66.2.

Sheet Unintent Injury Mortality
A1: Name | B1: Unintentional Injury Mortality, Age-Adjusted Rate per 100,000 Population, 2018–2021
A2: Table/Figure/Both | B2: Both
A3: Object ID | B3: =IF($B$1="","",_xlfn.XLOOKUP($B$1,Master!$F$2:$F$308,Master!$G$2:$G$308,"")) -> tbl-unint-injury-mortal-aar
A4: Figure ID | B4: =IF($B$1="","",_xlfn.XLOOKUP($B$1,Master!$F$2:$F$308,Master!$H$2:$H$308,"")) -> fig-unint-injury-mortal-aar | F4: number | G4: number | H4: number | I4: number | J4: number | K4: number | L4: number | M4: number | N4: number | O4: number
A5: Table Rules | E5: Enter Data | G5: Three Year Average | N5: Single Year
A6: Multilevel Headers | B6: TRUE | F6: Year | G6: Dutchess | H6: Orange | I6: Putnam | J6: Rockland | K6: Sullivan | L6: Ulster | M6: Westchester | N6: NYS excl NYC | O6: NYS
F7: 2018 | G7: 49 | H7: 49 | I7: 38 | J7: 32 | K7: 75 | L7: 50 | M7: 27 | N7: 41 | O7: 34
F8: 2019 | G8: 52 | H8: 49 | I8: 34 | J8: 36 | K8: 82 | L8: 57 | M8: 28 | N8: 40 | O8: 34
A9: Figure Rules | F9: 2020 | G9: 52 | H9: 50 | I9: 36 | J9: 39 | K9: 85 | L9: 59 | M9: 30 | N9: 47 | O9: 41
A10: Figure Type | B10: Line | F10: 2021 | G10: 59 | H10: 56 | I10: 41 | J10: 38 | K10: 92 | L10: 64 | M10: 32 | N10: 52 | O10: 47
A11: X Column | B11: Year
A12: Y Column | B12: Rate per 100,000
A13: X Axis Title | B13: Year
A14: Y Axis Title | B14: Rate per 100,000
A15: Start at Zero | B15: FALSE
A18: Source Specifications
A19: Table ID | B19: NYS Community Health Indicator Reports Dashboard
A20: URL | B20: https://apps.health.ny.gov/public/tabvis/PHIG_Public/chirs/reports/#county
A21: Data Year | B21: 2021
A22: Estimate Type
A23: Citation Month | B23: May
A24: Citation Year | B24: 2025
A25: Custom Text | B25: Source: NYS Community Health Indicator Reports Dashboard , May 2025 sourced from Vital Statistics of NYS https://apps.health.ny.gov/public/tabvis/PHIG_Public/chirs/reports/#county
A27: Note Specfications
A29: Note: Three-year averages are used for counties and single-year rates are used for NYS and NYS excluding NYC. Y-axis does not begin at zero in order to clearly display trend lines. The ICD-10 codes for unintentional injury are: V01-X59, Y85-Y86.

Sheet Poison Control Calls
A1: Name | B1: Poison Center Calls, Rate per 100,000, 2020–2024
A2: Table/Figure/Both | B2: Both
A3: Object ID | B3: =IF($B$1="","",_xlfn.XLOOKUP($B$1,Master!$F$2:$F$308,Master!$G$2:$G$308,""))
A4: Figure ID | B4: =IF($B$1="","",_xlfn.XLOOKUP($B$1,Master!$F$2:$F$308,Master!$H$2:$H$308,"")) | F4: number | G4: number | H4: number | I4: number | J4: number | K4: number | L4: number | M4: number
A5: Table Rules | E5: Enter Data | G5: Dutchess | H5: Orange | I5: Putnam | J5: Rockland | K5: Sullivan | L5: Ulster | M5: Westchester
A6: Multilevel Headers | B6: FALSE | F6: 2020 | G6: 541 | H6: 604 | I6: 237 | J6: 431 | K6: 583 | L6: 609 | M6: 497
F7: 2021 | G7: 421 | H7: 593 | I7: 220 | J7: 456 | K7: 589 | L7: 494 | M7: 441
F8: 2022 | G8: 436 | H8: 613 | I8: 222 | J8: 470 | K8: 542 | L8: 446 | M8: 408
A9: Figure Rules | F9: 2023 | G9: 443 | H9: 573 | I9: 230 | J9: 399 | K9: 642 | L9: 444 | M9: 404
A10: Figure Type | B10: Clustered Bar | F10: 2024 | G10: 464 | H10: 570 | I10: 226 | J10: 366 | K10: 636 | L10: 530 | M10: 388
A11: X Column | B11: County
A12: Y Column | B12: Rate
A13: X Axis Title
A14: Y Axis Title | B14: Rate per 100,000
A15: Start at Zero | B15: TRUE
A18: Source Specifications
A19: Table ID | B19: Data request from Upstate NY Poison Center and NYC Poison Center
A20: URL
A21: Data Year | B21: 2020-2024
A22: Estimate Type
A23: Citation Month | B23: May
A24: Citation Year | B24: 2025
A25: Custom Text | B25: Source: Data request from Upstate NY Poison Center and NYC Poison Center, May 2025
A27: Note Specfications
A29: Rates calculated using population estimates from U.S. Census Bureau’s 2023 American Community Survey (ACS) 5-Year Estimate, Table B01003.

Sheet Poison Control Calls Child
A1: Name | B1: Poison Center Calls, Percentage Children 5 Years Old and Younger, 2020–2024
A2: Table/Figure/Both | B2: Both
A3: Object ID | B3: =IF($B$1="","",_xlfn.XLOOKUP($B$1,Master!$F$2:$F$308,Master!$G$2:$G$308,""))
A4: Figure ID | B4: =IF($B$1="","",_xlfn.XLOOKUP($B$1,Master!$F$2:$F$308,Master!$H$2:$H$308,"")) | F4: number | G4: percent1 | H4: percent1 | I4: percent1 | J4: percent1 | K4: percent1 | L4: percent1 | M4: percent1
A5: Table Rules | E5: Enter Data | G5: Dutchess | H5: Orange | I5: Putnam | J5: Rockland | K5: Sullivan | L5: Ulster | M5: Westchester
A6: Multilevel Headers | B6: FALSE | F6: 2020 | G6: 29.7 | H6: 30.9 | I6: 20.1 | J6: 32.7 | K6: 34.6 | L6: 31.1 | M6: 34.6
F7: 2021 | G7: 30.9 | H7: 33.4 | I7: 26.4 | J7: 36.1 | K7: 30.4 | L7: 30.2 | M7: 34.2
F8: 2022 | G8: 31.9 | H8: 35.8 | I8: 26.7 | J8: 36.8 | K8: 34 | L8: 30.3 | M8: 33.8
A9: Figure Rules | F9: 2023 | G9: 32.6 | H9: 40.5 | I9: 26.7 | J9: 41.3 | K9: 32.7 | L9: 28.8 | M9: 33.8
A10: Figure Type | B10: Clustered Bar | F10: 2024 | G10: 30.6 | H10: 38.5 | I10: 28.5 | J10: 38.4 | K10: 30.8 | L10: 29 | M10: 31.6
A11: X Column | B11: County
A12: Y Column | B12: % of total calls
A13: X Axis Title
A14: Y Axis Title | B14: % of total calls
A15: Start at Zero | B15: TRUE
A18: Source Specifications
A19: Table ID | B19: Data request from Upstate NY Poison Center and NYC Poison Center
A20: URL
A21: Data Year | B21: 2020-2024
A22: Estimate Type
A23: Citation Month | B23: May
A24: Citation Year | B24: 2025
A25: Custom Text | B25: Source: Data request from Upstate NY Poison Center and NYC Poison Center, May 2025
A27: Note Specfications

Sheet Poison Control Calls Cannabis
A1: Name | B1: Poison Center Cannabis Calls, Rate per 100,000 Population, 2020–2024
A2: Table/Figure/Both | B2: Both
A3: Object ID | B3: =IF($B$1="","",_xlfn.XLOOKUP($B$1,Master!$F$2:$F$308,Master!$G$2:$G$308,"")) -> tbl-poison-control-cannabis
A4: Figure ID | B4: =IF($B$1="","",_xlfn.XLOOKUP($B$1,Master!$F$2:$F$308,Master!$H$2:$H$308,"")) -> fig-poison-control-cannabis | F4: number | G4: number | H4: number | I4: number | J4: number | K4: number | L4: number | M4: number
A5: Table Rules | E5: Enter Data | G5: Dutchess | H5: Orange | I5: Putnam | J5: Rockland | K5: Sullivan | L5: Ulster | M5: Westchester
A6: Multilevel Headers | B6: FALSE | F6: 2020 | G6: 1.4 | H6: 5.8 | I6: 2 | J6: 2.2 | K6: 0 | L6: 1.7 | M6: 5.5
F7: 2021 | G7: 3 | H7: 5.3 | I7: 2 | J7: 1.8 | K7: 10.2 | L7: 3.3 | M7: 7.1
F8: 2022 | G8: 5.1 | H8: 7.7 | I8: 3.1 | J8: 3.6 | K8: 7.6 | L8: 2.7 | M8: 6.4
A9: Figure Rules | F9: 2023 | G9: 5 | H9: 5.7 | I9: 3.14 | J9: 2.4 | K9: 8.8 | L9: 1.1 | M9: 6.7
A10: Figure Type | B10: Clustered Bar | F10: 2024 | G10: 5.7 | H10: 6.7 | I10: 2 | J10: 1.8 | K10: 8.8 | L10: 3.3 | M10: 5.9
A11: X Column | B11: County
A12: Y Column | B12: Rate
A13: X Axis Title
A14: Y Axis Title | B14: Rate per 100,000
A15: Start at Zero | B15: TRUE
A18: Source Specifications
A19: Table ID | B19: Data request from Upstate NY Poison Center and NYC Poison Center
A20: URL
A21: Data Year | B21: 2020-2024
A22: Estimate Type
A23: Citation Month | B23: May
A24: Citation Year | B24: 2025
A25: Custom Text | B25: Source: Data request from Upstate NY Poison Center and NYC Poison Center, May 2025
A27: Note Specfications
A29: Note: Rates calculated using population estimates from U.S. Census Bureau’s 2023 American Community Survey (ACS) 5-Year Estimate, Table B01003.

Sheet MV Injury Mortality
A1: Name | B1: Motor Vehicle Injury Mortality, Rate per 100,000 Population, 2018–2021
A2: Table/Figure/Both | B2: Both
A3: Object ID | B3: =IF($B$1="","",_xlfn.XLOOKUP($B$1,Master!$F$2:$F$308,Master!$G$2:$G$308,"")) -> tbl-mva-mortal-rate
A4: Figure ID | B4: =IF($B$1="","",_xlfn.XLOOKUP($B$1,Master!$F$2:$F$308,Master!$H$2:$H$308,"")) -> fig-mva-mortal-rate | F4: integer | G4: percent1 | H4: percent1 | I4: percent1 | J4: percent1 | K4: percent1 | L4: percent1 | M4: percent1 | N4: percent1 | O4: percent1
A5: Table Rules | E5: Enter Data | G5: Three Year Average | N5: Single Year
A6: Multilevel Headers | B6: TRUE | G6: Dutchess | H6: Orange | I6: Putnam | J6: Rockland | K6: Sullivan | L6: Ulster | M6: Westchester | N6: NYS excl NYC | O6: NYS
F7: 2018 | G7: 8.2 | H7: 9 | I7: 3.7 | J7: 4.7 | K7: 13.3 | L7: 8.4 | M7: 3.4 | N7: 7 | O7: 5.3
F8: 2019 | G8: 9.2 | H8: 7.9 | I8: 4.7 | J8: 4.5 | K8: 12.4 | L8: 9.5 | M8: 3.7 | N8: 7.1 | O8: 5.5
A9: Figure Rules | F9: 2020 | G9: 8.8 | H9: 8.2 | I9: 5.4 | J9: 5.1 | K9: 12.6 | L9: 10.9 | M9: 4.2 | N9: 7.6 | O9: 6
A10: Figure Type | B10: Line | F10: 2021 | G10: 9.9 | H10: 8.3 | I10: 7.8 | J10: 5.7 | K10: 14.9 | L10: 10.7 | M10: 4.5 | N10: 8.5 | O10: 6.7
A11: X Column | B11: Period
A12: Y Column | B12: Rate per 100,000
A13: X Axis Title
A14: Y Axis Title | B14: Rate per 100,000
A15: Start at Zero | B15: TRUE
A18: Source Specifications
A19: Table ID | B19: NYS Community Health Indicator Reports Dashboard
A20: URL | B20: https://apps.health.ny.gov/public/tabvis/PHIG_Public/chirs/reports/#county
A21: Data Year | B21: 2018-2021
A22: Estimate Type
A23: Citation Month | B23: May
A24: Citation Year | B24: 2025
A25: Custom Text | B25: Source: NYS Community Health Indicator Reports Dashboard , May 2025 sourced from Vital Statistics of NYS https://apps.health.ny.gov/public/tabvis/PHIG_Public/chirs/reports/#county
A27: Note Specfications
A29: Note: Three-year averages are used for counties and single-year rates are used for NYS and NYS excluding NYC. The ICD-10 codes for motor vehicle related injuries are: V02-V04, V09.0, V09.2, V12-V14, V19.0-V19.2, V19.4-V19.6, V20-V79, V80.3-V80.5, V81.0- V81.1, V82.0-V82.1, V83-V86, V87.0-V87.8, V88.0-V88.8,V89.0,V89.2.

Sheet Alcohol MV Injury Mortality
A1: Name | B1: Alcohol Related Motor Vehicle Injuries and Deaths, Crude Rate per 100,000 Population, 2018–2021
A2: Table/Figure/Both | B2: Both
A3: Object ID | B3: =IF($B$1="","",_xlfn.XLOOKUP($B$1,Master!$F$2:$F$308,Master!$G$2:$G$308,"")) -> tbl-mva-alcohol-injury-death-crude
A4: Figure ID | B4: =IF($B$1="","",_xlfn.XLOOKUP($B$1,Master!$F$2:$F$308,Master!$H$2:$H$308,"")) -> fig-mva-alcohol-injury-death-crude | F4: integer | G4: percent1 | H4: percent1 | I4: percent1 | J4: percent1 | K4: percent1 | L4: percent1 | M4: percent1 | N4: percent1 | O4: percent1
A5: Table Rules | E5: Enter Data | G5: Three Year Average | N5: Single Year
A6: Multilevel Headers | B6: TRUE | G6: Dutchess | H6: Orange | I6: Putnam | J6: Rockland | K6: Sullivan | L6: Ulster | M6: Westchester | N6: NYS excl NYC | O6: NYS
F7: 2018 | G7: 35.2 | H7: 34.9 | I7: 44.2 | J7: 29.2 | K7: 50.1 | L7: 44.8 | M7: 28.9 | N7: 35.1 | O7: 28.8
F8: 2019 | G8: 33.9 | H8: 34.2 | I8: 37.1 | J8: 29 | K8: 39.8 | L8: 43.1 | M8: 26.6 | N8: 33.5 | O8: 27.6
A9: Figure Rules | F9: 2020 | G9: 32.5 | H9: 34.4 | I9: 33.1 | J9: 27.9 | K9: 31.2 | L9: 42 | M9: 24.1 | N9: 28.6 | O9: 23
A10: Figure Type | B10: Line | F10: 2021 | G10: 31.7 | H10: 38.7 | I10: 28.1 | J10: 27.1 | K10: 36.6 | L10: 40.2 | M10: 22.5 | N10: 31.4 | O10: 25.4
A11: X Column | B11: Period
A12: Y Column | B12: Rate per 100,000
A13: X Axis Title
A14: Y Axis Title | B14: Rate per 100,000
A15: Start at Zero | B15: FALSE
A18: Source Specifications
A19: Table ID | B19: NYS Community Health Indicator Reports Dashboard
A20: URL | B20: https://apps.health.ny.gov/public/tabvis/PHIG_Public/chirs/reports/#county
A21: Data Year | B21: 2018-2021
A22: Estimate Type
A23: Citation Month | B23: May
A24: Citation Year | B24: 2025
A25: Custom Text | B25: Source: NYS Community Health Indicator Reports Dashboard , May 2025 sourced from Vital Statistics of NYS https://apps.health.ny.gov/public/tabvis/PHIG_Public/chirs/reports/#county
A27: Note Specfications
A29: Note: Three-year averages are used for counties and single-year rates are used for NYS and NYS excluding NYC. Y-axis does not begin at zero in order to clearly display trend lines. Data include persons killed or injured in motor vehicle crashes where alcohol was considered to be a factor. It also includes pedestrians, bicyclists and all other non-vehicle involved persons as well as vehicle occupants. These data were gathered from police reports. Crashes are reported by the county where the event occurred.

Sheet MV Injury Mortaltiy RE
A1: Name | B1: Motor Vehicle Related Mortality, Age-Adjusted Rate per 100,000 Population by Race and Ethnicity, 2020–2022
A2: Table/Figure/Both | B2: Both
A3: Object ID | B3: =IF($B$1="","",_xlfn.XLOOKUP($B$1,Master!$F$2:$F$308,Master!$G$2:$G$308,"")) -> tbl-mva-mortal-rande-aar
A4: Figure ID | B4: =IF($B$1="","",_xlfn.XLOOKUP($B$1,Master!$F$2:$F$308,Master!$H$2:$H$308,"")) -> fig-mva-mortal-rande-aar | G4: percent1 | H4: percent1 | I4: percent1 | J4: percent1 | K4: percent1 | L4: percent1 | M4: percent1 | N4: percent1 | O4: percent1
A5: Table Rules | E5: Enter Data | G5: Three-Year Average | N5: Single-Year
A6: Multilevel Headers | B6: FALSE | G6: Dutchess | H6: Orange | I6: Putnam | J6: Rockland | K6: Sullivan | L6: Ulster | M6: Westchester | N6: NYS excl NYC | O6: NYS
F7: Non-Hispanic White | G7: 10.1 | H7: 5.8 | I7: 2 | J7: 2.2 | K7: 0 | L7: 1.7 | M7: 5.5 | N7: 7.6 | O7: 6.3
F8: Non-Hispanic Black | G8: 6.3* | H8: 5.3 | I8: 2 | J8: 1.8 | K8: 10.2 | L8: 3.3 | M8: 7.1 | N8: 9.7 | O8: 6.6
A9: Figure Rules | F9: Non-Hispanic Asian/Pacific Islander | G9: 5.8* | H9: 7.7 | I9: 3.1 | J9: 3.6 | K9: 7.6 | L9: 2.7 | M9: 6.4 | N9: 3.4 | O9: 2.7
A10: Figure Type | B10: Clustered Bar | F10: Hispanic | G10: 8 | H10: 5.7 | I10: 3.14 | J10: 2.4 | K10: 8.8 | L10: 1.1 | M10: 6.7 | N10: 8.7 | O10: 5.9
A11: X Column | B11: Group | F11: Total | G11: 9.4 | H11: 6.7 | I11: 2 | J11: 1.8 | K11: 8.8 | L11: 3.3 | M11: 5.9 | N11: 8 | O11: 6.2
A12: Y Column | B12: Rate per 100,000
A13: X Axis Title
A14: Y Axis Title | B14: Rate per 100,000
A15: Start at Zero | B15: TRUE
A18: Source Specifications
A19: Table ID | B19: NYS County Health Indicators by Race and Ethnicity Dashboard
A20: URL | B20: https://www.health.ny.gov/community/health_equity/reports/county/
A21: Data Year | B21: 2020-2022
A22: Estimate Type
A23: Citation Month | B23: May
A24: Citation Year | B24: 2025
A25: Custom Text | B25: Source: NYS County Health Indicators by Race and Ethnicity Dashboard, May 2025 sourced from Vital Statistics of NYS https://www.health.ny.gov/community/health_equity/reports/county/
A27: Note Specfications
A29: *: The rate is unstable. Note: This indicator includes deaths with motor vehicle related as the primary cause of death. The ICD-10 codes for motor vehicle related injuries are: V02-V04, V09.0, V09.2, V12-V14, V19.0-V19.2, V19.4-V19.6, V20-V79, V80.3-V80.5, V81.0-V81.1, V82.0-V82.1, V83-V86, V87.0-V87.8, V88.0-V88.8,V89.0,V89.2.

Sheet Falls Hospitalization
A1: Name | B1: Falls Hospitalization, Age-Adjusted Rate per 10,000 Population, 2018–2021
A2: Table/Figure/Both | B2: Both
A3: Object ID | B3: =IF($B$1="","",_xlfn.XLOOKUP($B$1,Master!$F$2:$F$308,Master!$G$2:$G$308,"")) -> tbl-falls-hospital-aar
A4: Figure ID | B4: =IF($B$1="","",_xlfn.XLOOKUP($B$1,Master!$F$2:$F$308,Master!$H$2:$H$308,"")) -> fig-falls-hospital-aar | F4: number | G4: percent1 | H4: percent1 | I4: percent1 | J4: percent1 | K4: percent1 | L4: percent1 | M4: percent1 | N4: percent1 | O4: percent1
A5: Table Rules | E5: Enter Data | G5: Three Year Average | N5: Single Year
A6: Multilevel Headers | B6: TRUE | G6: Dutchess | H6: Orange | I6: Putnam | J6: Rockland | K6: Sullivan | L6: Ulster | M6: Westchester | N6: NYS excl NYC | O6: NYS
F7: 2018 | G7: 34.6 | H7: 39.8 | I7: 29.2 | J7: 30.9 | K7: 33.8 | L7: 39.6 | M7: 31.8 | N7: 37.6 | O7: 35.1
F8: 2019 | G8: 35.1 | H8: 39.8 | I8: 29.3 | J8: 30.4 | K8: 35.3 | L8: 40 | M8: 33 | N8: 38 | O8: 36.4
A9: Figure Rules | F9: 2020 | G9: 35.3 | H9: 39.4 | I9: 28.6 | J9: 29.4 | K9: 36.2 | L9: 39.7 | M9: 34.1 | N9: 35.2 | O9: 34.1
A10: Figure Type | B10: Line | F10: 2021 | G10: 36.5 | H10: 39.9 | I10: 27.8 | J10: 29.6 | K10: 39.9 | L10: 39.3 | M10: 33.6 | N10: 38 | O10: 36.4
A11: X Column | B11: Period
A12: Y Column | B12: Rate per 10,000
A13: X Axis Title
